Workbook

Sheet 17 Lists
A1: Dropdown Lists
A2: Controlled vocabulary used throughout the workbook. Edit these lists if the client or firm uses different categories.
A4: Owner | B4: Record Status | C4: Asset Type | D4: Liquidity | E4: Allocation Category | F4: Tax Registration | G4: Priority | H4: Liability Type | I4: Yes / No | J4: Cash Flow Type | K4: Frequency | L4: Goal Area | M4: Policy Type | N4: Estate Status | O4: Document Category | P4: Action Status | Q4: Filing Status | R4: Taxability | S4: Benefit Type | T4: Retirement Source Type | U4: Need Analysis Status | V4: Beneficiary Status
A5: Household | B5: Active | C5: Cash / Bank | D5: Immediate | E5: Cash | F5: Individual | G5: High | H5: Mortgage | I5: Yes | J5: Income | K5: Weekly | L5: Retirement | M5: Life | N5: Complete | O5: Tax | P5: Not Started | Q5: Single | R5: Taxable | S5: 401(k) / 403(b) | T5: Social Security | U5: Adequate | V5: Current
A6: Primary Client | B6: Pending | C6: Taxable Investment | D6: Short-term | E6: Equities | F6: Joint | G6: Medium | H6: HELOC | I6: No | J6: Expense | K6: Biweekly | L6: Education | M6: Disability | N6: Needs Drafting | O6: Income | P6: In Progress | Q6: Married Filing Jointly | R6: Partially Taxable | S6: Pension | T6: Pension | U6: Review Needed | V6: Needs Review
A7: Co-Client / Spouse | B7: Review | C7: Traditional Retirement | D7: Long-term | E7: Fixed Income | F7: Community Property | G7: Low | H7: Auto Loan | I7: TBD | K7: Monthly | L7: Home | M7: Long-Term Care | N7: Needs Update | O7: Investments | P7: Waiting on Client | Q7: Married Filing Separately | R7: Tax-Free | S7: HSA | T7: Annuity | U7: Gap Identified | V7: Missing
A8: Joint | B8: Closed | C8: Roth Retirement | D8: Illiquid | E8: Real Estate | F8: Revocable Trust | H8: Student Loan | K8: Quarterly | L8: Major Purchase | M8: Health | N8: Not Started | O8: Retirement | P8: Waiting on Advisor | Q8: Head of Household | R8: Pre-Tax | S8: FSA | T8: Retirement Account Withdrawal | U8: Quote Pending | V8: Not Applicable
A9: Trust | B9: Inactive | C9: HSA | E9: Alternatives | F9: Irrevocable Trust | H9: Credit Card | K9: Annual | L9: Debt Paydown | M9: Auto | N9: Unknown | O9: Insurance | P9: Complete | Q9: Qualifying Surviving Spouse | R9: After-Tax | S9: Deferred Compensation | T9: Rental Income | U9: Declined
A10: Business | B10: N/A | C10: 529 / Education | E10: Business | F10: Traditional IRA | H10: Personal Loan | K10: One-Time | L10: Legacy | M10: Homeowners | O10: Debt | P10: Deferred | R10: Unknown | S10: Stock Options / RSUs | T10: Business Income | U10: Unknown
A11: Child | C11: Real Estate | E11: Other | F11: Roth IRA | H11: Business Debt | L11: Emergency Fund | M11: Umbrella | O11: Estate | S11: Health Insurance | T11: Part-Time Work
A12: Other | C12: Business Interest | F12: 401(k) / 403(b) | H12: Tax Debt | L12: Tax | M12: Business | O12: Real Estate | S12: Disability | T12: Other
C13: Personal Property | F13: SEP / SIMPLE | H13: Other Liability | L13: Insurance | M13: Other | O13: Business | S13: Life Insurance
C14: Alternative / Crypto | F14: HSA | L14: Other | O14: Benefits | S14: LTC
C15: Other Asset | F15: 529 | O15: Identity | S15: Other
F16: UTMA / UGMA | O16: Other
F17: Business
F18: Other

Sheet 00 README
A1: CFP Client Planning Data Workbook
A2: Use this workbook as a secure planning intake and ongoing update file. Yellow cells are inputs; green cells are formulas or calculated outputs.
A4: Topic | B4: Guidance
A5: Purpose | B5: This workbook captures the client data a CFP professional typically needs to guide household financial planning: profile, goals, cash flow, assets, liabilities, insurance, taxes, retirement, benefits, estate, beneficiaries, documents, and action items.
A6: How to use | B6: Start with Client Profile, Assumptions, Documents, Assets, Liabilities, and Cash Flow. Mark rows Active when they should be included in dashboard totals.
A7: Privacy | B7: Avoid storing full Social Security numbers or full account numbers. Use last four digits only. Store the file securely and do not transmit it through unsecured channels.
A8: Review cadence | B8: Update values before each planning meeting, major life event, job change, tax filing, estate update, refinance, or insurance renewal.
A9: Advisor workflow | B9: Use the Data Map and Documents tabs as intake checklists. Use the Action Plan tab for recommendations, owner, due date, and follow-up status.
A10: Customization | B10: The Lists tab powers dropdowns. Customize categories to match your planning process, CRM, or financial planning software.

Sheet Retirement Projection
A1: Year | B1: Age | C1: Beginning | D1: Growth | E1: Social Security | F1: Annual Expenses | G1: Gross Withdrawal | H1: MAGI | I1: 0%cap gain | J1: Real AGI | K1: Taxes (Fec/CA) | L1: Ending Balance | M1: Use of Cost basis | N1: Cap G 0% | O1: Cap G 15% | P1: HSA Contribution | Q1: MAGI CC limit | R1: Mortgage | S1: Home Value | U1: Networth | Y1: MAGI only allows the deduction of, HSA, Student Loans, Capital Gains Losses. No Standard deduction or itemized count
A2: 2027 | B2: ='03 Client Profile'!$D$5 + (A2 - YEAR('02 Assumptions'!$B$16)) -> 37 | C2: ='01 Dashboard'!$E$6 + '01 Dashboard'!$E$9 + '01 Dashboard'!$E$10 -> 2912398 | D2: =C2 * $Z$43 -> 145619.9 | E2: =IF(B2>=67, '18 Social Security'!$G$5 * (1 + '02 Assumptions'!$B$5)^(B2 - '03 Client Profile'!$D$5), 0) -> 0 | F2: {=MAP(A2:A50540, LAMBDA(y, IF(y="",, SUMIFS('05 Cash Flow'!G:G, '05 Cash Flow'!A:A, "Expense") * (1 + '02 Assumptions'!B5)^(y - 2026))))} -> 169380.67 | G2: =F2 -> 169380.67 | H2: =G2-P2-M2 -> 158884.01 | I2: =H2-N2 -> 108394.01 | J2: =H2-N2-AB48-AE47 -> 72515.286 | K2: =J2 * 0.15 + SUMPRODUCT(--(J2 > {0, 11079, 26264, 41452, 57542, 72724, 371479, 445771, 742953}), (J2 - {0, 11079, 26264, 41452, 57542, 72724, 371479, 445771, 742953}), {0.01, 0.01, 0.02, 0.02, 0.02, 0.013, 0.01, 0.01, 0.01}) -> 14062.566 | L2: =C2 + D2 - G2-K2 -> 2874574.7 | M2: =AD42 -> 5996.6632 | N2: =49500 * (1 + $Z$47)^($A2-2026) -> 50490 | O2: 0 | P2: =4500*(1+$Z$47)^(A2-2027)+IF(B2>=55,1000,0) -> 4500 | Q2: =62600*(1+$Z$47)^(A2-2026) -> 63852 | R2: =PV($AD$50 / 12, 12*$AE$50, -$AF$50) -> 372138.39 | S2: 1000000 | U2: =S2+L2-R2 -> 3502436.3 | Y2: AGI counts itemized and standard deductions.
A3: =A2+1 -> 2028 | B3: =B2+1 -> 38 | C3: =L2 -> 2874574.7 | D3: =C3 * $Z$43 -> 143728.73 | E3: =IF(B3>=67, '18 Social Security'!$G$5 * (1 + '02 Assumptions'!$B$5)^(B3 - '03 Client Profile'!$D$5), 0) -> 0 | F3: 172768.28 | G3: =F3 -> 172768.28 | H3: =G3-P3-M3 -> 162181.62 | I3: =H3-49450-$AD$42-$AE$47-$AB$48 -> 70856.237 | J3: =I3-M3 -> 64859.573 | K3: =J3 * 0.15 + SUMPRODUCT(--(J3 > {0, 11079, 26264, 41452, 57542, 72724, 371479, 445771, 742953}), (J3 - {0, 11079, 26264, 41452, 57542, 72724, 371479, 445771, 742953}), {0.01, 0.01, 0.02, 0.02, 0.02, 0.013, 0.01, 0.01, 0.01}) -> 12301.752 | L3: =C3 + D3 - G3-K3 -> 2833233.4 | M3: =M2 -> 5996.6632 | N3: =49500 * (1 + $Z$47)^($A3-2026) -> 51499.8 | O3: 0 | P3: =4500*(1+$Z$47)^(A3-2027)+IF(B3>=55,1000,0) -> 4590 | Q3: =62600*(1+$Z$47)^(A3-2026) -> 65129.04 | R3: =PV($AD$50 / 12, 12*($AE$50-ROW(R1)), -$AF$50) -> 367002.39 | S3: =S2*1.03 -> 1030000 | U3: =S3+L3-R3 -> 3496231
A4: =A3+1 -> 2029 | B4: =B3+1 -> 39 | C4: =L3 -> 2833233.4 | D4: =C4 * $Z$43 -> 141661.67 | E4: =IF(B4>=67, '18 Social Security'!$G$5 * (1 + '02 Assumptions'!$B$5)^(B4 - '03 Client Profile'!$D$5), 0) -> 0 | F4: 176223.65 | G4: =F4 -> 176223.65 | H4: =G4-P4-M4 -> 165545.19 | I4: =H4-49450-$AD$42-$AE$47-$AB$48 -> 74219.802 | J4: =I4-M4 -> 68223.139 | K4: =J4 * 0.15 + SUMPRODUCT(--(J4 > {0, 11079, 26264, 41452, 57542, 72724, 371479, 445771, 742953}), (J4 - {0, 11079, 26264, 41452, 57542, 72724, 371479, 445771, 742953}), {0.01, 0.01, 0.02, 0.02, 0.02, 0.013, 0.01, 0.01, 0.01}) -> 13075.372 | L4: =C4 + D4 - G4-K4 -> 2785596 | M4: =M3 -> 5996.6632 | N4: =49500 * (1 + $Z$47)^($A4-2026) -> 52529.796 | O4: 0 | P4: =4500*(1+$Z$47)^(A4-2027)+IF(B4>=55,1000,0) -> 4681.8 | Q4: =62600*(1+$Z$47)^(A4-2026) -> 66431.621 | R4: =PV($AD$50 / 12, 12*($AE$50-ROW(R2)), -$AF$50) -> 361563.17 | S4: =S3*1.03 -> 1060900 | U4: =S4+L4-R4 -> 3484932.8
A5: =A4+1 -> 2030 | B5: =B4+1 -> 40 | C5: =L4 -> 2785596 | D5: =C5 * $Z$43 -> 139279.8 | E5: =IF(B5>=67, '18 Social Security'!$G$5 * (1 + '02 Assumptions'!$B$5)^(B5 - '03 Client Profile'!$D$5), 0) -> 0 | F5: 179748.12 | G5: =F5 -> 179748.12 | H5: =G5-P5-M5 -> 168976.02 | I5: =H5-49450-$AD$42-$AE$47-$AB$48 -> 77650.639 | J5: =I5-M5 -> 71653.976 | K5: =J5 * 0.15 + SUMPRODUCT(--(J5 > {0, 11079, 26264, 41452, 57542, 72724, 371479, 445771, 742953}), (J5 - {0, 11079, 26264, 41452, 57542, 72724, 371479, 445771, 742953}), {0.01, 0.01, 0.02, 0.02, 0.02, 0.013, 0.01, 0.01, 0.01}) -> 13864.464 | L5: =C5 + D5 - G5-K5 -> 2731263.2 | M5: =M4 -> 5996.6632 | N5: =49500 * (1 + $Z$47)^($A5-2026) -> 53580.392 | O5: 0 | P5: =4500*(1+$Z$47)^(A5-2027)+IF(B5>=55,1000,0) -> 4775.436 | Q5: =62600*(1+$Z$47)^(A5-2026) -> 67760.253 | R5: =PV($AD$50 / 12, 12*($AE$50-ROW(R3)), -$AF$50) -> 355802.82 | S5: =S4*1.03 -> 1092727 | U5: =S5+L5-R5 -> 3468187.4
A6: =A5+1 -> 2031 | B6: =B5+1 -> 41 | C6: =L5 -> 2731263.2 | D6: =C6 * $Z$43 -> 136563.16 | E6: =IF(B6>=67, '18 Social Security'!$G$5 * (1 + '02 Assumptions'!$B$5)^(B6 - '03 Client Profile'!$D$5), 0) -> 0 | F6: 183343.08 | G6: =F6 -> 183343.08 | H6: =G6-P6-M6 -> 172475.48 | I6: =H6-49450-$AD$42-$AE$47-$AB$48 -> 81150.093 | J6: =I6-M6 -> 75153.43 | K6: =J6 * 0.15 + SUMPRODUCT(--(J6 > {0, 11079, 26264, 41452, 57542, 72724, 371479, 445771, 742953}), (J6 - {0, 11079, 26264, 41452, 57542, 72724, 371479, 445771, 742953}), {0.01, 0.01, 0.02, 0.02, 0.02, 0.013, 0.01, 0.01, 0.01}) -> 14700.921 | L6: =C6 + D6 - G6-K6 -> 2669782.4 | M6: =M5 -> 5996.6632 | N6: =49500 * (1 + $Z$47)^($A6-2026) -> 54652 | O6: 0 | P6: =4500*(1+$Z$47)^(A6-2027)+IF(B6>=55,1000,0) -> 4870.9447 | Q6: =62600*(1+$Z$47)^(A6-2026) -> 69115.458 | R6: =PV($AD$50 / 12, 12*($AE$50-ROW(R4)), -$AF$50) -> 349702.37 | S6: =S5*1.03 -> 1125508.8 | U6: =S6+L6-R6 -> 3445588.8
A7: =A6+1 -> 2032 | B7: =B6+1 -> 42 | C7: =L6 -> 2669782.4 | D7: =C7 * $Z$43 -> 133489.12 | E7: =IF(B7>=67, '18 Social Security'!$G$5 * (1 + '02 Assumptions'!$B$5)^(B7 - '03 Client Profile'!$D$5), 0) -> 0 | F7: 187009.95 | G7: =F7 -> 187009.95 | H7: =G7-P7-M7 -> 176044.92 | I7: =H7-49450-$AD$42-$AE$47-$AB$48 -> 84719.536 | J7: =I7-M7 -> 78722.872 | K7: =J7 * 0.15 + SUMPRODUCT(--(J7 > {0, 11079, 26264, 41452, 57542, 72724, 371479, 445771, 742953}), (J7 - {0, 11079, 26264, 41452, 57542, 72724, 371479, 445771, 742953}), {0.01, 0.01, 0.02, 0.02, 0.02, 0.013, 0.01, 0.01, 0.01}) -> 15568.296 | L7: =C7 + D7 - G7-K7 -> 2600693.2 | M7: =M6 -> 5996.6632 | N7: =49500 * (1 + $Z$47)^($A7-2026) -> 55745.04 | O7: 0 | P7: =4500*(1+$Z$47)^(A7-2027)+IF(B7>=55,1000,0) -> 4968.3636 | Q7: =62600*(1+$Z$47)^(A7-2026) -> 70497.767 | R7: =PV($AD$50 / 12, 12*($AE$50-ROW(R5)), -$AF$50) -> 343241.76 | S7: =S6*1.03 -> 1159274.1 | U7: =S7+L7-R7 -> 3416725.6
A8: =A7+1 -> 2033 | B8: =B7+1 -> 43 | C8: =L7 -> 2600693.2 | D8: =C8 * $Z$43 -> 130034.66 | E8: =IF(B8>=67, '18 Social Security'!$G$5 * (1 + '02 Assumptions'!$B$5)^(B8 - '03 Client Profile'!$D$5), 0) -> 0 | F8: 190750.14 | G8: =F8 -> 190750.14 | H8: =G8-P8-M8 -> 179685.75 | I8: =H8-49450-$AD$42-$AE$47-$AB$48 -> 88360.367 | J8: =I8-M8 -> 82363.704 | K8: =J8 * 0.15 + SUMPRODUCT(--(J8 > {0, 11079, 26264, 41452, 57542, 72724, 371479, 445771, 742953}), (J8 - {0, 11079, 26264, 41452, 57542, 72724, 371479, 445771, 742953}), {0.01, 0.01, 0.02, 0.02, 0.02, 0.013, 0.01, 0.01, 0.01}) -> 16453.018 | L8: =C8 + D8 - G8-K8 -> 2523524.7 | M8: =M7 -> 5996.6632 | N8: =49500 * (1 + $Z$47)^($A8-2026) -> 56859.941 | O8: 0 | P8: =4500*(1+$Z$47)^(A8-2027)+IF(B8>=55,1000,0) -> 5067.7309 | Q8: =62600*(1+$Z$47)^(A8-2026) -> 71907.723 | R8: =PV($AD$50 / 12, 12*($AE$50-ROW(R6)), -$AF$50) -> 336399.71 | S8: =S7*1.03 -> 1194052.3 | U8: =S8+L8-R8 -> 3381177.3
A9: =A8+1 -> 2034 | B9: =B8+1 -> 44 | C9: =L8 -> 2523524.7 | D9: =C9 * $Z$43 -> 126176.24 | E9: =IF(B9>=67, '18 Social Security'!$G$5 * (1 + '02 Assumptions'!$B$5)^(B9 - '03 Client Profile'!$D$5), 0) -> 0 | F9: 194565.15 | G9: =F9 -> 194565.15 | H9: =G9-P9-M9 -> 183399.4 | I9: =H9-49450-$AD$42-$AE$47-$AB$48 -> 92074.016 | J9: =I9-M9 -> 86077.352 | K9: =J9 * 0.15 + SUMPRODUCT(--(J9 > {0, 11079, 26264, 41452, 57542, 72724, 371479, 445771, 742953}), (J9 - {0, 11079, 26264, 41452, 57542, 72724, 371479, 445771, 742953}), {0.01, 0.01, 0.02, 0.02, 0.02, 0.013, 0.01, 0.01, 0.01}) -> 17355.435 | L9: =C9 + D9 - G9-K9 -> 2437780.4 | M9: =M8 -> 5996.6632 | N9: =49500 * (1 + $Z$47)^($A9-2026) -> 57997.139 | O9: 0 | P9: =4500*(1+$Z$47)^(A9-2027)+IF(B9>=55,1000,0) -> 5169.0855 | Q9: =62600*(1+$Z$47)^(A9-2026) -> 73345.877 | R9: =PV($AD$50 / 12, 12*($AE$50-ROW(R7)), -$AF$50) -> 329153.71 | S9: =S8*1.03 -> 1229873.9 | U9: =S9+L9-R9 -> 3338500.6
A10: =A9+1 -> 2035 | B10: =B9+1 -> 45 | C10: =L9 -> 2437780.4 | D10: =C10 * $Z$43 -> 121889.02 | E10: =IF(B10>=67, '18 Social Security'!$G$5 * (1 + '02 Assumptions'!$B$5)^(B10 - '03 Client Profile'!$D$5), 0) -> 0 | F10: 198456.45 | G10: =F10 -> 198456.45 | H10: =G10-P10-M10 -> 187187.32 | I10: =H10-49450-$AD$42-$AE$47-$AB$48 -> 95861.937 | J10: =I10-M10 -> 89865.274 | K10: =J10 * 0.15 + SUMPRODUCT(--(J10 > {0, 11079, 26264, 41452, 57542, 72724, 371479, 445771, 742953}), (J10 - {0, 11079, 26264, 41452, 57542, 72724, 371479, 445771, 742953}), {0.01, 0.01, 0.02, 0.02, 0.02, 0.013, 0.01, 0.01, 0.01}) -> 18275.899 | L10: =C10 + D10 - G10-K10 -> 2342937.1 | M10: =M9 -> 5996.6632 | N10: =49500 * (1 + $Z$47)^($A10-2026) -> 59157.082 | O10: 0 | P10: =4500*(1+$Z$47)^(A10-2027)+IF(B10>=55,1000,0) -> 5272.4672 | Q10: =62600*(1+$Z$47)^(A10-2026) -> 74812.795 | R10: =PV($AD$50 / 12, 12*($AE$50-ROW(R8)), -$AF$50) -> 321479.9 | S10: =S9*1.03 -> 1266770.1 | U10: =S10+L10-R10 -> 3288227.2
A11: =A10+1 -> 2036 | B11: =B10+1 -> 46 | C11: =L10 -> 2342937.1 | D11: =C11 * $Z$43 -> 117146.85 | E11: =IF(B11>=67, '18 Social Security'!$G$5 * (1 + '02 Assumptions'!$B$5)^(B11 - '03 Client Profile'!$D$5), 0) -> 0 | F11: 202425.58 | G11: =F11 -> 202425.58 | H11: =G11-P11-M11 -> 191051 | I11: =H11-49450-$AD$42-$AE$47-$AB$48 -> 99725.617 | J11: =I11-M11 -> 93728.953 | K11: =J11 * 0.15 + SUMPRODUCT(--(J11 > {0, 11079, 26264, 41452, 57542, 72724, 371479, 445771, 742953}), (J11 - {0, 11079, 26264, 41452, 57542, 72724, 371479, 445771, 742953}), {0.01, 0.01, 0.02, 0.02, 0.02, 0.013, 0.01, 0.01, 0.01}) -> 19214.774 | L11: =C11 + D11 - G11-K11 -> 2238443.6 | M11: =M10 -> 5996.6632 | N11: =49500 * (1 + $Z$47)^($A11-2026) -> 60340.224 | O11: 0 | P11: =4500*(1+$Z$47)^(A11-2027)+IF(B11>=55,1000,0) -> 5377.9166 | Q11: =62600*(1+$Z$47)^(A11-2026) -> 76309.051 | R11: =PV($AD$50 / 12, 12*($AE$50-ROW(R9)), -$AF$50) -> 313353.04 | S11: =S10*1.03 -> 1304773.2 | U11: =S11+L11-R11 -> 3229863.7
A12: =A11+1 -> 2037 | B12: =B11+1 -> 47 | C12: =L11 -> 2238443.6 | D12: =C12 * $Z$43 -> 111922.18 | E12: =IF(B12>=67, '18 Social Security'!$G$5 * (1 + '02 Assumptions'!$B$5)^(B12 - '03 Client Profile'!$D$5), 0) -> 0 | F12: 206474.09 | G12: =F12 -> 206474.09 | H12: =G12-P12-M12 -> 194991.95 | I12: =H12-49450-$AD$42-$AE$47-$AB$48 -> 103666.57 | J12: =I12-M12 -> 97669.907 | K12: =J12 * 0.15 + SUMPRODUCT(--(J12 > {0, 11079, 26264, 41452, 57542, 72724, 371479, 445771, 742953}), (J12 - {0, 11079, 26264, 41452, 57542, 72724, 371479, 445771, 742953}), {0.01, 0.01, 0.02, 0.02, 0.02, 0.013, 0.01, 0.01, 0.01}) -> 20172.425 | L12: =C12 + D12 - G12-K12 -> 2123719.2 | M12: =M11 -> 5996.6632 | N12: =49500 * (1 + $Z$47)^($A12-2026) -> 61547.028 | O12: 0 | P12: =4500*(1+$Z$47)^(A12-2027)+IF(B12>=55,1000,0) -> 5485.4749 | Q12: =62600*(1+$Z$47)^(A12-2026) -> 77835.232 | R12: =PV($AD$50 / 12, 12*($AE$50-ROW(R10)), -$AF$50) -> 304746.36 | S12: =S11*1.03 -> 1343916.4 | U12: =S12+L12-R12 -> 3162889.2
A13: =A12+1 -> 2038 | B13: =B12+1 -> 48 | C13: =L12 -> 2123719.2 | D13: =C13 * $Z$43 -> 106185.96 | E13: =IF(B13>=67, '18 Social Security'!$G$5 * (1 + '02 Assumptions'!$B$5)^(B13 - '03 Client Profile'!$D$5), 0) -> 0 | F13: 210603.57 | G13: =F13 -> 210603.57 | H13: =G13-P13-M13 -> 199011.73 | I13: =H13-49450-$AD$42-$AE$47-$AB$48 -> 107686.34 | J13: =I13-M13 -> 101689.68 | K13: =J13 * 0.15 + SUMPRODUCT(--(J13 > {0, 11079, 26264, 41452, 57542, 72724, 371479, 445771, 742953}), (J13 - {0, 11079, 26264, 41452, 57542, 72724, 371479, 445771, 742953}), {0.01, 0.01, 0.02, 0.02, 0.02, 0.013, 0.01, 0.01, 0.01}) -> 21149.23 | L13: =C13 + D13 - G13-K13 -> 1998152.4 | M13: =M12 -> 5996.6632 | N13: =49500 * (1 + $Z$47)^($A13-2026) -> 62777.969 | O13: 0 | P13: =4500*(1+$Z$47)^(A13-2027)+IF(B13>=55,1000,0) -> 5595.1844 | Q13: =62600*(1+$Z$47)^(A13-2026) -> 79391.936 | R13: =PV($AD$50 / 12, 12*($AE$50-ROW(R11)), -$AF$50) -> 295631.56 | S13: =S12*1.03 -> 1384233.9 | U13: =S13+L13-R13 -> 3086754.7
A14: =A13+1 -> 2039 | B14: =B13+1 -> 49 | C14: =L13 -> 1998152.4 | D14: =C14 * $Z$43 -> 99907.619 | E14: =IF(B14>=67, '18 Social Security'!$G$5 * (1 + '02 Assumptions'!$B$5)^(B14 - '03 Client Profile'!$D$5), 0) -> 0 | F14: 214815.64 | G14: =F14 -> 214815.64 | H14: =G14-P14-M14 -> 203111.89 | I14: =H14-49450-$AD$42-$AE$47-$AB$48 -> 111786.51 | J14: =I14-M14 -> 105789.85 | K14: =J14 * 0.15 + SUMPRODUCT(--(J14 > {0, 11079, 26264, 41452, 57542, 72724, 371479, 445771, 742953}), (J14 - {0, 11079, 26264, 41452, 57542, 72724, 371479, 445771, 742953}), {0.01, 0.01, 0.02, 0.02, 0.02, 0.013, 0.01, 0.01, 0.01}) -> 22145.571 | L14: =C14 + D14 - G14-K14 -> 1861098.8 | M14: =M13 -> 5996.6632 | N14: =49500 * (1 + $Z$47)^($A14-2026) -> 64033.528 | O14: 0 | P14: =4500*(1+$Z$47)^(A14-2027)+IF(B14>=55,1000,0) -> 5707.0881 | Q14: =62600*(1+$Z$47)^(A14-2026) -> 80979.775 | R14: =PV($AD$50 / 12, 12*($AE$50-ROW(R12)), -$AF$50) -> 285978.61 | S14: =S13*1.03 -> 1425760.9 | U14: =S14+L14-R14 -> 3000881.1
... A24: =A23+1 -> 2049 | B24: =B23+1 -> 59 | C24: =L23 -> -12972.063 | D24: =C24 * $Z$43 -> -648.60314 | E24: =IF(B24>=67, '18 Social Security'!$G$5 * (1 + '02 Assumptions'!$B$5)^(B24 - '03 Client Profile'!$D$5), 0) -> 0 | F24: 261859.07 | G24: =F24 -> 261859.07 | H24: =G24-P24-M24 -> 247905.5 | I24: =H24-49450-$AD$42-$AE$47-$AB$48 -> 156580.12 | J24: =I24-M24 -> 150583.45 | K24: =J24 * 0.15 + SUMPRODUCT(--(J24 > {0, 11079, 26264, 41452, 57542, 72724, 371479, 445771, 742953}), (J24 - {0, 11079, 26264, 41452, 57542, 72724, 371479, 445771, 742953}), {0.01, 0.01, 0.02, 0.02, 0.02, 0.013, 0.01, 0.01, 0.01}) -> 33030.417 | L24: =C24 + D24 - G24-K24 -> -308510.16 | M24: =M23 -> 5996.6632 | N24: =49500 * (1 + $Z$47)^($A24-2026) -> 78056.514 | O24: 0 | P24: =4500*(1+$Z$47)^(A24-2027)+IF(B24>=55,1000,0) -> 7956.9085 | Q24: =62600*(1+$Z$47)^(A24-2026) -> 98713.894 | R24: =PV($AD$50 / 12, 12*($AE$50-ROW(R22)), -$AF$50) -> 151839.31 | S24: =S23*1.03 -> 1916103.4 | U24: =S24+L24-R24 -> 1455753.9
A25: =A24+1 -> 2050 | B25: =B24+1 -> 60 | C25: =L24 -> -308510.16 | D25: =C25 * $Z$43 -> -15425.508 | E25: =IF(B25>=67, '18 Social Security'!$G$5 * (1 + '02 Assumptions'!$B$5)^(B25 - '03 Client Profile'!$D$5), 0) -> 0 | F25: 267096.25 | G25: =F25 -> 267096.25 | H25: =G25-P25-M25 -> 253003.54 | I25: =H25-49450-$AD$42-$AE$47-$AB$48 -> 161678.16 | J25: =I25-M25 -> 155681.5 | K25: =J25 * 0.15 + SUMPRODUCT(--(J25 > {0, 11079, 26264, 41452, 57542, 72724, 371479, 445771, 742953}), (J25 - {0, 11079, 26264, 41452, 57542, 72724, 371479, 445771, 742953}), {0.01, 0.01, 0.02, 0.02, 0.02, 0.013, 0.01, 0.01, 0.01}) -> 34269.242 | L25: =C25 + D25 - G25-K25 -> -625301.16 | M25: =M24 -> 5996.6632 | N25: =49500 * (1 + $Z$47)^($A25-2026) -> 79617.644 | O25: 0 | P25: =4500*(1+$Z$47)^(A25-2027)+IF(B25>=55,1000,0) -> 8096.0467 | Q25: =62600*(1+$Z$47)^(A25-2026) -> 100688.17 | R25: =PV($AD$50 / 12, 12*($AE$50-ROW(R23)), -$AF$50) -> 133696.89 | S25: =S24*1.03 -> 1973586.5 | U25: =S25+L25-R25 -> 1214588.5 | AG25: 185000 | AH25: 15000
A26: =A25+1 -> 2051 | B26: =B25+1 -> 61 | C26: =L25 -> -625301.16 | D26: =C26 * $Z$43 -> -31265.058 | E26: =IF(B26>=67, '18 Social Security'!$G$5 * (1 + '02 Assumptions'!$B$5)^(B26 - '03 Client Profile'!$D$5), 0) -> 0 | F26: 272438.18 | G26: =F26 -> 272438.18 | H26: =G26-P26-M26 -> 258203.55 | I26: =H26-49450-$AD$42-$AE$47-$AB$48 -> 166878.16 | J26: =I26-M26 -> 160881.5 | K26: =J26 * 0.15 + SUMPRODUCT(--(J26 > {0, 11079, 26264, 41452, 57542, 72724, 371479, 445771, 742953}), (J26 - {0, 11079, 26264, 41452, 57542, 72724, 371479, 445771, 742953}), {0.01, 0.01, 0.02, 0.02, 0.02, 0.013, 0.01, 0.01, 0.01}) -> 35532.843 | L26: =C26 + D26 - G26-K26 -> -964537.24 | M26: =M25 -> 5996.6632 | N26: =49500 * (1 + $Z$47)^($A26-2026) -> 81209.997 | O26: 0 | P26: =4500*(1+$Z$47)^(A26-2027)+IF(B26>=55,1000,0) -> 8237.9676 | Q26: =62600*(1+$Z$47)^(A26-2026) -> 102701.94 | R26: =PV($AD$50 / 12, 12*($AE$50-ROW(R24)), -$AF$50) -> 114483.35 | S26: =S25*1.03 -> 2032794.1 | U26: =S26+L26-R26 -> 953773.52 | AH26: 160000
A27: =A26+1 -> 2052 | B27: =B26+1 -> 62 | C27: =L26 -> -964537.24 | D27: =C27 * $Z$43 -> -48226.862 | E27: =IF(B27>=67, '18 Social Security'!$G$5 * (1 + '02 Assumptions'!$B$5)^(B27 - '03 Client Profile'!$D$5), 0) -> 0 | F27: 277886.94 | G27: =F27 -> 277886.94 | H27: =G27-P27-M27 -> 263507.55 | I27: =H27-49450-$AD$42-$AE$47-$AB$48 -> 172182.17 | J27: =I27-M27 -> 166185.51 | K27: =J27 * 0.15 + SUMPRODUCT(--(J27 > {0, 11079, 26264, 41452, 57542, 72724, 371479, 445771, 742953}), (J27 - {0, 11079, 26264, 41452, 57542, 72724, 371479, 445771, 742953}), {0.01, 0.01, 0.02, 0.02, 0.02, 0.013, 0.01, 0.01, 0.01}) -> 36821.716 | L27: =C27 + D27 - G27-K27 -> -1327472.8 | M27: =M26 -> 5996.6632 | N27: =49500 * (1 + $Z$47)^($A27-2026) -> 82834.197 | O27: 0 | P27: =4500*(1+$Z$47)^(A27-2027)+IF(B27>=55,1000,0) -> 8382.727 | Q27: =62600*(1+$Z$47)^(A27-2026) -> 104755.97 | R27: =PV($AD$50 / 12, 12*($AE$50-ROW(R25)), -$AF$50) -> 94135.444 | S27: =S26*1.03 -> 2093777.9 | U27: =S27+L27-R27 -> 672169.73
A28: =A27+1 -> 2053 | B28: =B27+1 -> 63 | C28: =L27 -> -1327472.8 | D28: =C28 * $Z$43 -> -66373.638 | E28: =IF(B28>=67, '18 Social Security'!$G$5 * (1 + '02 Assumptions'!$B$5)^(B28 - '03 Client Profile'!$D$5), 0) -> 0 | F28: 283444.68 | G28: =F28 -> 283444.68 | H28: =G28-P28-M28 -> 268917.64 | I28: =H28-49450-$AD$42-$AE$47-$AB$48 -> 177592.25 | J28: =I28-M28 -> 171595.59 | K28: =J28 * 0.15 + SUMPRODUCT(--(J28 > {0, 11079, 26264, 41452, 57542, 72724, 371479, 445771, 742953}), (J28 - {0, 11079, 26264, 41452, 57542, 72724, 371479, 445771, 742953}), {0.01, 0.01, 0.02, 0.02, 0.02, 0.013, 0.01, 0.01, 0.01}) -> 38136.366 | L28: =C28 + D28 - G28-K28 -> -1715427.4 | M28: =M27 -> 5996.6632 | N28: =49500 * (1 + $Z$47)^($A28-2026) -> 84490.881 | O28: 0 | P28: =4500*(1+$Z$47)^(A28-2027)+IF(B28>=55,1000,0) -> 8530.3815 | Q28: =62600*(1+$Z$47)^(A28-2026) -> 106851.09 | R28: =PV($AD$50 / 12, 12*($AE$50-ROW(R26)), -$AF$50) -> 72586.202 | S28: =S27*1.03 -> 2156591.3 | U28: =S28+L28-R28 -> 368577.62
A29: =A28+1 -> 2054 | B29: =B28+1 -> 64 | C29: =L28 -> -1715427.4 | D29: =C29 * $Z$43 -> -85771.372 | E29: =IF(B29>=67, '18 Social Security'!$G$5 * (1 + '02 Assumptions'!$B$5)^(B29 - '03 Client Profile'!$D$5), 0) -> 0 | F29: 289113.57 | G29: =F29 -> 289113.57 | H29: =G29-P29-M29 -> 274435.92 | I29: =H29-49450-$AD$42-$AE$47-$AB$48 -> 183110.54 | J29: =I29-M29 -> 177113.88 | K29: =J29 * 0.15 + SUMPRODUCT(--(J29 > {0, 11079, 26264, 41452, 57542, 72724, 371479, 445771, 742953}), (J29 - {0, 11079, 26264, 41452, 57542, 72724, 371479, 445771, 742953}), {0.01, 0.01, 0.02, 0.02, 0.02, 0.013, 0.01, 0.01, 0.01}) -> 39477.31 | L29: =C29 + D29 - G29-K29 -> -2129789.7 | M29: =M28 -> 5996.6632 | N29: =49500 * (1 + $Z$47)^($A29-2026) -> 86180.698 | O29: 0 | P29: =4500*(1+$Z$47)^(A29-2027)+IF(B29>=55,1000,0) -> 8680.9891 | Q29: =62600*(1+$Z$47)^(A29-2026) -> 108988.12 | R29: =PV($AD$50 / 12, 12*($AE$50-ROW(R27)), -$AF$50) -> 49764.695 | S29: =S28*1.03 -> 2221289 | U29: =S29+L29-R29 -> 41734.613
A30: =A29+1 -> 2055 | B30: =B29+1 -> 65 | C30: =L29 -> -2129789.7 | D30: =C30 * $Z$43 -> -106489.48 | E30: =IF(B30>=67, '18 Social Security'!$G$5 * (1 + '02 Assumptions'!$B$5)^(B30 - '03 Client Profile'!$D$5), 0) -> 0 | F30: 294895.85 | G30: =F30 -> 294895.85 | H30: =G30-P30-M30 -> 280064.57 | I30: =H30-49450-$AD$42-$AE$47-$AB$48 -> 188739.19 | J30: =I30-M30 -> 182742.53 | K30: =J30 * 0.15 + SUMPRODUCT(--(J30 > {0, 11079, 26264, 41452, 57542, 72724, 371479, 445771, 742953}), (J30 - {0, 11079, 26264, 41452, 57542, 72724, 371479, 445771, 742953}), {0.01, 0.01, 0.02, 0.02, 0.02, 0.013, 0.01, 0.01, 0.01}) -> 40845.072 | L30: =C30 + D30 - G30-K30 -> -2572020.1 | M30: =M29 -> 5996.6632 | N30: =49500 * (1 + $Z$47)^($A30-2026) -> 87904.312 | O30: 0 | P30: =4500*(1+$Z$47)^(A30-2027)+IF(B30>=55,1000,0) -> 8834.6089 | Q30: =62600*(1+$Z$47)^(A30-2026) -> 111167.88 | R30: =PV($AD$50 / 12, 12*($AE$50-ROW(R28)), -$AF$50) -> 25595.811 | S30: =S29*1.03 -> 2287927.7 | U30: =S30+L30-R30 -> -309688.24
A31: =A30+1 -> 2056 | B31: =B30+1 -> 66 | C31: =L30 -> -2572020.1 | D31: =C31 * $Z$43 -> -128601.01 | E31: =IF(B31>=67, '18 Social Security'!$G$5 * (1 + '02 Assumptions'!$B$5)^(B31 - '03 Client Profile'!$D$5), 0) -> 0 | F31: 300793.76 | G31: =F31 -> 300793.76 | H31: =G31-P31-M31 -> 285805.8 | I31: =H31-49450-$AD$42-$AE$47-$AB$48 -> 194480.42 | J31: =I31-M31 -> 188483.75 | K31: =J31 * 0.15 + SUMPRODUCT(--(J31 > {0, 11079, 26264, 41452, 57542, 72724, 371479, 445771, 742953}), (J31 - {0, 11079, 26264, 41452, 57542, 72724, 371479, 445771, 742953}), {0.01, 0.01, 0.02, 0.02, 0.02, 0.013, 0.01, 0.01, 0.01}) -> 42240.19 | L31: =C31 + D31 - G31-K31 -> -3043655.1 | M31: =M30 -> 5996.6632 | N31: =49500 * (1 + $Z$47)^($A31-2026) -> 89662.398 | O31: 0 | P31: =4500*(1+$Z$47)^(A31-2027)+IF(B31>=55,1000,0) -> 8991.3011 | Q31: =62600*(1+$Z$47)^(A31-2026) -> 113391.24 | R31: =PV($AD$50 / 12, 12*($AE$50-ROW(R29)), -$AF$50) -> 0 | S31: =S30*1.03 -> 2356565.5 | U31: =S31+L31-R31 -> -687089.55
A32: =A31+1 -> 2057 | B32: =B31+1 -> 67 | C32: =L31 -> -3043655.1 | D32: =C32 * $Z$43 -> -152182.75 | E32: =IF(B32>=67, '18 Social Security'!$G$5 * (1 + '02 Assumptions'!$B$5)^(B32 - '03 Client Profile'!$D$5), 0) -> 66513.197 | F32: 306809.64 | G32: =F32-E32 -> 240296.44 | H32: =G32-P32-M32 -> 225148.65 | I32: =H32-49450-$AD$42-$AE$47-$AB$48 -> 133823.27 | J32: =I32-M32 -> 127826.6 | K32: =J32 * 0.15 + SUMPRODUCT(--(J32 > {0, 11079, 26264, 41452, 57542, 72724, 371479, 445771, 742953}), (J32 - {0, 11079, 26264, 41452, 57542, 72724, 371479, 445771, 742953}), {0.01, 0.01, 0.02, 0.02, 0.02, 0.013, 0.01, 0.01, 0.01}) -> 27500.503 | L32: =C32 + D32 - G32-K32 -> -3463634.8 | M32: =M31 -> 5996.6632 | N32: =49500 * (1 + $Z$47)^($A32-2026) -> 91455.646 | O32: 0 | P32: =4500*(1+$Z$47)^(A32-2027)+IF(B32>=55,1000,0) -> 9151.1271 | Q32: =62600*(1+$Z$47)^(A32-2026) -> 115659.06 | S32: =S31*1.03 -> 2427262.5 | U32: =S32+L32-R32 -> -1036372.3
A33: =A32+1 -> 2058 | B33: =B32+1 -> 68 | C33: =L32 -> -3463634.8 | D33: =C33 * $Z$43 -> -173181.74 | E33: =IF(B33>=67, '18 Social Security'!$G$5 * (1 + '02 Assumptions'!$B$5)^(B33 - '03 Client Profile'!$D$5), 0) -> 67843.461 | F33: 312945.83 | G33: =F33-E33 -> 245102.37 | H33: =G33-P33-M33 -> 229791.56 | I33: =H33-49450-$AD$42-$AE$47-$AB$48 -> 138466.17 | J33: =I33-M33 -> 132469.51 | K33: =J33 * 0.15 + SUMPRODUCT(--(J33 > {0, 11079, 26264, 41452, 57542, 72724, 371479, 445771, 742953}), (J33 - {0, 11079, 26264, 41452, 57542, 72724, 371479, 445771, 742953}), {0.01, 0.01, 0.02, 0.02, 0.02, 0.013, 0.01, 0.01, 0.01}) -> 28628.729 | L33: =C33 + D33 - G33-K33 -> -3910547.6 | M33: =M32 -> 5996.6632 | N33: =49500 * (1 + $Z$47)^($A33-2026) -> 93284.759 | O33: 0 | P33: =4500*(1+$Z$47)^(A33-2027)+IF(B33>=55,1000,0) -> 9314.1497 | Q33: =62600*(1+$Z$47)^(A33-2026) -> 117972.24 | S33: =S32*1.03 -> 2500080.3 | U33: =S33+L33-R33 -> -1410467.2 | AC33: Ideal
A34: =A33+1 -> 2059 | B34: =B33+1 -> 69 | C34: =L33 -> -3910547.6 | D34: =C34 * $Z$43 -> -195527.38 | E34: =IF(B34>=67, '18 Social Security'!$G$5 * (1 + '02 Assumptions'!$B$5)^(B34 - '03 Client Profile'!$D$5), 0) -> 69200.331 | F34: 319204.75 | G34: =F34-E34 -> 250004.42 | H34: =G34-P34-M34 -> 234527.32 | I34: =H34-49450-$AD$42-$AE$47-$AB$48 -> 143201.94 | J34: =I34-M34 -> 137205.27 | K34: =J34 * 0.15 + SUMPRODUCT(--(J34 > {0, 11079, 26264, 41452, 57542, 72724, 371479, 445771, 742953}), (J34 - {0, 11079, 26264, 41452, 57542, 72724, 371479, 445771, 742953}), {0.01, 0.01, 0.02, 0.02, 0.02, 0.013, 0.01, 0.01, 0.01}) -> 29779.52 | L34: =C34 + D34 - G34-K34 -> -4385858.9 | M34: =M33 -> 5996.6632 | N34: =49500 * (1 + $Z$47)^($A34-2026) -> 95150.455 | O34: 0 | P34: =4500*(1+$Z$47)^(A34-2027)+IF(B34>=55,1000,0) -> 9480.4327 | Q34: =62600*(1+$Z$47)^(A34-2026) -> 120331.69 | S34: =S33*1.03 -> 2575082.8 | U34: =S34+L34-R34 -> -1810776.1 | Y34: NIT threshold | Z34: 200000 | AC34: 200000
A35: =A34+1 -> 2060 | B35: =B34+1 -> 70 | C35: =L34 -> -4385858.9 | D35: =C35 * $Z$43 -> -219292.95 | E35: =IF(B35>=67, '18 Social Security'!$G$5 * (1 + '02 Assumptions'!$B$5)^(B35 - '03 Client Profile'!$D$5), 0) -> 70584.337 | F35: 325588.84 | G35: =F35-E35 -> 255004.51 | H35: =G35-P35-M35 -> 239357.8 | I35: =H35-49450-$AD$42-$AE$47-$AB$48 -> 148032.42 | J35: =I35-M35 -> 142035.75 | K35: =J35 * 0.15 + SUMPRODUCT(--(J35 > {0, 11079, 26264, 41452, 57542, 72724, 371479, 445771, 742953}), (J35 - {0, 11079, 26264, 41452, 57542, 72724, 371479, 445771, 742953}), {0.01, 0.01, 0.02, 0.02, 0.02, 0.013, 0.01, 0.01, 0.01}) -> 30953.326 | L35: =C35 + D35 - G35-K35 -> -4891109.7 | M35: =M34 -> 5996.6632 | N35: =49500 * (1 + $Z$47)^($A35-2026) -> 97053.464 | O35: 0 | P35: =4500*(1+$Z$47)^(A35-2027)+IF(B35>=55,1000,0) -> 9650.0413 | Q35: =62600*(1+$Z$47)^(A35-2026) -> 122738.32 | S35: =S34*1.03 -> 2652335.2 | U35: =S35+L35-R35 -> -2238774.4 | Y35: Standard deduction | Z35: 16100 | AC35: ST/Ordinary | AD35: Capital Gains | AE35: TaxFree | AF35: Total | AH35: Tax | AI35: CA
A36: =A35+1 -> 2061 | B36: =B35+1 -> 71 | C36: =L35 -> -4891109.7 | D36: =C36 * $Z$43 -> -244555.48 | E36: =IF(B36>=67, '18 Social Security'!$G$5 * (1 + '02 Assumptions'!$B$5)^(B36 - '03 Client Profile'!$D$5), 0) -> 71996.024 | F36: 332100.62 | G36: =F36-E36 -> 260104.6 | H36: =G36-P36-M36 -> 244284.89 | I36: =H36-49450-$AD$42-$AE$47-$AB$48 -> 152959.51 | J36: =I36-M36 -> 146962.84 | K36: =J36 * 0.15 + SUMPRODUCT(--(J36 > {0, 11079, 26264, 41452, 57542, 72724, 371479, 445771, 742953}), (J36 - {0, 11079, 26264, 41452, 57542, 72724, 371479, 445771, 742953}), {0.01, 0.01, 0.02, 0.02, 0.02, 0.013, 0.01, 0.01, 0.01}) -> 32150.609 | L36: =C36 + D36 - G36-K36 -> -5427920.4 | M36: =M35 -> 5996.6632 | N36: =49500 * (1 + $Z$47)^($A36-2026) -> 98994.533 | O36: 0 | P36: =4500*(1+$Z$47)^(A36-2027)+IF(B36>=55,1000,0) -> 9823.0421 | Q36: =62600*(1+$Z$47)^(A36-2026) -> 125193.09 | S36: =S35*1.03 -> 2731905.3 | U36: =S36+L36-R36 -> -2696015.1 | Y36: Itemized deductions | Z36: 25000 | AC36: =max(Z35,Z36) -> 25000 | AD36: 162500 | AE36: 3000 | AF36: =SUM(AC36:AE36) -> 190500 | AH36: =(AD36-N2)*0.15 -> 16801.5 | AI36: =(AD36-AC36)*0.093 -> 12787.5
A37: =A36+1 -> 2062 | B37: =B36+1 -> 72 | C37: =L36 -> -5427920.4 | D37: =C37 * $Z$43 -> -271396.02 | E37: =IF(B37>=67, '18 Social Security'!$G$5 * (1 + '02 Assumptions'!$B$5)^(B37 - '03 Client Profile'!$D$5), 0) -> 73435.944 | F37: 338742.63 | G37: =F37-E37 -> 265306.69 | H37: =G37-P37-M37 -> 249310.52 | I37: =H37-49450-$AD$42-$AE$47-$AB$48 -> 157985.14 | J37: =I37-M37 -> 151988.47 | K37: =J37 * 0.15 + SUMPRODUCT(--(J37 > {0, 11079, 26264, 41452, 57542, 72724, 371479, 445771, 742953}), (J37 - {0, 11079, 26264, 41452, 57542, 72724, 371479, 445771, 742953}), {0.01, 0.01, 0.02, 0.02, 0.02, 0.013, 0.01, 0.01, 0.01}) -> 33371.837 | L37: =C37 + D37 - G37-K37 -> -5997994.9 | M37: =M36 -> 5996.6632 | N37: =49500 * (1 + $Z$47)^($A37-2026) -> 100974.42 | O37: 0 | P37: =4500*(1+$Z$47)^(A37-2027)+IF(B37>=55,1000,0) -> 9999.503 | Q37: =62600*(1+$Z$47)^(A37-2026) -> 127696.95 | S37: =S36*1.03 -> 2813862.5 | U37: =S37+L37-R37 -> -3184132.5
A38: =A37+1 -> 2063 | B38: =B37+1 -> 73 | C38: =L37 -> -5997994.9 | D38: =C38 * $Z$43 -> -299899.75 | E38: =IF(B38>=67, '18 Social Security'!$G$5 * (1 + '02 Assumptions'!$B$5)^(B38 - '03 Client Profile'!$D$5), 0) -> 74904.663 | F38: 345517.48 | G38: =F38-E38 -> 270612.82 | H38: =G38-P38-M38 -> 254436.66 | I38: =H38-49450-$AD$42-$AE$47-$AB$48 -> 163111.28 | J38: =I38-M38 -> 157114.62 | K38: =J38 * 0.15 + SUMPRODUCT(--(J38 > {0, 11079, 26264, 41452, 57542, 72724, 371479, 445771, 742953}), (J38 - {0, 11079, 26264, 41452, 57542, 72724, 371479, 445771, 742953}), {0.01, 0.01, 0.02, 0.02, 0.02, 0.013, 0.01, 0.01, 0.01}) -> 34617.49 | L38: =C38 + D38 - G38-K38 -> -6603125 | M38: =M37 -> 5996.6632 | N38: =49500 * (1 + $Z$47)^($A38-2026) -> 102993.91 | O38: 0 | P38: =4500*(1+$Z$47)^(A38-2027)+IF(B38>=55,1000,0) -> 10179.493 | Q38: =62600*(1+$Z$47)^(A38-2026) -> 130250.89 | S38: =S37*1.03 -> 2898278.3 | U38: =S38+L38-R38 -> -3704846.6
A39: =A38+1 -> 2064 | B39: =B38+1 -> 74 | C39: =L38 -> -6603125 | D39: =C39 * $Z$43 -> -330156.25 | E39: =IF(B39>=67, '18 Social Security'!$G$5 * (1 + '02 Assumptions'!$B$5)^(B39 - '03 Client Profile'!$D$5), 0) -> 76402.757 | F39: 352427.83 | G39: =F39-E39 -> 276025.08 | H39: =G39-P39-M39 -> 259665.33 | I39: =H39-49450-$AD$42-$AE$47-$AB$48 -> 168339.95 | J39: =I39-M39 -> 162343.28 | K39: =J39 * 0.15 + SUMPRODUCT(--(J39 > {0, 11079, 26264, 41452, 57542, 72724, 371479, 445771, 742953}), (J39 - {0, 11079, 26264, 41452, 57542, 72724, 371479, 445771, 742953}), {0.01, 0.01, 0.02, 0.02, 0.02, 0.013, 0.01, 0.01, 0.01}) -> 35888.056 | L39: =C39 + D39 - G39-K39 -> -7245194.4 | M39: =M38 -> 5996.6632 | N39: =49500 * (1 + $Z$47)^($A39-2026) -> 105053.79 | O39: 0 | P39: =4500*(1+$Z$47)^(A39-2027)+IF(B39>=55,1000,0) -> 10363.083 | Q39: =62600*(1+$Z$47)^(A39-2026) -> 132855.9 | S39: =S38*1.03 -> 2985226.7 | U39: =S39+L39-R39 -> -4259967.7
A40: =A39+1 -> 2065 | B40: =B39+1 -> 75 | C40: =L39 -> -7245194.4 | D40: =C40 * $Z$43 -> -362259.72 | E40: =IF(B40>=67, '18 Social Security'!$G$5 * (1 + '02 Assumptions'!$B$5)^(B40 - '03 Client Profile'!$D$5), 0) -> 77930.812 | F40: 359476.39 | G40: =F40-E40 -> 281545.58 | H40: =G40-P40-M40 -> 264998.57 | I40: =H40-49450-$AD$42-$AE$47-$AB$48 -> 173673.19 | J40: =I40-M40 -> 167676.52 | K40: =J40 * 0.15 + SUMPRODUCT(--(J40 > {0, 11079, 26264, 41452, 57542, 72724, 371479, 445771, 742953}), (J40 - {0, 11079, 26264, 41452, 57542, 72724, 371479, 445771, 742953}), {0.01, 0.01, 0.02, 0.02, 0.02, 0.013, 0.01, 0.01, 0.01}) -> 37184.033 | L40: =C40 + D40 - G40-K40 -> -7926183.7 | M40: =M39 -> 5996.6632 | N40: =49500 * (1 + $Z$47)^($A40-2026) -> 107154.87 | O40: 0 | P40: =4500*(1+$Z$47)^(A40-2027)+IF(B40>=55,1000,0) -> 10550.345 | Q40: =62600*(1+$Z$47)^(A40-2026) -> 135513.02 | S40: =S39*1.03 -> 3074783.5 | U40: =S40+L40-R40 -> -4851400.2
A41: =A40+1 -> 2066 | B41: =B40+1 -> 76 | C41: =L40 -> -7926183.7 | D41: =C41 * $Z$43 -> -396309.18 | E41: =IF(B41>=67, '18 Social Security'!$G$5 * (1 + '02 Assumptions'!$B$5)^(B41 - '03 Client Profile'!$D$5), 0) -> 79489.428 | F41: 366665.92 | G41: =F41-E41 -> 287176.49 | H41: =G41-P41-M41 -> 270438.48 | I41: =H41-49450-$AD$42-$AE$47-$AB$48 -> 179113.09 | J41: =I41-M41 -> 173116.43 | K41: =J41 * 0.15 + SUMPRODUCT(--(J41 > {0, 11079, 26264, 41452, 57542, 72724, 371479, 445771, 742953}), (J41 - {0, 11079, 26264, 41452, 57542, 72724, 371479, 445771, 742953}), {0.01, 0.01, 0.02, 0.02, 0.02, 0.013, 0.01, 0.01, 0.01}) -> 38505.93 | L41: =C41 + D41 - G41-K41 -> -8648175.3 | M41: =M40 -> 5996.6632 | N41: =49500 * (1 + $Z$47)^($A41-2026) -> 109297.96 | O41: 0 | P41: =4500*(1+$Z$47)^(A41-2027)+IF(B41>=55,1000,0) -> 10741.351 | Q41: =62600*(1+$Z$47)^(A41-2026) -> 138223.28 | S41: =S40*1.03 -> 3167027 | U41: =S41+L41-R41 -> -5481148.3 | AB41: Spacex, etc. | AC41: Total Cost Basis | AD41: Total/yr | AE41: Cost Basis left
A42: =A41+1 -> 2067 | B42: =B41+1 -> 77 | C42: =L41 -> -8648175.3 | D42: =C42 * $Z$43 -> -432408.76 | E42: =IF(B42>=67, '18 Social Security'!$G$5 * (1 + '02 Assumptions'!$B$5)^(B42 - '03 Client Profile'!$D$5), 0) -> 81079.216 | F42: 373999.24 | G42: =F42-E42 -> 292920.02 | H42: =G42-P42-M42 -> 275987.18 | I42: =H42-49450-$AD$42-$AE$47-$AB$48 -> 184661.8 | J42: =I42-M42 -> 178665.13 | K42: =J42 * 0.15 + SUMPRODUCT(--(J42 > {0, 11079, 26264, 41452, 57542, 72724, 371479, 445771, 742953}), (J42 - {0, 11079, 26264, 41452, 57542, 72724, 371479, 445771, 742953}), {0.01, 0.01, 0.02, 0.02, 0.02, 0.013, 0.01, 0.01, 0.01}) -> 39854.265 | L42: =C42 + D42 - G42-K42 -> -9413358.3 | M42: =M41 -> 5996.6632 | N42: =49500 * (1 + $Z$47)^($A42-2026) -> 111483.92 | O42: 0 | P42: =4500*(1+$Z$47)^(A42-2027)+IF(B42>=55,1000,0) -> 10936.178 | Q42: =62600*(1+$Z$47)^(A42-2026) -> 140987.75 | S42: =S41*1.03 -> 3262037.8 | U42: =S42+L42-R42 -> -6151320.5 | Y42: Configuration | AC42: =SUM('Tax Lots'!F2:'Tax Lots'!F126) -> 353803.13 | AD42: =AC42/59 -> 5996.6632 | AE42: =AC42-sum(M2:M126) -> -2.3283064e-10
A43: =A42+1 -> 2068 | B43: =B42+1 -> 78 | C43: =L42 -> -9413358.3 | D43: =C43 * $Z$43 -> -470667.92 | E43: =IF(B43>=67, '18 Social Security'!$G$5 * (1 + '02 Assumptions'!$B$5)^(B43 - '03 Client Profile'!$D$5), 0) -> 82700.801 | F43: 381479.22 | G43: =F43-E43 -> 298778.42 | H43: =G43-P43-M43 -> 281646.86 | I43: =H43-49450-$AD$42-$AE$47-$AB$48 -> 190321.47 | J43: =I43-M43 -> 184324.81 | K43: =J43 * 0.15 + SUMPRODUCT(--(J43 > {0, 11079, 26264, 41452, 57542, 72724, 371479, 445771, 742953}), (J43 - {0, 11079, 26264, 41452, 57542, 72724, 371479, 445771, 742953}), {0.01, 0.01, 0.02, 0.02, 0.02, 0.013, 0.01, 0.01, 0.01}) -> 41229.567 | L43: =C43 + D43 - G43-K43 -> -10224034 | M43: =M42 -> 5996.6632 | N43: =49500 * (1 + $Z$47)^($A43-2026) -> 113713.6 | O43: 0 | P43: =4500*(1+$Z$47)^(A43-2027)+IF(B43>=55,1000,0) -> 11134.902 | Q43: =62600*(1+$Z$47)^(A43-2026) -> 143807.5 | S43: =S42*1.03 -> 3359898.9 | U43: =S43+L43-R43 -> -6864135.3 | Y43: Rate of Return | Z43: 0.05 | AB43: 401k
A44: =A43+1 -> 2069 | B44: =B43+1 -> 79 | C44: =L43 -> -10224034 | D44: =C44 * $Z$43 -> -511201.71 | E44: =IF(B44>=67, '18 Social Security'!$G$5 * (1 + '02 Assumptions'!$B$5)^(B44 - '03 Client Profile'!$D$5), 0) -> 84354.817 | F44: 389108.81 | G44: =F44-E44 -> 304753.99 | H44: =G44-P44-M44 -> 287419.73 | I44: =H44-49450-$AD$42-$AE$47-$AB$48 -> 196094.34 | J44: =I44-M44 -> 190097.68 | K44: =J44 * 0.15 + SUMPRODUCT(--(J44 > {0, 11079, 26264, 41452, 57542, 72724, 371479, 445771, 742953}), (J44 - {0, 11079, 26264, 41452, 57542, 72724, 371479, 445771, 742953}), {0.01, 0.01, 0.02, 0.02, 0.02, 0.013, 0.01, 0.01, 0.01}) -> 42632.374 | L44: =C44 + D44 - G44-K44 -> -11082622 | M44: =M43 -> 5996.6632 | N44: =49500 * (1 + $Z$47)^($A44-2026) -> 115987.87 | O44: 0 | P44: =4500*(1+$Z$47)^(A44-2027)+IF(B44>=55,1000,0) -> 11337.6 | Q44: =62600*(1+$Z$47)^(A44-2026) -> 146683.65 | S44: =S43*1.03 -> 3460695.9 | U44: =S44+L44-R44 -> -7621926.4 | Y44: MAGI Goal | Z44: 62000 | AB44: HSA/Roth
A45: =A44+1 -> 2070 | B45: =B44+1 -> 80 | C45: =L44 -> -11082622 | D45: =C45 * $Z$43 -> -554131.12 | E45: =IF(B45>=67, '18 Social Security'!$G$5 * (1 + '02 Assumptions'!$B$5)^(B45 - '03 Client Profile'!$D$5), 0) -> 86041.913 | F45: 396890.98 | G45: =F45-E45 -> 310849.07 | H45: =G45-P45-M45 -> 293308.05 | I45: =H45-49450-$AD$42-$AE$47-$AB$48 -> 201982.67 | J45: =I45-M45 -> 195986.01 | K45: =J45 * 0.15 + SUMPRODUCT(--(J45 > {0, 11079, 26264, 41452, 57542, 72724, 371479, 445771, 742953}), (J45 - {0, 11079, 26264, 41452, 57542, 72724, 371479, 445771, 742953}), {0.01, 0.01, 0.02, 0.02, 0.02, 0.013, 0.01, 0.01, 0.01}) -> 44063.238 | L45: =C45 + D45 - G45-K45 -> -11991666 | M45: =M44 -> 5996.6632 | N45: =49500 * (1 + $Z$47)^($A45-2026) -> 118307.63 | O45: 0 | P45: =4500*(1+$Z$47)^(A45-2027)+IF(B45>=55,1000,0) -> 11544.352 | Q45: =62600*(1+$Z$47)^(A45-2026) -> 149617.33 | S45: =S44*1.03 -> 3564516.8 | U45: =S45+L45-R45 -> -8427149 | Y45: AGI Goal | Z45: 49000 | AD45: 0 | AE45: 0.15 | AG45: California
A46: =A45+1 -> 2071 | B46: =B45+1 -> 81 | C46: =L45 -> -11991666 | D46: =C46 * $Z$43 -> -599583.29 | E46: =IF(B46>=67, '18 Social Security'!$G$5 * (1 + '02 Assumptions'!$B$5)^(B46 - '03 Client Profile'!$D$5), 0) -> 87762.751 | F46: 404828.8 | G46: =F46-E46 -> 317066.05 | H46: =G46-P46-M46 -> 299314.15 | I46: =H46-49450-$AD$42-$AE$47-$AB$48 -> 207988.76 | J46: =I46-M46 -> 201992.1 | K46: =J46 * 0.15 + SUMPRODUCT(--(J46 > {0, 11079, 26264, 41452, 57542, 72724, 371479, 445771, 742953}), (J46 - {0, 11079, 26264, 41452, 57542, 72724, 371479, 445771, 742953}), {0.01, 0.01, 0.02, 0.02, 0.02, 0.013, 0.01, 0.01, 0.01}) -> 45522.719 | L46: =C46 + D46 - G46-K46 -> -12953838 | M46: =M45 -> 5996.6632 | N46: =49500 * (1 + $Z$47)^($A46-2026) -> 120673.78 | O46: 0 | P46: =4500*(1+$Z$47)^(A46-2027)+IF(B46>=55,1000,0) -> 11755.239 | Q46: =62600*(1+$Z$47)^(A46-2026) -> 152609.67 | S46: =S45*1.03 -> 3671452.3 | U46: =S46+L46-R46 -> -9282385.5 | Y46: Total Income Target | Z46: 150000 | AB46: Tax Rate | AD46: $0 – $49,450 | AE46: $49,451 – $545,500 | AG46: 0.1
A47: =A46+1 -> 2072 | B47: =B46+1 -> 82 | C47: =L46 -> -12953838 | D47: =C47 * $Z$43 -> -647691.89 | E47: =IF(B47>=67, '18 Social Security'!$G$5 * (1 + '02 Assumptions'!$B$5)^(B47 - '03 Client Profile'!$D$5), 0) -> 89518.006 | F47: 412925.38 | G47: =F47-E47 -> 323407.37 | H47: =G47-P47-M47 -> 305440.36 | I47: =H47-49450-$AD$42-$AE$47-$AB$48 -> 214114.98 | J47: =I47-M47 -> 208118.32 | K47: =J47 * 0.15 + SUMPRODUCT(--(J47 > {0, 11079, 26264, 41452, 57542, 72724, 371479, 445771, 742953}), (J47 - {0, 11079, 26264, 41452, 57542, 72724, 371479, 445771, 742953}), {0.01, 0.01, 0.02, 0.02, 0.02, 0.013, 0.01, 0.01, 0.01}) -> 47011.389 | L47: =C47 + D47 - G47-K47 -> -13971948 | M47: =M46 -> 5996.6632 | N47: =49500 * (1 + $Z$47)^($A47-2026) -> 123087.26 | O47: 0 | P47: =4500*(1+$Z$47)^(A47-2027)+IF(B47>=55,1000,0) -> 11970.344 | Q47: =62600*(1+$Z$47)^(A47-2026) -> 155661.87 | S47: =S46*1.03 -> 3781595.8 | U47: =S47+L47-R47 -> -10190353 | Y47: Inflation | Z47: ='02 Assumptions'!B5 -> 0.02 | AB47: Deductions | AD47: Property tax | AE47: 13000
A48: =A47+1 -> 2073 | B48: =B47+1 -> 83 | C48: =L47 -> -13971948 | D48: =C48 * $Z$43 -> -698597.42 | E48: =IF(B48>=67, '18 Social Security'!$G$5 * (1 + '02 Assumptions'!$B$5)^(B48 - '03 Client Profile'!$D$5), 0) -> 91308.367 | F48: 421183.89 | G48: =F48-E48 -> 329875.52 | H48: =G48-P48-M48 -> 311689.1 | I48: =H48-49450-$AD$42-$AE$47-$AB$48 -> 220363.72 | J48: =I48-M48 -> 214367.06 | K48: =J48 * 0.15 + SUMPRODUCT(--(J48 > {0, 11079, 26264, 41452, 57542, 72724, 371479, 445771, 742953}), (J48 - {0, 11079, 26264, 41452, 57542, 72724, 371479, 445771, 742953}), {0.01, 0.01, 0.02, 0.02, 0.02, 0.013, 0.01, 0.01, 0.01}) -> 48529.833 | L48: =C48 + D48 - G48-K48 -> -15048951 | M48: =M47 -> 5996.6632 | N48: =49500 * (1 + $Z$47)^($A48-2026) -> 125549 | O48: 0 | P48: =4500*(1+$Z$47)^(A48-2027)+IF(B48>=55,1000,0) -> 12189.751 | Q48: =62600*(1+$Z$47)^(A48-2026) -> 158775.1 | S48: =S47*1.03 -> 3895043.7 | U48: =S48+L48-R48 -> -11153908 | AA48: Mortgage interest | AB48: =1906.56*12 -> 22878.72 | AD48: 11832
A49: =A48+1 -> 2074 | B49: =B48+1 -> 84 | C49: =L48 -> -15048951 | D49: =C49 * $Z$43 -> -752447.56 | E49: =IF(B49>=67, '18 Social Security'!$G$5 * (1 + '02 Assumptions'!$B$5)^(B49 - '03 Client Profile'!$D$5), 0) -> 93134.534 | F49: 429607.56 | G49: =F49-E49 -> 336473.03 | H49: =G49-P49-M49 -> 318062.82 | I49: =H49-49450-$AD$42-$AE$47-$AB$48 -> 226737.44 | J49: =I49-M49 -> 220740.77 | K49: =J49 * 0.15 + SUMPRODUCT(--(J49 > {0, 11079, 26264, 41452, 57542, 72724, 371479, 445771, 742953}), (J49 - {0, 11079, 26264, 41452, 57542, 72724, 371479, 445771, 742953}), {0.01, 0.01, 0.02, 0.02, 0.02, 0.013, 0.01, 0.01, 0.01}) -> 50078.646 | L49: =C49 + D49 - G49-K49 -> -16187950 | M49: =M48 -> 5996.6632 | N49: =49500 * (1 + $Z$47)^($A49-2026) -> 128059.98 | O49: 0 | P49: =4500*(1+$Z$47)^(A49-2027)+IF(B49>=55,1000,0) -> 12413.546 | Q49: =62600*(1+$Z$47)^(A49-2026) -> 161950.61 | S49: =S48*1.03 -> 4011895 | U49: =S49+L49-R49 -> -12176055 | Y49: CA tax | AD49: Interest | AE49: Yrs left | AF49: Payment
A50: =A49+1 -> 2075 | B50: =B49+1 -> 85 | C50: =L49 -> -16187950 | D50: =C50 * $Z$43 -> -809397.52 | E50: =IF(B50>=67, '18 Social Security'!$G$5 * (1 + '02 Assumptions'!$B$5)^(B50 - '03 Client Profile'!$D$5), 0) -> 94997.225 | F50: 438199.71 | G50: =F50-E50 -> 343202.49 | H50: =G50-P50-M50 -> 324564.01 | I50: =H50-49450-$AD$42-$AE$47-$AB$48 -> 233238.63 | J50: =I50-M50 -> 227241.96 | K50: =J50 * 0.15 + SUMPRODUCT(--(J50 > {0, 11079, 26264, 41452, 57542, 72724, 371479, 445771, 742953}), (J50 - {0, 11079, 26264, 41452, 57542, 72724, 371479, 445771, 742953}), {0.01, 0.01, 0.02, 0.02, 0.02, 0.013, 0.01, 0.01, 0.01}) -> 51658.435 | L50: =C50 + D50 - G50-K50 -> -17392209 | M50: =M49 -> 5996.6632 | N50: =49500 * (1 + $Z$47)^($A50-2026) -> 130621.18 | O50: 0 | P50: =4500*(1+$Z$47)^(A50-2027)+IF(B50>=55,1000,0) -> 12641.817 | Q50: =62600*(1+$Z$47)^(A50-2026) -> 165189.62 | S50: =S49*1.03 -> 4132251.9 | U50: =S50+L50-R50 -> -13259957 | Y50: 0.01 | Z50: $0 to $11,079 | AB50: Mortgage | AC50: 400000 | AD50: 0.0575 | AE50: 29 | AF50: 2200
A51: =A50+1 -> 2076 | B51: =B50+1 -> 86 | C51: =L50 -> -17392209 | D51: =C51 * $Z$43 -> -869610.45 | E51: =IF(B51>=67, '18 Social Security'!$G$5 * (1 + '02 Assumptions'!$B$5)^(B51 - '03 Client Profile'!$D$5), 0) -> 96897.169 | F51: 446963.71 | G51: =F51-E51 -> 350066.54 | H51: =G51-P51-M51 -> 331195.22 | I51: =H51-49450-$AD$42-$AE$47-$AB$48 -> 239869.84 | J51: =I51-M51 -> 233873.18 | K51: =J51 * 0.15 + SUMPRODUCT(--(J51 > {0, 11079, 26264, 41452, 57542, 72724, 371479, 445771, 742953}), (J51 - {0, 11079, 26264, 41452, 57542, 72724, 371479, 445771, 742953}), {0.01, 0.01, 0.02, 0.02, 0.02, 0.013, 0.01, 0.01, 0.01}) -> 53269.82 | L51: =C51 + D51 - G51-K51 -> -18665156 | M51: =M50 -> 5996.6632 | N51: =49500 * (1 + $Z$47)^($A51-2026) -> 133233.61 | O51: 0 | P51: =4500*(1+$Z$47)^(A51-2027)+IF(B51>=55,1000,0) -> 12874.653 | Q51: =62600*(1+$Z$47)^(A51-2026) -> 168493.41 | S51: =S50*1.03 -> 4256219.4 | U51: =S51+L51-R51 -> -14408936 | Y51: 0.02 | Z51: $11,080 to $26,264
A52: =A51+1 -> 2077 | B52: =B51+1 -> 87 | C52: =L51 -> -18665156 | D52: =C52 * $Z$43 -> -933257.79 | E52: =IF(B52>=67, '18 Social Security'!$G$5 * (1 + '02 Assumptions'!$B$5)^(B52 - '03 Client Profile'!$D$5), 0) -> 98835.112 | F52: 455902.98 | G52: =F52-E52 -> 357067.87 | H52: =G52-P52-M52 -> 337959.06 | I52: =H52-49450-$AD$42-$AE$47-$AB$48 -> 246633.68 | J52: =I52-M52 -> 240637.01 | K52: =J52 * 0.15 + SUMPRODUCT(--(J52 > {0, 11079, 26264, 41452, 57542, 72724, 371479, 445771, 742953}), (J52 - {0, 11079, 26264, 41452, 57542, 72724, 371479, 445771, 742953}), {0.01, 0.01, 0.02, 0.02, 0.02, 0.013, 0.01, 0.01, 0.01}) -> 54913.433 | L52: =C52 + D52 - G52-K52 -> -20010395 | M52: =M51 -> 5996.6632 | N52: =49500 * (1 + $Z$47)^($A52-2026) -> 135898.28 | O52: 0 | P52: =4500*(1+$Z$47)^(A52-2027)+IF(B52>=55,1000,0) -> 13112.146 | Q52: =62600*(1+$Z$47)^(A52-2026) -> 171863.28 | S52: =S51*1.03 -> 4383906 | U52: =S52+L52-R52 -> -15626489 | Y52: 0.04 | Z52: $26,265 to $41,452
A53: =A52+1 -> 2078 | B53: =B52+1 -> 88 | C53: =L52 -> -20010395 | D53: =C53 * $Z$43 -> -1000519.7 | E53: =IF(B53>=67, '18 Social Security'!$G$5 * (1 + '02 Assumptions'!$B$5)^(B53 - '03 Client Profile'!$D$5), 0) -> 100811.81 | F53: 465021.04 | G53: =F53-E53 -> 364209.23 | H53: =G53-P53-M53 -> 344858.18 | I53: =H53-49450-$AD$42-$AE$47-$AB$48 -> 253532.79 | J53: =I53-M53 -> 247536.13 | K53: =J53 * 0.15 + SUMPRODUCT(--(J53 > {0, 11079, 26264, 41452, 57542, 72724, 371479, 445771, 742953}), (J53 - {0, 11079, 26264, 41452, 57542, 72724, 371479, 445771, 742953}), {0.01, 0.01, 0.02, 0.02, 0.02, 0.013, 0.01, 0.01, 0.01}) -> 56589.917 | L53: =C53 + D53 - G53-K53 -> -21431714 | M53: =M52 -> 5996.6632 | N53: =49500 * (1 + $Z$47)^($A53-2026) -> 138616.25 | O53: 0 | P53: =4500*(1+$Z$47)^(A53-2027)+IF(B53>=55,1000,0) -> 13354.389 | Q53: =62600*(1+$Z$47)^(A53-2026) -> 175300.54 | S53: =S52*1.03 -> 4515423.2 | U53: =S53+L53-R53 -> -16916290 | Y53: 0.06 | Z53: $41,453 to $57,542
A54: =A53+1 -> 2079 | B54: =B53+1 -> 89 | C54: =L53 -> -21431714 | D54: =C54 * $Z$43 -> -1071585.7 | E54: =IF(B54>=67, '18 Social Security'!$G$5 * (1 + '02 Assumptions'!$B$5)^(B54 - '03 Client Profile'!$D$5), 0) -> 102828.05 | F54: 474321.46 | G54: =F54-E54 -> 371493.41 | H54: =G54-P54-M54 -> 351895.27 | I54: =H54-49450-$AD$42-$AE$47-$AB$48 -> 260569.89 | J54: =I54-M54 -> 254573.23 | K54: =J54 * 0.15 + SUMPRODUCT(--(J54 > {0, 11079, 26264, 41452, 57542, 72724, 371479, 445771, 742953}), (J54 - {0, 11079, 26264, 41452, 57542, 72724, 371479, 445771, 742953}), {0.01, 0.01, 0.02, 0.02, 0.02, 0.013, 0.01, 0.01, 0.01}) -> 58299.932 | L54: =C54 + D54 - G54-K54 -> -22933093 | M54: =M53 -> 5996.6632 | N54: =49500 * (1 + $Z$47)^($A54-2026) -> 141388.57 | O54: 0 | P54: =4500*(1+$Z$47)^(A54-2027)+IF(B54>=55,1000,0) -> 13601.477 | Q54: =62600*(1+$Z$47)^(A54-2026) -> 178806.56 | S54: =S53*1.03 -> 4650885.9 | U54: =S54+L54-R54 -> -18282207 | Y54: 0.08 | Z54: $57,543 to $72,724
A55: =A54+1 -> 2080 | B55: =B54+1 -> 90 | C55: =L54 -> -22933093 | D55: =C55 * $Z$43 -> -1146654.6 | E55: =IF(B55>=67, '18 Social Security'!$G$5 * (1 + '02 Assumptions'!$B$5)^(B55 - '03 Client Profile'!$D$5), 0) -> 104884.61 | F55: 483807.89 | G55: =F55-E55 -> 378923.28 | H55: =G55-P55-M55 -> 359073.11 | I55: =H55-49450-$AD$42-$AE$47-$AB$48 -> 267747.73 | J55: =I55-M55 -> 261751.06 | K55: =J55 * 0.15 + SUMPRODUCT(--(J55 > {0, 11079, 26264, 41452, 57542, 72724, 371479, 445771, 742953}), (J55 - {0, 11079, 26264, 41452, 57542, 72724, 371479, 445771, 742953}), {0.01, 0.01, 0.02, 0.02, 0.02, 0.013, 0.01, 0.01, 0.01}) -> 60044.147 | L55: =C55 + D55 - G55-K55 -> -24518715 | M55: =M54 -> 5996.6632 | N55: =49500 * (1 + $Z$47)^($A55-2026) -> 144216.34 | O55: 0 | P55: =4500*(1+$Z$47)^(A55-2027)+IF(B55>=55,1000,0) -> 13853.506 | Q55: =62600*(1+$Z$47)^(A55-2026) -> 182382.69 | S55: =S54*1.03 -> 4790412.5 | U55: =S55+L55-R55 -> -19728302 | Y55: 0.093 | Z55: $72,725 to $371,479
A56: =A55+1 -> 2081 | B56: =B55+1 -> 91 | C56: =L55 -> -24518715 | D56: =C56 * $Z$43 -> -1225935.7 | E56: =IF(B56>=67, '18 Social Security'!$G$5 * (1 + '02 Assumptions'!$B$5)^(B56 - '03 Client Profile'!$D$5), 0) -> 106982.3 | F56: 493484.05 | G56: =F56-E56 -> 386501.75 | H56: =G56-P56-M56 -> 366394.51 | I56: =H56-49450-$AD$42-$AE$47-$AB$48 -> 275069.12 | J56: =I56-M56 -> 269072.46 | K56: =J56 * 0.15 + SUMPRODUCT(--(J56 > {0, 11079, 26264, 41452, 57542, 72724, 371479, 445771, 742953}), (J56 - {0, 11079, 26264, 41452, 57542, 72724, 371479, 445771, 742953}), {0.01, 0.01, 0.02, 0.02, 0.02, 0.013, 0.01, 0.01, 0.01}) -> 61823.246 | L56: =C56 + D56 - G56-K56 -> -26192976 | M56: =M55 -> 5996.6632 | N56: =49500 * (1 + $Z$47)^($A56-2026) -> 147100.67 | O56: 0 | P56: =4500*(1+$Z$47)^(A56-2027)+IF(B56>=55,1000,0) -> 14110.576 | Q56: =62600*(1+$Z$47)^(A56-2026) -> 186030.34 | S56: =S55*1.03 -> 4934124.8 | U56: =S56+L56-R56 -> -21258851 | Y56: 0.103 | Z56: $371,480 to $445,771
A57: =A56+1 -> 2082 | B57: =B56+1 -> 92 | C57: =L56 -> -26192976 | D57: =C57 * $Z$43 -> -1309648.8 | E57: =IF(B57>=67, '18 Social Security'!$G$5 * (1 + '02 Assumptions'!$B$5)^(B57 - '03 Client Profile'!$D$5), 0) -> 109121.95 | F57: 503353.73 | G57: =F57-E57 -> 394231.78 | H57: =G57-P57-M57 -> 373862.33 | I57: =H57-49450-$AD$42-$AE$47-$AB$48 -> 282536.95 | J57: =I57-M57 -> 276540.28 | K57: =J57 * 0.15 + SUMPRODUCT(--(J57 > {0, 11079, 26264, 41452, 57542, 72724, 371479, 445771, 742953}), (J57 - {0, 11079, 26264, 41452, 57542, 72724, 371479, 445771, 742953}), {0.01, 0.01, 0.02, 0.02, 0.02, 0.013, 0.01, 0.01, 0.01}) -> 63637.927 | L57: =C57 + D57 - G57-K57 -> -27960494 | M57: =M56 -> 5996.6632 | N57: =49500 * (1 + $Z$47)^($A57-2026) -> 150042.68 | O57: 0 | P57: =4500*(1+$Z$47)^(A57-2027)+IF(B57>=55,1000,0) -> 14372.788 | Q57: =62600*(1+$Z$47)^(A57-2026) -> 189750.95 | S57: =S56*1.03 -> 5082148.6 | U57: =S57+L57-R57 -> -22878345 | Y57: 0.113 | Z57: $445,772 to $742,953
A58: =A57+1 -> 2083 | B58: =B57+1 -> 93 | C58: =L57 -> -27960494 | D58: =C58 * $Z$43 -> -1398024.7 | E58: =IF(B58>=67, '18 Social Security'!$G$5 * (1 + '02 Assumptions'!$B$5)^(B58 - '03 Client Profile'!$D$5), 0) -> 111304.39 | F58: 513420.81 | G58: =F58-E58 -> 402116.42 | H58: =G58-P58-M58 -> 381479.51 | I58: =H58-49450-$AD$42-$AE$47-$AB$48 -> 290154.13 | J58: =I58-M58 -> 284157.46 | K58: =J58 * 0.15 + SUMPRODUCT(--(J58 > {0, 11079, 26264, 41452, 57542, 72724, 371479, 445771, 742953}), (J58 - {0, 11079, 26264, 41452, 57542, 72724, 371479, 445771, 742953}), {0.01, 0.01, 0.02, 0.02, 0.02, 0.013, 0.01, 0.01, 0.01}) -> 65488.902 | L58: =C58 + D58 - G58-K58 -> -29826124 | M58: =M57 -> 5996.6632 | N58: =49500 * (1 + $Z$47)^($A58-2026) -> 153043.54 | O58: 0 | P58: =4500*(1+$Z$47)^(A58-2027)+IF(B58>=55,1000,0) -> 14640.244 | Q58: =62600*(1+$Z$47)^(A58-2026) -> 193545.97 | S58: =S57*1.03 -> 5234613 | U58: =S58+L58-R58 -> -24591511 | Y58: 0.123 | Z58: $742,954 and over
A59: =A58+1 -> 2084 | B59: =B58+1 -> 94 | C59: =L58 -> -29826124 | D59: =C59 * $Z$43 -> -1491306.2 | E59: =IF(B59>=67, '18 Social Security'!$G$5 * (1 + '02 Assumptions'!$B$5)^(B59 - '03 Client Profile'!$D$5), 0) -> 113530.48 | F59: 523689.22 | G59: =F59-E59 -> 410158.74 | H59: =G59-P59-M59 -> 389249.03 | I59: =H59-49450-$AD$42-$AE$47-$AB$48 -> 297923.65 | J59: =I59-M59 -> 291926.99 | K59: =J59 * 0.15 + SUMPRODUCT(--(J59 > {0, 11079, 26264, 41452, 57542, 72724, 371479, 445771, 742953}), (J59 - {0, 11079, 26264, 41452, 57542, 72724, 371479, 445771, 742953}), {0.01, 0.01, 0.02, 0.02, 0.02, 0.013, 0.01, 0.01, 0.01}) -> 67376.896 | L59: =C59 + D59 - G59-K59 -> -31794966 | M59: =M58 -> 5996.6632 | N59: =49500 * (1 + $Z$47)^($A59-2026) -> 156104.41 | O59: 0 | P59: =4500*(1+$Z$47)^(A59-2027)+IF(B59>=55,1000,0) -> 14913.049 | Q59: =62600*(1+$Z$47)^(A59-2026) -> 197416.89 | S59: =S58*1.03 -> 5391651.4 | U59: =S59+L59-R59 -> -26403314
A60: =A59+1 -> 2085 | B60: =B59+1 -> 95 | C60: =L59 -> -31794966 | D60: =C60 * $Z$43 -> -1589748.3 | E60: =IF(B60>=67, '18 Social Security'!$G$5 * (1 + '02 Assumptions'!$B$5)^(B60 - '03 Client Profile'!$D$5), 0) -> 115801.09 | F60: 534163.01 | G60: =F60-E60 -> 418361.92 | H60: =G60-P60-M60 -> 397173.95 | I60: =H60-49450-$AD$42-$AE$47-$AB$48 -> 305848.56 | J60: =I60-M60 -> 299851.9 | K60: =J60 * 0.15 + SUMPRODUCT(--(J60 > {0, 11079, 26264, 41452, 57542, 72724, 371479, 445771, 742953}), (J60 - {0, 11079, 26264, 41452, 57542, 72724, 371479, 445771, 742953}), {0.01, 0.01, 0.02, 0.02, 0.02, 0.013, 0.01, 0.01, 0.01}) -> 69302.65 | L60: =C60 + D60 - G60-K60 -> -33872379 | M60: =M59 -> 5996.6632 | N60: =49500 * (1 + $Z$47)^($A60-2026) -> 159226.49 | O60: 0 | P60: =4500*(1+$Z$47)^(A60-2027)+IF(B60>=55,1000,0) -> 15191.31 | Q60: =62600*(1+$Z$47)^(A60-2026) -> 201365.22 | S60: =S59*1.03 -> 5553401 | U60: =S60+L60-R60 -> -28318978
Z63: =25000/52 -> 480.76923
T66: =1668*0.24*4 -> 1601.28
T67: =30000*0.03 -> 900
N77: Tax-Efficient Sell Analyzer | W77: Tax-Efficient Sell Analyzer | AE77: Tax-Efficient Sell Analyzer
N78: Selected Value | P78: =SUM(T82:T50540) -> 0 | Q78: Ordinary Gain | R78: =SUMIF(W82:W50540, "Short Term", V82:V50540) -> 0 | S78: Tax-Free Gain | T78: =SUMIF(W82:W50540, "Long Term", V82:V50540) -> 0
N79: Target Tax-Free | P79: 50000 | Q79: Target Ordinary | S79: Cost Basis | T79: =SUM(U82:U50540) -> 0
N81: Sell All? | P81: Partial Shares | Q81: Asset | R81: Acq Date | S81: Total Shares | T81: Sold Value | U81: Sold Basis | V81: Sold Gain | W81: Term | X81: Shares Remaining | Y81: Shares Remaining | Z81: Shares Remaining | AA81: Shares Remaining | AB81: Shares Remaining | AC81: Shares Remaining | AD81: Shares Remaining | AE81: Shares Remaining
N82: FALSE | Q82: {=IF(Z82:Z50540="", "", Z82:Z50540)} -> Google | R82: {=IF(AA82:AA50540="", "", AA82:AA50540)} -> GOOG | S82: {=IF(AB82:AB50540="", "", AB82:AB50540)} | T82: {=IF(Q82:Q50540="", "", IF(N82:N50540=TRUE, S82:S50540 * AC82:AC50540, IF(P82:P50540>0, P82:P50540 * AC82:AC50540, 0)))} -> 0 | U82: {=IF(Q82:Q50540="", "", IF(N82:N50540=TRUE, S82:S50540 * AD82:AD50540, IF(P82:P50540>0, P82:P50540 * AD82:AD50540, 0)))} -> 0 | V82: {=IF(Q82:Q50540="", "", T82:T50540 - U82:U50540)} -> #REF! | W82: {=IF(Q82:Q50540="", "", AE82:AE50540)} -> #REF! | X82: {=IF(Q82:Q50540="", "", S82:S50540 - IF(N82:N50540=TRUE, S82:S50540, IF(P82:P50540>0, P82:P50540, 0)))} -> #REF! | Z82: =IFERROR(__xludf.DUMMYFUNCTION("LET(data, FILTER(HSTACK('Tax Lots'!A2:A50540, 'Tax Lots'!B2:B50540, 'Tax Lots'!D128:D50540, 'Tax Lots'!F128:F50540, 'Tax Lots'!C128:C50540), 'Tax Lots'!A2:A50540 <> """"), assets, CHOOSECOLS(data, 1), acqDates, CHOOSECOLS(data, 2), totalShares, CHOOSECOLS"&"(data, 3), cbps, CHOOSECOLS(data, 4), terms, MAP(acqDates, LAMBDA(d, IF(DAYS(TODAY(), d)>=365, ""Long Term"", ""Short Term""))), prices, MAP(assets, LAMBDA(a, IFS(a=""Google"", GOOGLEFINANCE(""GOOG""), a=""Agilent"", GOOGLEFINANCE(""A""), a=""Keysight"", "&"GOOGLEFINANCE(""KEYS""), a=""SpaceX"", 157.54, TRUE, 0))), fullTable, HSTACK(assets, acqDates, totalShares, prices, cbps, terms), SORT(fullTable, 5, FALSE))"),"Google") -> Google | AA82: =IFERROR(__xludf.DUMMYFUNCTION("""COMPUTED_VALUE"""),"GOOG") -> GOOG | AC82: =IFERROR(__xludf.DUMMYFUNCTION("""COMPUTED_VALUE"""),332.56) -> 332.56 | AE82: =IFERROR(__xludf.DUMMYFUNCTION("""COMPUTED_VALUE"""),"#VALUE!") -> #VALUE!
N83: FALSE | Q83: Google | R83: GOOG | T83: 0 | U83: 0 | Z83: =IFERROR(__xludf.DUMMYFUNCTION("""COMPUTED_VALUE"""),"Google") -> Google | AA83: =IFERROR(__xludf.DUMMYFUNCTION("""COMPUTED_VALUE"""),"GOOG") -> GOOG | AC83: =IFERROR(__xludf.DUMMYFUNCTION("""COMPUTED_VALUE"""),332.56) -> 332.56 | AE83: =IFERROR(__xludf.DUMMYFUNCTION("""COMPUTED_VALUE"""),"#VALUE!") -> #VALUE!
N84: FALSE | Q84: Google | R84: GOOG | T84: 0 | U84: 0 | Z84: =IFERROR(__xludf.DUMMYFUNCTION("""COMPUTED_VALUE"""),"Google") -> Google | AA84: =IFERROR(__xludf.DUMMYFUNCTION("""COMPUTED_VALUE"""),"GOOG") -> GOOG | AC84: =IFERROR(__xludf.DUMMYFUNCTION("""COMPUTED_VALUE"""),332.56) -> 332.56 | AE84: =IFERROR(__xludf.DUMMYFUNCTION("""COMPUTED_VALUE"""),"#VALUE!") -> #VALUE!
N85: FALSE | Q85: Google | R85: GOOG | T85: 0 | U85: 0 | Z85: =IFERROR(__xludf.DUMMYFUNCTION("""COMPUTED_VALUE"""),"Google") -> Google | AA85: =IFERROR(__xludf.DUMMYFUNCTION("""COMPUTED_VALUE"""),"GOOG") -> GOOG | AC85: =IFERROR(__xludf.DUMMYFUNCTION("""COMPUTED_VALUE"""),332.56) -> 332.56 | AE85: =IFERROR(__xludf.DUMMYFUNCTION("""COMPUTED_VALUE"""),"#VALUE!") -> #VALUE!
N86: FALSE | Q86: Google | R86: GOOG | T86: 0 | U86: 0 | Z86: =IFERROR(__xludf.DUMMYFUNCTION("""COMPUTED_VALUE"""),"Google") -> Google | AA86: =IFERROR(__xludf.DUMMYFUNCTION("""COMPUTED_VALUE"""),"GOOG") -> GOOG | AC86: =IFERROR(__xludf.DUMMYFUNCTION("""COMPUTED_VALUE"""),332.56) -> 332.56 | AE86: =IFERROR(__xludf.DUMMYFUNCTION("""COMPUTED_VALUE"""),"#VALUE!") -> #VALUE!
N87: FALSE | Q87: Google | R87: GOOG | T87: 0 | U87: 0 | Z87: =IFERROR(__xludf.DUMMYFUNCTION("""COMPUTED_VALUE"""),"Google") -> Google | AA87: =IFERROR(__xludf.DUMMYFUNCTION("""COMPUTED_VALUE"""),"GOOG") -> GOOG | AC87: =IFERROR(__xludf.DUMMYFUNCTION("""COMPUTED_VALUE"""),332.56) -> 332.56 | AE87: =IFERROR(__xludf.DUMMYFUNCTION("""COMPUTED_VALUE"""),"#VALUE!") -> #VALUE!
N88: FALSE | Q88: Google | R88: GOOG | T88: 0 | U88: 0 | Z88: =IFERROR(__xludf.DUMMYFUNCTION("""COMPUTED_VALUE"""),"Google") -> Google | AA88: =IFERROR(__xludf.DUMMYFUNCTION("""COMPUTED_VALUE"""),"GOOG") -> GOOG | AC88: =IFERROR(__xludf.DUMMYFUNCTION("""COMPUTED_VALUE"""),332.56) -> 332.56 | AE88: =IFERROR(__xludf.DUMMYFUNCTION("""COMPUTED_VALUE"""),"#VALUE!") -> #VALUE!
N89: FALSE | Q89: Google | R89: GOOG | T89: 0 | U89: 0 | Z89: =IFERROR(__xludf.DUMMYFUNCTION("""COMPUTED_VALUE"""),"Google") -> Google | AA89: =IFERROR(__xludf.DUMMYFUNCTION("""COMPUTED_VALUE"""),"GOOG") -> GOOG | AC89: =IFERROR(__xludf.DUMMYFUNCTION("""COMPUTED_VALUE"""),332.56) -> 332.56 | AE89: =IFERROR(__xludf.DUMMYFUNCTION("""COMPUTED_VALUE"""),"#VALUE!") -> #VALUE!
N90: FALSE | Q90: Google | R90: GOOG | T90: 0 | U90: 0 | Z90: =IFERROR(__xludf.DUMMYFUNCTION("""COMPUTED_VALUE"""),"Google") -> Google | AA90: =IFERROR(__xludf.DUMMYFUNCTION("""COMPUTED_VALUE"""),"GOOG") -> GOOG | AC90: =IFERROR(__xludf.DUMMYFUNCTION("""COMPUTED_VALUE"""),332.56) -> 332.56 | AE90: =IFERROR(__xludf.DUMMYFUNCTION("""COMPUTED_VALUE"""),"#VALUE!") -> #VALUE!
N91: FALSE | Q91: Google | R91: GOOG | T91: 0 | U91: 0 | Z91: =IFERROR(__xludf.DUMMYFUNCTION("""COMPUTED_VALUE"""),"Google") -> Google | AA91: =IFERROR(__xludf.DUMMYFUNCTION("""COMPUTED_VALUE"""),"GOOG") -> GOOG | AC91: =IFERROR(__xludf.DUMMYFUNCTION("""COMPUTED_VALUE"""),332.56) -> 332.56 | AE91: =IFERROR(__xludf.DUMMYFUNCTION("""COMPUTED_VALUE"""),"#VALUE!") -> #VALUE!
N92: FALSE | Q92: Google | R92: GOOG | T92: 0 | U92: 0 | Z92: =IFERROR(__xludf.DUMMYFUNCTION("""COMPUTED_VALUE"""),"Google") -> Google | AA92: =IFERROR(__xludf.DUMMYFUNCTION("""COMPUTED_VALUE"""),"GOOG") -> GOOG | AC92: =IFERROR(__xludf.DUMMYFUNCTION("""COMPUTED_VALUE"""),332.56) -> 332.56 | AE92: =IFERROR(__xludf.DUMMYFUNCTION("""COMPUTED_VALUE"""),"#VALUE!") -> #VALUE!
N93: FALSE | Q93: Google | R93: GOOG | T93: 0 | U93: 0 | Z93: =IFERROR(__xludf.DUMMYFUNCTION("""COMPUTED_VALUE"""),"Google") -> Google | AA93: =IFERROR(__xludf.DUMMYFUNCTION("""COMPUTED_VALUE"""),"GOOG") -> GOOG | AC93: =IFERROR(__xludf.DUMMYFUNCTION("""COMPUTED_VALUE"""),332.56) -> 332.56 | AE93: =IFERROR(__xludf.DUMMYFUNCTION("""COMPUTED_VALUE"""),"#VALUE!") -> #VALUE!
N94: FALSE | Q94: Google | R94: GOOG | T94: 0 | U94: 0 | Z94: =IFERROR(__xludf.DUMMYFUNCTION("""COMPUTED_VALUE"""),"Google") -> Google | AA94: =IFERROR(__xludf.DUMMYFUNCTION("""COMPUTED_VALUE"""),"GOOG") -> GOOG | AC94: =IFERROR(__xludf.DUMMYFUNCTION("""COMPUTED_VALUE"""),332.56) -> 332.56 | AE94: =IFERROR(__xludf.DUMMYFUNCTION("""COMPUTED_VALUE"""),"#VALUE!") -> #VALUE!
... N199: FALSE | Q199: Google | R199: GOOG | T199: 0 | U199: 0 | Z199: =IFERROR(__xludf.DUMMYFUNCTION("""COMPUTED_VALUE"""),"Google") -> Google | AA199: =IFERROR(__xludf.DUMMYFUNCTION("""COMPUTED_VALUE"""),"GOOG") -> GOOG | AC199: =IFERROR(__xludf.DUMMYFUNCTION("""COMPUTED_VALUE"""),332.56) -> 332.56 | AE199: =IFERROR(__xludf.DUMMYFUNCTION("""COMPUTED_VALUE"""),"#VALUE!") -> #VALUE!
N200: FALSE | Q200: SpaceX | R200: SPCX | T200: 0 | U200: 0 | Z200: =IFERROR(__xludf.DUMMYFUNCTION("""COMPUTED_VALUE"""),"SpaceX") -> SpaceX | AA200: =IFERROR(__xludf.DUMMYFUNCTION("""COMPUTED_VALUE"""),"SPCX") -> SPCX | AC200: =IFERROR(__xludf.DUMMYFUNCTION("""COMPUTED_VALUE"""),157.54) -> 157.54 | AE200: =IFERROR(__xludf.DUMMYFUNCTION("""COMPUTED_VALUE"""),"#VALUE!") -> #VALUE!
N201: FALSE | Q201: SpaceX | R201: SPCX | T201: 0 | U201: 0 | Z201: =IFERROR(__xludf.DUMMYFUNCTION("""COMPUTED_VALUE"""),"SpaceX") -> SpaceX | AA201: =IFERROR(__xludf.DUMMYFUNCTION("""COMPUTED_VALUE"""),"SPCX") -> SPCX | AC201: =IFERROR(__xludf.DUMMYFUNCTION("""COMPUTED_VALUE"""),157.54) -> 157.54 | AE201: =IFERROR(__xludf.DUMMYFUNCTION("""COMPUTED_VALUE"""),"#VALUE!") -> #VALUE!
N202: FALSE | Q202: SpaceX | R202: SPCX | T202: 0 | U202: 0 | Z202: =IFERROR(__xludf.DUMMYFUNCTION("""COMPUTED_VALUE"""),"SpaceX") -> SpaceX | AA202: =IFERROR(__xludf.DUMMYFUNCTION("""COMPUTED_VALUE"""),"SPCX") -> SPCX | AC202: =IFERROR(__xludf.DUMMYFUNCTION("""COMPUTED_VALUE"""),157.54) -> 157.54 | AE202: =IFERROR(__xludf.DUMMYFUNCTION("""COMPUTED_VALUE"""),"#VALUE!") -> #VALUE!
N203: FALSE | Q203: SpaceX | R203: SPCX | T203: 0 | U203: 0 | Z203: =IFERROR(__xludf.DUMMYFUNCTION("""COMPUTED_VALUE"""),"SpaceX") -> SpaceX | AA203: =IFERROR(__xludf.DUMMYFUNCTION("""COMPUTED_VALUE"""),"SPCX") -> SPCX | AC203: =IFERROR(__xludf.DUMMYFUNCTION("""COMPUTED_VALUE"""),157.54) -> 157.54 | AE203: =IFERROR(__xludf.DUMMYFUNCTION("""COMPUTED_VALUE"""),"#VALUE!") -> #VALUE!
N204: FALSE | Q204: SpaceX | R204: SPCX | T204: 0 | U204: 0 | Z204: =IFERROR(__xludf.DUMMYFUNCTION("""COMPUTED_VALUE"""),"SpaceX") -> SpaceX | AA204: =IFERROR(__xludf.DUMMYFUNCTION("""COMPUTED_VALUE"""),"SPCX") -> SPCX | AC204: =IFERROR(__xludf.DUMMYFUNCTION("""COMPUTED_VALUE"""),157.54) -> 157.54 | AE204: =IFERROR(__xludf.DUMMYFUNCTION("""COMPUTED_VALUE"""),"#VALUE!") -> #VALUE!
N205: FALSE
N206: FALSE
W210: Total | X210: Tax Free
W211: =130*1000 -> 130000 | X211: 2000
W212: =250*130 -> 32500 | X212: =250*4 -> 1000
W213: =SUM(W211:W212) -> 162500 | X213: =SUM(X211:X212) -> 3000
V216: Step one we need to makeup a captial gains income stream
V217: Selling Spcx and/goog to generate ~160k

Sheet Meeting notes
A1: 46213
B2: Lockout shares period
C3: Google until you leave you can't do options | F3: Create a Rule 10b5-1 trading plan
B5: Spending/income
C6: Lets update the cashflow sheet
B8: Volatility Strategy
C9: Options education | E9: https://youtu.be/gWp3op51ZzI | G9: https://youtu.be/hK_MP1RRU9w?list=PL8a6s5nq1lPRcGlhhMLSqx1BK1rttI00R
B10: Buy | C10: Puts | D10: Insurance | E10: You pay the premium
B11: sell | C11: Calls | D11: Income | E11: against shares you hold
B13: MAGI
C14: Only deductions are HSA, IRA against earned income(so never lowers MAGI)
C15: Business losses, Captial Gain losses.
C16: Max capital gain loss is $3k a year but carry over to future years if you go over.
B18: 1 Year Emergency Fund
C19: Low volatility low return just to make sure you always have 1 year available | H19: We will figure out how much
D20: SGOV or FLOT
A23: 46230 | C23: Intro | D23: Details
B24: Discount Cash Flow | C24: https://youtu.be/J8E64j-2pvc?si=7tfpNpnxoiDXXcuD | D24: https://youtu.be/CfkFFk-r9aA?si=mec-m6_s463gHC_2
C25: "How much should I pay today for the cash this business will generate in the future?"
C27: Imagine a magic machine that prints $100 a year for the next 10 years, and then it breaks. In total, it will print $1,000.
C29: If your neighbor offers to sell you this machine, what is a fair price?
C31: You definitely would not pay $1,000 for it. Why? Because you have to wait a full 10 years to get all your money. If you have $1,000 today, you could just put it in a savings account or an index fund, earn interest, and have way more than $1,000 in a decade.
C33: Because of that wait time, future money is worth less than present money. So, to buy that machine, you demand a discount for the wait. Maybe you decide you are only willing to pay $700 for it today.
C35: That thought process is exactly what a DCF model does for a stock, just with a few more moving parts.
B37: Types of income
C38: Income Bucket | D38: Tax Brackets Applied | E38: Subject to Payroll Taxes? | F38: Can be offset by Capital Losses?
C39: Earned Income | D39: Standard (Graduated) | E39: Yes (Social Security/Medicare) | F39: No
C41: Unearned Ordinary | D41: Standard (Graduated) | E41: No | F41: No
C42: Short-Term Capital Gains | D42: Standard (Graduated) | E42: No | F42: Yes
C43: Long-Term Capital Gains | D43: Preferential (0%, 15%, or 20%) | E43: No | F43: Yes
B45: Social Security
C46: Get your estimate
B48: Real estate
C49: No need for an LLC unless you have many properties
C50: Live in the home for 2 of 5 years for $250k exclusion on the capital gains
C51: Rent for 3 years and then sell it
C52: If you rent it beyond the 3 years you would lose the exclusion
C54: Earned income
D55: Things like bed and breakfast or AirBnB where you are providing services as well
C56: Unearned incom | D56: Rent
C57: ST CapGains | D57: Sell the asset under a year
C58: LT CapGains | D58: Sell after a year

Sheet Yearly Breakdown
A3: Category | B3: Item | C3: 2027 | D3: 2028 | E3: 2029 | F3: 2030 | G3: 2031 | H3: 2032 | I3: 2033 | J3: 2034 | K3: 2035 | L3: 2036 | M3: 2037
A4: Summary | B4: Beginning Balance | C4: =VLOOKUP(C$3, 'Retirement Projection'!$A:$U, 3, FALSE) -> 2912398 | D4: =VLOOKUP(D$3, 'Retirement Projection'!$A:$U, 3, FALSE) -> 2874574.7 | E4: =VLOOKUP(E$3, 'Retirement Projection'!$A:$U, 3, FALSE) -> 2833233.4 | F4: =VLOOKUP(F$3, 'Retirement Projection'!$A:$U, 3, FALSE) -> 2785596 | G4: =VLOOKUP(G$3, 'Retirement Projection'!$A:$U, 3, FALSE) -> 2731263.2 | H4: =VLOOKUP(H$3, 'Retirement Projection'!$A:$U, 3, FALSE) -> 2669782.4 | I4: =VLOOKUP(I$3, 'Retirement Projection'!$A:$U, 3, FALSE) -> 2600693.2 | J4: =VLOOKUP(J$3, 'Retirement Projection'!$A:$U, 3, FALSE) -> 2523524.7 | ... M4: =VLOOKUP(M$3, 'Retirement Projection'!$A:$U, 3, FALSE) -> 2238443.6
B5: Ending Balance | C5: =VLOOKUP(C$3, 'Retirement Projection'!$A:$U, 12, FALSE) -> 2874574.7 | D5: =VLOOKUP(D$3, 'Retirement Projection'!$A:$U, 12, FALSE) -> 2833233.4 | E5: =VLOOKUP(E$3, 'Retirement Projection'!$A:$U, 12, FALSE) -> 2785596 | F5: =VLOOKUP(F$3, 'Retirement Projection'!$A:$U, 12, FALSE) -> 2731263.2 | G5: =VLOOKUP(G$3, 'Retirement Projection'!$A:$U, 12, FALSE) -> 2669782.4 | H5: =VLOOKUP(H$3, 'Retirement Projection'!$A:$U, 12, FALSE) -> 2600693.2 | I5: =VLOOKUP(I$3, 'Retirement Projection'!$A:$U, 12, FALSE) -> 2523524.7 | J5: =VLOOKUP(J$3, 'Retirement Projection'!$A:$U, 12, FALSE) -> 2437780.4 | ... M5: =VLOOKUP(M$3, 'Retirement Projection'!$A:$U, 12, FALSE) -> 2123719.2
B6: Networth | C6: =VLOOKUP(C$3, 'Retirement Projection'!$A:$U, 21, FALSE) -> 3502436.3 | D6: =VLOOKUP(D$3, 'Retirement Projection'!$A:$U, 21, FALSE) -> 3496231 | E6: =VLOOKUP(E$3, 'Retirement Projection'!$A:$U, 21, FALSE) -> 3484932.8 | F6: =VLOOKUP(F$3, 'Retirement Projection'!$A:$U, 21, FALSE) -> 3468187.4 | G6: =VLOOKUP(G$3, 'Retirement Projection'!$A:$U, 21, FALSE) -> 3445588.8 | H6: =VLOOKUP(H$3, 'Retirement Projection'!$A:$U, 21, FALSE) -> 3416725.6 | I6: =VLOOKUP(I$3, 'Retirement Projection'!$A:$U, 21, FALSE) -> 3381177.3 | J6: =VLOOKUP(J$3, 'Retirement Projection'!$A:$U, 21, FALSE) -> 3338500.6 | ... M6: =VLOOKUP(M$3, 'Retirement Projection'!$A:$U, 21, FALSE) -> 3162889.2
A8: Income | B8: Earned income | C8: 0 | D8: 0 | E8: 0 | F8: 0 | G8: 0 | H8: 0 | I8: 0 | J8: 0 | K8: 0 | L8: 0 | M8: 0
A9: Income | B9: Dividends (60 day hold) | C9: 0 | D9: 0 | E9: 0 | F9: 0 | G9: 0 | H9: 0 | I9: 0 | J9: 0 | K9: 0 | L9: 0 | M9: 0
A10: Income | B10: Rental | C10: 0 | D10: 0 | E10: 0 | F10: 0 | G10: 0 | H10: 0 | I10: 0 | J10: 0 | K10: 0 | L10: 0 | M10: 0
A11: Income | B11: Options | C11: 0 | D11: 0 | E11: 0 | F11: 0 | G11: 0 | H11: 0 | I11: 0 | J11: 0 | K11: 0 | L11: 0 | M11: 0
A12: Income | B12: Interest | C12: 0 | D12: 0 | E12: 0 | F12: 0 | G12: 0 | H12: 0 | I12: 0 | J12: 0 | K12: 0 | L12: 0 | M12: 0
A13: Income | B13: Other | C13: 0 | D13: 0 | E13: 0 | F13: 0 | G13: 0 | H13: 0 | I13: 0 | J13: 0 | K13: 0 | L13: 0 | M13: 0
A14: Income | B14: GOOG Sales Income | C14: =SUMIFS(C$48:C$1083, $B$48:$B$1083, "Realized Gain/Loss") -> 170326.48 | D14: =SUMIFS(D$48:D$1083, $B$48:$B$1083, "Realized Gain/Loss") -> 90196.919 | E14: =SUMIFS(E$48:E$1083, $B$48:$B$1083, "Realized Gain/Loss") -> 0 | F14: =SUMIFS(F$48:F$1083, $B$48:$B$1083, "Realized Gain/Loss") -> 0 | G14: =SUMIFS(G$48:G$1083, $B$48:$B$1083, "Realized Gain/Loss") -> 0 | H14: =SUMIFS(H$48:H$1083, $B$48:$B$1083, "Realized Gain/Loss") -> 0 | I14: =SUMIFS(I$48:I$1083, $B$48:$B$1083, "Realized Gain/Loss") -> 0 | J14: =SUMIFS(J$48:J$1083, $B$48:$B$1083, "Realized Gain/Loss") -> 0 | ... M14: =SUMIFS(M$48:M$1083, $B$48:$B$1083, "Realized Gain/Loss") -> 0
A15: Income | B15: SPCX Sales Income | C15: =SUMIFS(C$1085:C$1134, $B$1085:$B$1134, "Realized Gain/Loss") -> 0 | D15: =SUMIFS(D$1085:D$1134, $B$1085:$B$1134, "Realized Gain/Loss") -> 0 | E15: =SUMIFS(E$1085:E$1134, $B$1085:$B$1134, "Realized Gain/Loss") -> 171248 | F15: =SUMIFS(F$1085:F$1134, $B$1085:$B$1134, "Realized Gain/Loss") -> 175140 | G15: =SUMIFS(G$1085:G$1134, $B$1085:$B$1134, "Realized Gain/Loss") -> 180005 | H15: =SUMIFS(H$1085:H$1134, $B$1085:$B$1134, "Realized Gain/Loss") -> 182437.5 | I15: =SUMIFS(I$1085:I$1134, $B$1085:$B$1134, "Realized Gain/Loss") -> 184870 | J15: =SUMIFS(J$1085:J$1134, $B$1085:$B$1134, "Realized Gain/Loss") -> 189735 | ... M15: =SUMIFS(M$1085:M$1134, $B$1085:$B$1134, "Realized Gain/Loss") -> 201897.5
A16: Income | B16: Tax-Free Principal from Sales | C16: =SUMIFS(C$48:C2072, $B$48:$B2072, "Cost Basis Used") -> 120835.37 | D16: =SUMIFS(D$48:D2072, $B$48:$B2072, "Cost Basis Used") -> 92973.481 | E16: =SUMIFS(E$48:E2072, $B$48:$B2072, "Cost Basis Used") -> 4752 | F16: =SUMIFS(F$48:F2072, $B$48:$B2072, "Cost Basis Used") -> 4860 | G16: =SUMIFS(G$48:G2072, $B$48:$B2072, "Cost Basis Used") -> 4995 | H16: =SUMIFS(H$48:H2072, $B$48:$B2072, "Cost Basis Used") -> 5062.5 | I16: =SUMIFS(I$48:I2072, $B$48:$B2072, "Cost Basis Used") -> 5130 | J16: =SUMIFS(J$48:J2072, $B$48:$B2072, "Cost Basis Used") -> 5265 | ... M16: =SUMIFS(M$48:M2072, $B$48:$B2072, "Cost Basis Used") -> 5602.5
A17: Income | B17: Total Income | C17: =C14+C9+C10+C11+C12+C13+C8 -> 170326.48 | D17: =SUM(D9:D16) -> 183170.4 | E17: =SUM(E9:E16) -> 176000 | F17: =SUM(F9:F16) -> 180000 | G17: =SUM(G9:G16) -> 185000 | H17: =SUM(H9:H16) -> 187500 | I17: =SUM(I9:I16) -> 190000 | J17: =SUM(J9:J16) -> 195000 | K17: =SUM(K9:K16) -> 197500 | ... M17: =SUM(M9:M16) -> 207500
A19: Taxes | B19: Earned | C19: =C8 -> 0 | D19: =D8 -> 0 | E19: =E8 -> 0 | F19: =F8 -> 0 | G19: =G8 -> 0 | H19: =H8 -> 0 | I19: =I8 -> 0 | J19: =J8 -> 0 | ... M19: =M8 -> 0
B20: Unearned | C20: =C10+C11+C12 -> 0 | D20: =D10+D11+D12 -> 0 | E20: =E10+E11+E12 -> 0 | F20: =F10+F11+F12 -> 0 | G20: =G10+G11+G12 -> 0 | H20: =H10+H11+H12 -> 0 | I20: =I10+I11+I12 -> 0 | J20: =J10+J11+J12 -> 0 | ... M20: =M10+M11+M12 -> 0
B21: Short Term CapGains
B22: Long Term CapGains | C22: =(C14+C15)-C16 -> 49491.12 | D22: =(D14+D15)-D16 -> -2776.5615 | E22: =(E14+E15)-E16 -> 166496 | F22: =(F14+F15)-F16 -> 170280 | G22: =(G14+G15)-G16 -> 175010 | H22: =(H14+H15)-H16 -> 177375 | I22: =(I14+I15)-I16 -> 179740 | J22: =(J14+J15)-J16 -> 184470 | ... M22: =(M14+M15)-M16 -> 196295
A24: Deductions | B24: SALT
B25: CAP Gains | C25: ='Retirement Projection'!N2 -> 50490 | D25: ='Retirement Projection'!N3 -> 51499.8 | E25: ='Retirement Projection'!N4 -> 52529.796 | F25: ='Retirement Projection'!N5 -> 53580.392 | G25: ='Retirement Projection'!N6 -> 54652 | H25: ='Retirement Projection'!N7 -> 55745.04 | I25: ='Retirement Projection'!N8 -> 56859.941 | J25: ='Retirement Projection'!N9 -> 57997.139 | K25: ='Retirement Projection'!N10 -> 59157.082 | L25: ='Retirement Projection'!N11 -> 60340.224 | M25: ='Retirement Projection'!N12 -> 61547.028
A27: AGI | C27: =C22-C25 -> -998.88038 | D27: =D22-D25 -> -54276.361 | E27: =E22-E25 -> 113966.2 | F27: =F22-F25 -> 116699.61 | G27: =G22-G25 -> 120358 | H27: =H22-H25 -> 121629.96 | I27: =I22-I25 -> 122880.06 | J27: =J22-J25 -> 126472.86 | ... M27: =M22-M25 -> 134747.97
A29: Expense | B29: Total Expense | C29: =SUM(C30:C35) -> 169380.67 | D29: =SUM(D30:D35) -> 172768.28 | E29: =SUM(E30:E35) -> 176223.65 | F29: =SUM(F30:F35) -> 179748.12 | G29: =SUM(G30:G35) -> 183343.08 | H29: =SUM(H30:H35) -> 187009.95 | I29: =SUM(I30:I35) -> 190750.14 | J29: =SUM(J30:J35) -> 194565.15 | ... M29: =SUM(M30:M35) -> 206474.09
A30: {=IF(B30:B35<>"", "Expense", "")} -> Expense | B30: =IFERROR(__xludf.DUMMYFUNCTION("UNIQUE(FILTER('05 Cash Flow'!B5:B2072, '05 Cash Flow'!A5:A2072=""Expense""))"),"Mortgage") -> Mortgage | C30: =IF($B30="","", SUMIFS('05 Cash Flow'!$G:$G, '05 Cash Flow'!$B:$B, $B30) * (1 + '02 Assumptions'!$B$5)) -> 28571.71 | D30: =IF($B30="","", C30 * (1 + '02 Assumptions'!$B$5)) -> 29143.144 | E30: =IF($B30="","", D30 * (1 + '02 Assumptions'!$B$5)) -> 29726.007 | F30: =IF($B30="","", E30 * (1 + '02 Assumptions'!$B$5)) -> 30320.527 | G30: =IF($B30="","", F30 * (1 + '02 Assumptions'!$B$5)) -> 30926.937 | H30: =IF($B30="","", G30 * (1 + '02 Assumptions'!$B$5)) -> 31545.476 | I30: =IF($B30="","", H30 * (1 + '02 Assumptions'!$B$5)) -> 32176.386 | J30: =IF($B30="","", I30 * (1 + '02 Assumptions'!$B$5)) -> 32819.913 | K30: =IF($B30="","", J30 * (1 + '02 Assumptions'!$B$5)) -> 33476.312 | ... M30: =IF($B30="","", L30 * (1 + '02 Assumptions'!$B$5)) -> 34828.755
A31: Expense | B31: =IFERROR(__xludf.DUMMYFUNCTION("""COMPUTED_VALUE"""),"Home") -> Home | C31: =IF($B31="","", SUMIFS('05 Cash Flow'!$G:$G, '05 Cash Flow'!$B:$B, $B31) * (1 + '02 Assumptions'!$B$5)) -> 71432.64 | D31: =IF($B31="","", C31 * (1 + '02 Assumptions'!$B$5)) -> 72861.293 | E31: =IF($B31="","", D31 * (1 + '02 Assumptions'!$B$5)) -> 74318.519 | F31: =IF($B31="","", E31 * (1 + '02 Assumptions'!$B$5)) -> 75804.889 | G31: =IF($B31="","", F31 * (1 + '02 Assumptions'!$B$5)) -> 77320.987 | H31: =IF($B31="","", G31 * (1 + '02 Assumptions'!$B$5)) -> 78867.407 | I31: =IF($B31="","", H31 * (1 + '02 Assumptions'!$B$5)) -> 80444.755 | J31: =IF($B31="","", I31 * (1 + '02 Assumptions'!$B$5)) -> 82053.65 | K31: =IF($B31="","", J31 * (1 + '02 Assumptions'!$B$5)) -> 83694.723 | ... M31: =IF($B31="","", L31 * (1 + '02 Assumptions'!$B$5)) -> 87075.99
A32: Expense | B32: =IFERROR(__xludf.DUMMYFUNCTION("""COMPUTED_VALUE"""),"Groceries") -> Groceries | C32: =IF($B32="","", SUMIFS('05 Cash Flow'!$G:$G, '05 Cash Flow'!$B:$B, $B32) * (1 + '02 Assumptions'!$B$5)) -> 12509.28 | D32: =IF($B32="","", C32 * (1 + '02 Assumptions'!$B$5)) -> 12759.466 | E32: =IF($B32="","", D32 * (1 + '02 Assumptions'!$B$5)) -> 13014.655 | F32: =IF($B32="","", E32 * (1 + '02 Assumptions'!$B$5)) -> 13274.948 | G32: =IF($B32="","", F32 * (1 + '02 Assumptions'!$B$5)) -> 13540.447 | H32: =IF($B32="","", G32 * (1 + '02 Assumptions'!$B$5)) -> 13811.256 | I32: =IF($B32="","", H32 * (1 + '02 Assumptions'!$B$5)) -> 14087.481 | J32: =IF($B32="","", I32 * (1 + '02 Assumptions'!$B$5)) -> 14369.231 | K32: =IF($B32="","", J32 * (1 + '02 Assumptions'!$B$5)) -> 14656.615 | ... M32: =IF($B32="","", L32 * (1 + '02 Assumptions'!$B$5)) -> 15248.743
A33: Expense | B33: =IFERROR(__xludf.DUMMYFUNCTION("""COMPUTED_VALUE"""),"Shopping/Entertainment") -> Shopping/Entertainment | C33: =IF($B33="","", SUMIFS('05 Cash Flow'!$G:$G, '05 Cash Flow'!$B:$B, $B33) * (1 + '02 Assumptions'!$B$5)) -> 28152 | D33: =IF($B33="","", C33 * (1 + '02 Assumptions'!$B$5)) -> 28715.04 | E33: =IF($B33="","", D33 * (1 + '02 Assumptions'!$B$5)) -> 29289.341 | F33: =IF($B33="","", E33 * (1 + '02 Assumptions'!$B$5)) -> 29875.128 | G33: =IF($B33="","", F33 * (1 + '02 Assumptions'!$B$5)) -> 30472.63 | H33: =IF($B33="","", G33 * (1 + '02 Assumptions'!$B$5)) -> 31082.083 | I33: =IF($B33="","", H33 * (1 + '02 Assumptions'!$B$5)) -> 31703.724 | J33: =IF($B33="","", I33 * (1 + '02 Assumptions'!$B$5)) -> 32337.799 | K33: =IF($B33="","", J33 * (1 + '02 Assumptions'!$B$5)) -> 32984.555 | ... M33: =IF($B33="","", L33 * (1 + '02 Assumptions'!$B$5)) -> 34317.131
A34: Expense | B34: =IFERROR(__xludf.DUMMYFUNCTION("""COMPUTED_VALUE"""),"Other") -> Other | C34: =IF($B34="","", SUMIFS('05 Cash Flow'!$G:$G, '05 Cash Flow'!$B:$B, $B34) * (1 + '02 Assumptions'!$B$5)) -> 10355.04 | D34: =IF($B34="","", C34 * (1 + '02 Assumptions'!$B$5)) -> 10562.141 | E34: =IF($B34="","", D34 * (1 + '02 Assumptions'!$B$5)) -> 10773.384 | F34: =IF($B34="","", E34 * (1 + '02 Assumptions'!$B$5)) -> 10988.851 | G34: =IF($B34="","", F34 * (1 + '02 Assumptions'!$B$5)) -> 11208.628 | H34: =IF($B34="","", G34 * (1 + '02 Assumptions'!$B$5)) -> 11432.801 | I34: =IF($B34="","", H34 * (1 + '02 Assumptions'!$B$5)) -> 11661.457 | J34: =IF($B34="","", I34 * (1 + '02 Assumptions'!$B$5)) -> 11894.686 | K34: =IF($B34="","", J34 * (1 + '02 Assumptions'!$B$5)) -> 12132.58 | ... M34: =IF($B34="","", L34 * (1 + '02 Assumptions'!$B$5)) -> 12622.736
A35: Expense | B35: =IFERROR(__xludf.DUMMYFUNCTION("""COMPUTED_VALUE"""),"Health") -> Health | C35: =IF($B35="","", SUMIFS('05 Cash Flow'!$G:$G, '05 Cash Flow'!$B:$B, $B35) * (1 + '02 Assumptions'!$B$5)) -> 18360 | D35: =IF($B35="","", C35 * (1 + '02 Assumptions'!$B$5)) -> 18727.2 | E35: =IF($B35="","", D35 * (1 + '02 Assumptions'!$B$5)) -> 19101.744 | F35: =IF($B35="","", E35 * (1 + '02 Assumptions'!$B$5)) -> 19483.779 | G35: =IF($B35="","", F35 * (1 + '02 Assumptions'!$B$5)) -> 19873.454 | H35: =IF($B35="","", G35 * (1 + '02 Assumptions'!$B$5)) -> 20270.924 | I35: =IF($B35="","", H35 * (1 + '02 Assumptions'!$B$5)) -> 20676.342 | J35: =IF($B35="","", I35 * (1 + '02 Assumptions'!$B$5)) -> 21089.869 | K35: =IF($B35="","", J35 * (1 + '02 Assumptions'!$B$5)) -> 21511.666 | ... M35: =IF($B35="","", L35 * (1 + '02 Assumptions'!$B$5)) -> 22380.738
C36: =IF($B36="","", SUMIFS('05 Cash Flow'!$G:$G, '05 Cash Flow'!$B:$B, $B36) * (1 + '02 Assumptions'!$B$5)) | D36: =IF($B36="","", C36 * (1 + '02 Assumptions'!$B$5)) | E36: =IF($B36="","", D36 * (1 + '02 Assumptions'!$B$5)) | F36: =IF($B36="","", E36 * (1 + '02 Assumptions'!$B$5)) | G36: =IF($B36="","", F36 * (1 + '02 Assumptions'!$B$5)) | H36: =IF($B36="","", G36 * (1 + '02 Assumptions'!$B$5)) | I36: =IF($B36="","", H36 * (1 + '02 Assumptions'!$B$5)) | J36: =IF($B36="","", I36 * (1 + '02 Assumptions'!$B$5)) | K36: =IF($B36="","", J36 * (1 + '02 Assumptions'!$B$5)) | ... M36: =IF($B36="","", L36 * (1 + '02 Assumptions'!$B$5))
A37: Net Cash Flow | C37: =C17-C29 -> 945.81521 | D37: =D17-D29 -> 10402.117 | E37: =E17-E29 -> -223.64865 | F37: =F17-F29 -> 251.87838 | G37: =G17-G29 -> 1656.9159 | H37: =H17-H29 -> 490.05426 | I37: =I17-I29 -> -750.14465 | J37: =J17-J29 -> 434.85245 | ... M37: =M17-M29 -> 1025.9089
C38: =IF($B38="","", SUMIFS('05 Cash Flow'!$G:$G, '05 Cash Flow'!$B:$B, $B38) * (1 + '02 Assumptions'!$B$5)) | D38: =IF($B38="","", C38 * (1 + '02 Assumptions'!$B$5)) | E38: =IF($B38="","", D38 * (1 + '02 Assumptions'!$B$5)) | F38: =IF($B38="","", E38 * (1 + '02 Assumptions'!$B$5)) | G38: =IF($B38="","", F38 * (1 + '02 Assumptions'!$B$5)) | H38: =IF($B38="","", G38 * (1 + '02 Assumptions'!$B$5)) | I38: =IF($B38="","", H38 * (1 + '02 Assumptions'!$B$5)) | J38: =IF($B38="","", I38 * (1 + '02 Assumptions'!$B$5)) | K38: =IF($B38="","", J38 * (1 + '02 Assumptions'!$B$5)) | ... M38: =IF($B38="","", L38 * (1 + '02 Assumptions'!$B$5))
C39: =IF($B39="","", SUMIFS('05 Cash Flow'!$G:$G, '05 Cash Flow'!$B:$B, $B39) * (1 + '02 Assumptions'!$B$5)) | D39: =IF($B39="","", C39 * (1 + '02 Assumptions'!$B$5)) | E39: =IF($B39="","", D39 * (1 + '02 Assumptions'!$B$5)) | F39: =IF($B39="","", E39 * (1 + '02 Assumptions'!$B$5)) | G39: =IF($B39="","", F39 * (1 + '02 Assumptions'!$B$5)) | H39: =IF($B39="","", G39 * (1 + '02 Assumptions'!$B$5)) | I39: =IF($B39="","", H39 * (1 + '02 Assumptions'!$B$5)) | J39: =IF($B39="","", I39 * (1 + '02 Assumptions'!$B$5)) | K39: =IF($B39="","", J39 * (1 + '02 Assumptions'!$B$5)) | ... M39: =IF($B39="","", L39 * (1 + '02 Assumptions'!$B$5))
A40: Net Cash Flow | B40: Total Net Cash Flow | C40: =C17 - C29 -> 945.81521 | D40: =D17 - D29 -> 10402.117 | E40: =E17 - E29 -> -223.64865 | F40: =F17 - F29 -> 251.87838 | G40: =G17 - G29 -> 1656.9159 | H40: =H17 - H29 -> 490.05426 | I40: =I17 - I29 -> -750.14465 | J40: =J17 - J29 -> 434.85245 | ... M40: =M17 - M29 -> 1025.9089
B42: GOOG Sale Price | C42: 350
B43: SPCX Sale Price | C43: 100
B44: Total GOOG Shares Remaining | C44: =SUMIFS(C$48:C$1083, $B$48:$B$1083, "Remaining Shares") -> 585.032 | D44: =SUMIFS(D$48:D$1083, $B$48:$B$1083, "Remaining Shares") -> 61.688 | E44: =SUMIFS(E$48:E$1083, $B$48:$B$1083, "Remaining Shares") -> 61.688 | F44: =SUMIFS(F$48:F$1083, $B$48:$B$1083, "Remaining Shares") -> 61.688 | G44: =SUMIFS(G$48:G$1083, $B$48:$B$1083, "Remaining Shares") -> 61.688 | H44: =SUMIFS(H$48:H$1083, $B$48:$B$1083, "Remaining Shares") -> 61.688 | I44: =SUMIFS(I$48:I$1083, $B$48:$B$1083, "Remaining Shares") -> 61.688 | J44: =SUMIFS(J$48:J$1083, $B$48:$B$1083, "Remaining Shares") -> 61.688 | ... M44: =SUMIFS(M$48:M$1083, $B$48:$B$1083, "Remaining Shares") -> 61.688
B45: Total SPCX Shares Remaining | C45: =SUMIFS(C$1085:C$1134, $B$1085:$B$1134, "Remaining Shares") -> 30250 | D45: =SUMIFS(D$1085:D$1134, $B$1085:$B$1134, "Remaining Shares") -> 30250 | E45: =SUMIFS(E$1085:E$1134, $B$1085:$B$1134, "Remaining Shares") -> 28490 | F45: =SUMIFS(F$1085:F$1134, $B$1085:$B$1134, "Remaining Shares") -> 26690 | G45: =SUMIFS(G$1085:G$1134, $B$1085:$B$1134, "Remaining Shares") -> 24840 | H45: =SUMIFS(H$1085:H$1134, $B$1085:$B$1134, "Remaining Shares") -> 22965 | I45: =SUMIFS(I$1085:I$1134, $B$1085:$B$1134, "Remaining Shares") -> 21065 | J45: =SUMIFS(J$1085:J$1134, $B$1085:$B$1134, "Remaining Shares") -> 19115 | ... M45: =SUMIFS(M$1085:M$1134, $B$1085:$B$1134, "Remaining Shares") -> 13040
A47: Tax Lots | B47: 2026
A48: Tax Lots | B48: GOOG Lot 1
B49: Acquisition Date | C49: =DATE(2026,6,25) -> 46198
B50: Total Starting Shares | C50: 4.784
B51: Cost Basis Per Share | C51: 345.04
B52: Total Cost Basis | C52: =C50*C51 -> 1650.6714
B53: Sell All? | C53: FALSE | D53: TRUE | E53: FALSE | F53: FALSE | G53: FALSE | H53: FALSE | I53: FALSE | J53: FALSE | K53: FALSE | L53: FALSE | M53: FALSE
B54: Manual Shares Sold | C54: 0 | D54: 0 | E54: 0 | F54: 0 | G54: 0 | H54: 0 | I54: 0 | J54: 0 | K54: 0 | L54: 0 | M54: 0
B55: Shares Sold | C55: =IF(C53, C50, C54) -> 0 | D55: =IF(D53, C59, D54) -> 4.784 | E55: =IF(E53, D59, E54) -> 0 | F55: =IF(F53, E59, F54) -> 0 | G55: =IF(G53, F59, G54) -> 0 | H55: =IF(H53, G59, H54) -> 0 | I55: =IF(I53, H59, I54) -> 0 | J55: =IF(J53, I59, J54) -> 0 | K55: =IF(K53, J59, K54) -> 0 | ... M55: =IF(M53, L59, M54) -> 0
B56: Sale Price | C56: =$C$42 -> 350 | D56: =$C$42 -> 350 | E56: =$C$42 -> 350 | F56: =$C$42 -> 350 | G56: =$C$42 -> 350 | H56: =$C$42 -> 350 | I56: =$C$42 -> 350 | J56: =$C$42 -> 350 | ... M56: =$C$42 -> 350
B57: Cost Basis Used | C57: =C55*$C51 -> 0 | D57: =D55*$C51 -> 1650.6714 | E57: =E55*$C51 -> 0 | F57: =F55*$C51 -> 0 | G57: =G55*$C51 -> 0 | H57: =H55*$C51 -> 0 | I57: =I55*$C51 -> 0 | J57: =J55*$C51 -> 0 | ... M57: =M55*$C51 -> 0
B58: Realized Gain/Loss | C58: =C55*C56-C57 -> 0 | D58: =D55*D56-D57 -> 23.72864 | E58: =E55*E56-E57 -> 0 | F58: =F55*F56-F57 -> 0 | G58: =G55*G56-G57 -> 0 | H58: =H55*H56-H57 -> 0 | I58: =I55*I56-I57 -> 0 | J58: =J55*J56-J57 -> 0 | ... M58: =M55*M56-M57 -> 0
B59: Remaining Shares | C59: =IF(COLUMN()=3, $C50-C55, B59-C55) -> 4.784 | D59: =IF(COLUMN()=3, $C50-D55, C59-D55) -> 0 | E59: =IF(COLUMN()=3, $C50-E55, D59-E55) -> 0 | F59: =IF(COLUMN()=3, $C50-F55, E59-F55) -> 0 | G59: =IF(COLUMN()=3, $C50-G55, F59-G55) -> 0 | H59: =IF(COLUMN()=3, $C50-H55, G59-H55) -> 0 | I59: =IF(COLUMN()=3, $C50-I55, H59-I55) -> 0 | J59: =IF(COLUMN()=3, $C50-J55, I59-J55) -> 0 | ... M59: =IF(COLUMN()=3, $C50-M55, L59-M55) -> 0
A60: Tax Lots | B60: GOOG Lot 2
B61: Acquisition Date | C61: =DATE(2026,6,25) -> 46198
B62: Total Starting Shares | C62: 4.2
B63: Cost Basis Per Share | C63: 345.04
B64: Total Cost Basis | C64: =C62*C63 -> 1449.168
B65: Sell All? | C65: FALSE | D65: TRUE | E65: FALSE | F65: FALSE | G65: FALSE | H65: FALSE | I65: FALSE | J65: FALSE | K65: FALSE | L65: FALSE | M65: FALSE
B66: Manual Shares Sold | C66: 0 | D66: 0 | E66: 0 | F66: 0 | G66: 0 | H66: 0 | I66: 0 | J66: 0 | K66: 0 | L66: 0 | M66: 0
B67: Shares Sold | C67: =IF(C65, C62, C66) -> 0 | D67: =IF(D65, C71, D66) -> 4.2 | E67: =IF(E65, D71, E66) -> 0 | F67: =IF(F65, E71, F66) -> 0 | G67: =IF(G65, F71, G66) -> 0 | H67: =IF(H65, G71, H66) -> 0 | I67: =IF(I65, H71, I66) -> 0 | J67: =IF(J65, I71, J66) -> 0 | K67: =IF(K65, J71, K66) -> 0 | ... M67: =IF(M65, L71, M66) -> 0
B68: Sale Price | C68: =$C$42 -> 350 | D68: =$C$42 -> 350 | E68: =$C$42 -> 350 | F68: =$C$42 -> 350 | G68: =$C$42 -> 350 | H68: =$C$42 -> 350 | I68: =$C$42 -> 350 | J68: =$C$42 -> 350 | ... M68: =$C$42 -> 350
B69: Cost Basis Used | C69: =C67*$C63 -> 0 | D69: =D67*$C63 -> 1449.168 | E69: =E67*$C63 -> 0 | F69: =F67*$C63 -> 0 | G69: =G67*$C63 -> 0 | H69: =H67*$C63 -> 0 | I69: =I67*$C63 -> 0 | J69: =J67*$C63 -> 0 | ... M69: =M67*$C63 -> 0
B70: Realized Gain/Loss | C70: =C67*C68-C69 -> 0 | D70: =D67*D68-D69 -> 20.832 | E70: =E67*E68-E69 -> 0 | F70: =F67*F68-F69 -> 0 | G70: =G67*G68-G69 -> 0 | H70: =H67*H68-H69 -> 0 | I70: =I67*I68-I69 -> 0 | J70: =J67*J68-J69 -> 0 | ... M70: =M67*M68-M69 -> 0
B71: Remaining Shares | C71: =IF(COLUMN()=3, $C62-C67, B71-C67) -> 4.2 | D71: =IF(COLUMN()=3, $C62-D67, C71-D67) -> 0 | E71: =IF(COLUMN()=3, $C62-E67, D71-E67) -> 0 | F71: =IF(COLUMN()=3, $C62-F67, E71-F67) -> 0 | G71: =IF(COLUMN()=3, $C62-G67, F71-G67) -> 0 | H71: =IF(COLUMN()=3, $C62-H67, G71-H67) -> 0 | I71: =IF(COLUMN()=3, $C62-I67, H71-I67) -> 0 | J71: =IF(COLUMN()=3, $C62-J67, I71-J67) -> 0 | ... M71: =IF(COLUMN()=3, $C62-M67, L71-M67) -> 0
A72: Tax Lots | B72: GOOG Lot 3
B73: Acquisition Date | C73: =DATE(2026,5,25) -> 46167
B74: Total Starting Shares | C74: 9.591
B75: Cost Basis Per Share | C75: 379.38
B76: Total Cost Basis | C76: =C74*C75 -> 3638.6336
B77: Sell All? | C77: FALSE | D77: FALSE | E77: FALSE | F77: FALSE | G77: FALSE | H77: FALSE | I77: FALSE | J77: FALSE | K77: FALSE | L77: FALSE | M77: FALSE
B78: Manual Shares Sold | C78: 0 | D78: 0 | E78: 0 | F78: 0 | G78: 0 | H78: 0 | I78: 0 | J78: 0 | K78: 0 | L78: 0 | M78: 0
B79: Shares Sold | C79: =IF(C77, C74, C78) -> 0 | D79: =IF(D77, C83, D78) -> 0 | E79: =IF(E77, D83, E78) -> 0 | F79: =IF(F77, E83, F78) -> 0 | G79: =IF(G77, F83, G78) -> 0 | H79: =IF(H77, G83, H78) -> 0 | I79: =IF(I77, H83, I78) -> 0 | J79: =IF(J77, I83, J78) -> 0 | K79: =IF(K77, J83, K78) -> 0 | ... M79: =IF(M77, L83, M78) -> 0
B80: Sale Price | C80: =$C$42 -> 350 | D80: =$C$42 -> 350 | E80: =$C$42 -> 350 | F80: =$C$42 -> 350 | G80: =$C$42 -> 350 | H80: =$C$42 -> 350 | I80: =$C$42 -> 350 | J80: =$C$42 -> 350 | ... M80: =$C$42 -> 350
B81: Cost Basis Used | C81: =C79*$C75 -> 0 | D81: =D79*$C75 -> 0 | E81: =E79*$C75 -> 0 | F81: =F79*$C75 -> 0 | G81: =G79*$C75 -> 0 | H81: =H79*$C75 -> 0 | I81: =I79*$C75 -> 0 | J81: =J79*$C75 -> 0 | ... M81: =M79*$C75 -> 0
B82: Realized Gain/Loss | C82: =C79*C80-C81 -> 0 | D82: =D79*D80-D81 -> 0 | E82: =E79*E80-E81 -> 0 | F82: =F79*F80-F81 -> 0 | G82: =G79*G80-G81 -> 0 | H82: =H79*H80-H81 -> 0 | I82: =I79*I80-I81 -> 0 | J82: =J79*J80-J81 -> 0 | ... M82: =M79*M80-M81 -> 0
B83: Remaining Shares | C83: =IF(COLUMN()=3, $C74-C79, B83-C79) -> 9.591 | D83: =IF(COLUMN()=3, $C74-D79, C83-D79) -> 9.591 | E83: =IF(COLUMN()=3, $C74-E79, D83-E79) -> 9.591 | F83: =IF(COLUMN()=3, $C74-F79, E83-F79) -> 9.591 | G83: =IF(COLUMN()=3, $C74-G79, F83-G79) -> 9.591 | H83: =IF(COLUMN()=3, $C74-H79, G83-H79) -> 9.591 | I83: =IF(COLUMN()=3, $C74-I79, H83-I79) -> 9.591 | J83: =IF(COLUMN()=3, $C74-J79, I83-J79) -> 9.591 | ... M83: =IF(COLUMN()=3, $C74-M79, L83-M79) -> 9.591
A84: Tax Lots | B84: GOOG Lot 4
B85: Acquisition Date | C85: =DATE(2026,5,25) -> 46167
B86: Total Starting Shares | C86: 4.182
B87: Cost Basis Per Share | C87: 379.38
B88: Total Cost Basis | C88: =C86*C87 -> 1586.5672
B89: Sell All? | C89: FALSE | D89: FALSE | E89: FALSE | F89: FALSE | G89: FALSE | H89: FALSE | I89: FALSE | J89: FALSE | K89: FALSE | L89: FALSE | M89: FALSE
B90: Manual Shares Sold | C90: 0 | D90: 0 | E90: 0 | F90: 0 | G90: 0 | H90: 0 | I90: 0 | J90: 0 | K90: 0 | L90: 0 | M90: 0
B91: Shares Sold | C91: =IF(C89, C86, C90) -> 0 | D91: =IF(D89, C95, D90) -> 0 | E91: =IF(E89, D95, E90) -> 0 | F91: =IF(F89, E95, F90) -> 0 | G91: =IF(G89, F95, G90) -> 0 | H91: =IF(H89, G95, H90) -> 0 | I91: =IF(I89, H95, I90) -> 0 | J91: =IF(J89, I95, J90) -> 0 | K91: =IF(K89, J95, K90) -> 0 | ... M91: =IF(M89, L95, M90) -> 0
B92: Sale Price | C92: =$C$42 -> 350 | D92: =$C$42 -> 350 | E92: =$C$42 -> 350 | F92: =$C$42 -> 350 | G92: =$C$42 -> 350 | H92: =$C$42 -> 350 | I92: =$C$42 -> 350 | J92: =$C$42 -> 350 | ... M92: =$C$42 -> 350
B93: Cost Basis Used | C93: =C91*$C87 -> 0 | D93: =D91*$C87 -> 0 | E93: =E91*$C87 -> 0 | F93: =F91*$C87 -> 0 | G93: =G91*$C87 -> 0 | H93: =H91*$C87 -> 0 | I93: =I91*$C87 -> 0 | J93: =J91*$C87 -> 0 | ... M93: =M91*$C87 -> 0
B94: Realized Gain/Loss | C94: =C91*C92-C93 -> 0 | D94: =D91*D92-D93 -> 0 | E94: =E91*E92-E93 -> 0 | F94: =F91*F92-F93 -> 0 | G94: =G91*G92-G93 -> 0 | H94: =H91*H92-H93 -> 0 | I94: =I91*I92-I93 -> 0 | J94: =J91*J92-J93 -> 0 | ... M94: =M91*M92-M93 -> 0
B95: Remaining Shares | C95: =IF(COLUMN()=3, $C86-C91, B95-C91) -> 4.182 | D95: =IF(COLUMN()=3, $C86-D91, C95-D91) -> 4.182 | E95: =IF(COLUMN()=3, $C86-E91, D95-E91) -> 4.182 | F95: =IF(COLUMN()=3, $C86-F91, E95-F91) -> 4.182 | G95: =IF(COLUMN()=3, $C86-G91, F95-G91) -> 4.182 | H95: =IF(COLUMN()=3, $C86-H91, G95-H91) -> 4.182 | I95: =IF(COLUMN()=3, $C86-I91, H95-I91) -> 4.182 | J95: =IF(COLUMN()=3, $C86-J91, I95-J91) -> 4.182 | ... M95: =IF(COLUMN()=3, $C86-M91, L95-M91) -> 4.182
A96: Tax Lots | B96: GOOG Lot 5
B97: Acquisition Date | C97: =DATE(2026,4,25) -> 46137
B98: Total Starting Shares | C98: 8.993
B99: Cost Basis Per Share | C99: 342.32
B100: Total Cost Basis | C100: =C98*C99 -> 3078.4838
B101: Sell All? | C101: FALSE | D101: FALSE | E101: FALSE | F101: FALSE | G101: FALSE | H101: FALSE | I101: FALSE | J101: FALSE | K101: FALSE | L101: FALSE | M101: FALSE
B102: Manual Shares Sold | C102: 0 | D102: 0 | E102: 0 | F102: 0 | G102: 0 | H102: 0 | I102: 0 | J102: 0 | K102: 0 | L102: 0 | M102: 0
B103: Shares Sold | C103: =IF(C101, C98, C102) -> 0 | D103: =IF(D101, C107, D102) -> 0 | E103: =IF(E101, D107, E102) -> 0 | F103: =IF(F101, E107, F102) -> 0 | G103: =IF(G101, F107, G102) -> 0 | H103: =IF(H101, G107, H102) -> 0 | I103: =IF(I101, H107, I102) -> 0 | J103: =IF(J101, I107, J102) -> 0 | K103: =IF(K101, J107, K102) -> 0 | ... M103: =IF(M101, L107, M102) -> 0
B104: Sale Price | C104: =$C$42 -> 350 | D104: =$C$42 -> 350 | E104: =$C$42 -> 350 | F104: =$C$42 -> 350 | G104: =$C$42 -> 350 | H104: =$C$42 -> 350 | I104: =$C$42 -> 350 | J104: =$C$42 -> 350 | ... M104: =$C$42 -> 350
B105: Cost Basis Used | C105: =C103*$C99 -> 0 | D105: =D103*$C99 -> 0 | E105: =E103*$C99 -> 0 | F105: =F103*$C99 -> 0 | G105: =G103*$C99 -> 0 | H105: =H103*$C99 -> 0 | I105: =I103*$C99 -> 0 | J105: =J103*$C99 -> 0 | ... M105: =M103*$C99 -> 0
B106: Realized Gain/Loss | C106: =C103*C104-C105 -> 0 | D106: =D103*D104-D105 -> 0 | E106: =E103*E104-E105 -> 0 | F106: =F103*F104-F105 -> 0 | G106: =G103*G104-G105 -> 0 | H106: =H103*H104-H105 -> 0 | I106: =I103*I104-I105 -> 0 | J106: =J103*J104-J105 -> 0 | ... M106: =M103*M104-M105 -> 0
B107: Remaining Shares | C107: =IF(COLUMN()=3, $C98-C103, B107-C103) -> 8.993 | D107: =IF(COLUMN()=3, $C98-D103, C107-D103) -> 8.993 | E107: =IF(COLUMN()=3, $C98-E103, D107-E103) -> 8.993 | F107: =IF(COLUMN()=3, $C98-F103, E107-F103) -> 8.993 | G107: =IF(COLUMN()=3, $C98-G103, F107-G103) -> 8.993 | H107: =IF(COLUMN()=3, $C98-H103, G107-H103) -> 8.993 | I107: =IF(COLUMN()=3, $C98-I103, H107-I103) -> 8.993 | J107: =IF(COLUMN()=3, $C98-J103, I107-J103) -> 8.993 | ... M107: =IF(COLUMN()=3, $C98-M103, L107-M103) -> 8.993
A108: Tax Lots | B108: GOOG Lot 6
B109: Acquisition Date | C109: =DATE(2026,4,25) -> 46137
...

Sheet 02 Assumptions
A1: Planning Assumptions
A2: Default assumptions are placeholders. A CFP should override them for each client and document the basis in the source notes.
A4: Assumption | B4: Value | C4: Planning Use | D4: Override / Source Notes
A5: Inflation Rate | B5: 0.02 | C5: General purchasing-power and future-value planning | D5: Replace with client-specific or firm-approved assumption
A6: Pre-Retirement Portfolio Return | B6: 0.06 | C6: Goal and retirement accumulation modeling | D6: Replace with risk-profile-based assumption
A7: Retirement Portfolio Return | B7: 0.05 | C7: Retirement income and distribution modeling | D7: Replace with risk-profile-based assumption
A8: Cash / Short-Term Return | B8: 0.02 | C8: Emergency fund and cash planning | D8: Replace with current cash yield assumption
A9: Emergency Fund Target Months | B9: 6 | C9: Dashboard emergency reserve flag | D9: Adjust for income stability, dependents, business ownership
A10: Debt-to-Income Watch Limit | B10: 0.36 | C10: Dashboard debt load flag | D10: Customize for underwriting and planning context
A11: High-Interest Debt Threshold | B11: 0.08 | C11: Dashboard high-interest debt flag | D11: Customize for client opportunity cost
A12: Estate Review Cadence Years | B12: 3 | C12: Estate review flag | D12: Shorten after life events or law changes
A13: Insurance Review Cadence Years | B13: 2 | C13: Insurance coverage review flag | D13: Shorten after job, family, mortgage, or business changes
A14: Primary Retirement Age | B14: 65 | C14: Retirement planning target | D14: Replace with client goal
A15: Co-Client Retirement Age | B15: 65 | C15: Retirement planning target | D15: Replace with client goal
A16: Planning Review Date | B16: =TODAY() -> 46233 | C16: Workbook dashboard as-of date | D16: Refreshes automatically in Excel

Sheet 01 Dashboard
A1: Planning Dashboard
A2: Formula-driven summary. Populate the data tabs and mark rows Active to roll values into the dashboard.
A3: As of | B3: ='02 Assumptions'!$B$16 -> 46233
A4: Metric | D4: Assets by Type | E4: Current Value | G4: Liabilities by Type | H4: Balance | J4: Planning Flag
A5: Total Assets | B5: =SUMIFS('06 Assets'!$I$5:$I$302,'06 Assets'!$T$5:$T$302,"Active") -> 3954898 | D5: Cash / Bank | E5: =SUMIFS('06 Assets'!$I$5:$I$302,'06 Assets'!$C$5:$C$302,D5,'06 Assets'!$T$5:$T$302,"Active") -> 0 | G5: Mortgage | H5: =SUMIFS('07 Liabilities'!$G$5:$G$304,'07 Liabilities'!$D$5:$D$304,G5,'07 Liabilities'!$T$5:$T$304,"Active") -> 397891.78 | J5: Emergency Fund | K5: =IF($B$13>='02 Assumptions'!$B$9,"OK","Review") -> OK | L5: =TEXT($B$13,"0.0")&" months vs target "&TEXT('02 Assumptions'!$B$9,"0.0") -> 166.4 months vs target 6.0
A6: Total Liabilities | B6: =SUMIFS('07 Liabilities'!$G$5:$G$304,'07 Liabilities'!$T$5:$T$304,"Active") -> 397891.78 | D6: Taxable Investment | E6: =SUMIFS('06 Assets'!$I$5:$I$302,'06 Assets'!$C$5:$C$302,D6,'06 Assets'!$T$5:$T$302,"Active") -> 2912398 | G6: HELOC | H6: =SUMIFS('07 Liabilities'!$G$5:$G$304,'07 Liabilities'!$D$5:$D$304,G6,'07 Liabilities'!$T$5:$T$304,"Active") -> 0 | J6: Cash Flow | K6: =IF($B$11>=0,"OK","Review") -> Review | L6: =TEXT($B$11,"$#,##0;($#,##0)")&" monthly net cash flow" -> ($3,834) monthly net cash flow
A7: Net Worth | B7: =B5-B6 -> 3557006.2 | D7: ↳ Cost Basis | E7: =SUMIFS('06 Assets'!$J$5:$J$302,'06 Assets'!$C$5:$C$302,D$6,'06 Assets'!$T$5:$T$302,"Active") -> 413803.14 | G7: Auto Loan | H7: =SUMIFS('07 Liabilities'!$G$5:$G$304,'07 Liabilities'!$D$5:$D$304,G7,'07 Liabilities'!$T$5:$T$304,"Active") -> 0 | J7: Debt Load | K7: =IF($B$15<='02 Assumptions'!$B$10,"OK","Review") -> OK | L7: =TEXT($B$15,"0.0%")&" DTI vs watch limit "&TEXT('02 Assumptions'!$B$10,"0.0%") -> 0.0% DTI vs watch limit 36.0%
A8: Liquid Assets | B8: =SUMIFS('06 Assets'!$I$5:$I$302,'06 Assets'!$T$5:$T$302,"Active",'06 Assets'!$G$5:$G$302,"Immediate")+SUMIFS('06 Assets'!$I$5:$I$302,'06 Assets'!$T$5:$T$302,"Active",'06 Assets'!$G$5:$G$302,"Short-term") -> 637892.99 | D8: ↳ Taxable Gains | E8: =E6-E7 -> 2498594.8 | G8: Student Loan | H8: =SUMIFS('07 Liabilities'!$G$5:$G$304,'07 Liabilities'!$D$5:$D$304,G8,'07 Liabilities'!$T$5:$T$304,"Active") -> 0 | J8: High-Interest Debt | K8: =IF(COUNTIFS('07 Liabilities'!$H$5:$H$304,">="&'02 Assumptions'!$B$11,'07 Liabilities'!$T$5:$T$304,"Active")=0,"OK","Review") -> OK | L8: =COUNTIFS('07 Liabilities'!$H$5:$H$304,">="&'02 Assumptions'!$B$11,'07 Liabilities'!$T$5:$T$304,"Active")&" active debts over threshold" -> 0 active debts over threshold
A9: Monthly Income | B9: =SUMIFS('05 Cash Flow'!$F$5:$F$302,'05 Cash Flow'!$A$5:$A$302,"Income",'05 Cash Flow'!$K$5:$K$302,"Active") -> 0 | D9: Traditional Retirement | E9: =SUMIFS('06 Assets'!$I$5:$I$302,'06 Assets'!$C$5:$C$302,D9,'06 Assets'!$T$5:$T$302,"Active") -> 0 | G9: Credit Card | H9: =SUMIFS('07 Liabilities'!$G$5:$G$304,'07 Liabilities'!$D$5:$D$304,G9,'07 Liabilities'!$T$5:$T$304,"Active") -> 0 | J9: Estate Plan | K9: =IF($B$17=0,"OK","Review") -> Review | L9: =$B$17&" estate items need review" -> 10 estate items need review
A10: Monthly Expenses | B10: =SUMIFS('05 Cash Flow'!$F$5:$F$302,'05 Cash Flow'!$A$5:$A$302,"Expense",'05 Cash Flow'!$K$5:$K$302,"Active") -> 3834.29 | D10: Roth Retirement | E10: =SUMIFS('06 Assets'!$I$5:$I$302,'06 Assets'!$C$5:$C$302,D10,'06 Assets'!$T$5:$T$302,"Active") -> 0 | G10: Personal Loan | H10: =SUMIFS('07 Liabilities'!$G$5:$G$304,'07 Liabilities'!$D$5:$D$304,G10,'07 Liabilities'!$T$5:$T$304,"Active") -> 0 | J10: Document Collection | K10: =IF($B$18=0,"OK","Review") -> Review | L10: =$B$18&" needed documents outstanding" -> 24 needed documents outstanding
A11: Monthly Net Cash Flow | B11: =B9-B10 -> -3834.29 | D11: HSA | E11: =SUMIFS('06 Assets'!$I$5:$I$302,'06 Assets'!$C$5:$C$302,D11,'06 Assets'!$T$5:$T$302,"Active") -> 2000 | G11: Business Debt | H11: =SUMIFS('07 Liabilities'!$G$5:$G$304,'07 Liabilities'!$D$5:$D$304,G11,'07 Liabilities'!$T$5:$T$304,"Active") -> 0 | J11: Goals | K11: =IF($B$19=0,"OK","Review") -> OK | L11: =$B$19&" active goals need review" -> 0 active goals need review
A12: Essential Monthly Expenses | B12: =SUMIFS('05 Cash Flow'!$F$5:$F$302,'05 Cash Flow'!$A$5:$A$302,"Expense",'05 Cash Flow'!$H$5:$H$302,"Yes",'05 Cash Flow'!$K$5:$K$302,"Active") -> 3834.29 | D12: 529 / Education | E12: =SUMIFS('06 Assets'!$I$5:$I$302,'06 Assets'!$C$5:$C$302,D12,'06 Assets'!$T$5:$T$302,"Active") -> 0 | G12: Tax Debt | H12: =SUMIFS('07 Liabilities'!$G$5:$G$304,'07 Liabilities'!$D$5:$D$304,G12,'07 Liabilities'!$T$5:$T$304,"Active") -> 0 | J12: Action Items | K12: =IF($B$20=0,"OK","Review") -> OK | L12: =$B$20&" overdue open actions" -> 0 overdue open actions
A13: Emergency Fund Months | B13: =IFERROR(B8/B12,0) -> 166.36535 | D13: Real Estate | E13: =SUMIFS('06 Assets'!$I$5:$I$302,'06 Assets'!$C$5:$C$302,D13,'06 Assets'!$T$5:$T$302,"Active") -> 1040500 | G13: Other Liability | H13: =SUMIFS('07 Liabilities'!$G$5:$G$304,'07 Liabilities'!$D$5:$D$304,G13,'07 Liabilities'!$T$5:$T$304,"Active") -> 0
A14: Monthly Debt Payments | B14: =SUMIFS('07 Liabilities'!$J$5:$J$304,'07 Liabilities'!$T$5:$T$304,"Active") -> 2334.29 | D14: Business Interest | E14: =SUMIFS('06 Assets'!$I$5:$I$302,'06 Assets'!$C$5:$C$302,D14,'06 Assets'!$T$5:$T$302,"Active") -> 0
A15: Debt-to-Income Ratio | B15: =IFERROR(B14/B9,0) -> 0 | D15: Personal Property | E15: =SUMIFS('06 Assets'!$I$5:$I$302,'06 Assets'!$C$5:$C$302,D15,'06 Assets'!$T$5:$T$302,"Active") -> 0
A16: Insurance Monthly Premiums | B16: =SUMIFS('08 Insurance'!$H$5:$H$304,'08 Insurance'!$N$5:$N$304,"Active") -> 0 | D16: Alternative / Crypto | E16: =SUMIFS('06 Assets'!$I$5:$I$302,'06 Assets'!$C$5:$C$302,D16,'06 Assets'!$T$5:$T$302,"Active") -> 0
A17: Estate Items Needing Review | B17: =COUNTIF('12 Estate'!$H$5:$H$304,"Review") -> 10 | D17: Other Asset | E17: =SUMIFS('06 Assets'!$I$5:$I$302,'06 Assets'!$C$5:$C$302,D17,'06 Assets'!$T$5:$T$302,"Active") -> 0
A18: Documents Outstanding | B18: =COUNTIFS('14 Documents'!$D$5:$D$304,"Yes",'14 Documents'!$E$5:$E$304,"<>Yes") -> 24 | D18: Asset Allocation | E18: Current Value | G18: Insurance Coverage | H18: Coverage Amount
A19: Active Goals Needing Review | B19: =COUNTIFS('04 Goals'!$O$5:$O$304,"Active",'04 Goals'!$M$5:$M$304,"Needs review") -> 0 | D19: Cash | E19: =SUMIFS('06 Assets'!$I$5:$I$302,'06 Assets'!$H$5:$H$302,D19,'06 Assets'!$T$5:$T$302,"Active") -> 2000 | G19: Life | H19: =SUMIFS('08 Insurance'!$G$5:$G$304,'08 Insurance'!$B$5:$B$304,G19,'08 Insurance'!$N$5:$N$304,"Active") -> 0
A20: Overdue Open Actions | B20: =COUNTIFS('15 Action Plan'!$G$5:$G$304,"<>Complete",'15 Action Plan'!$F$5:$F$304,"<"&TODAY(),'15 Action Plan'!$C$5:$C$304,"<>") -> 0 | D20: Equities | E20: =SUMIFS('06 Assets'!$I$5:$I$302,'06 Assets'!$H$5:$H$302,D20,'06 Assets'!$T$5:$T$302,"Active") -> 2912398 | G20: Disability | H20: =SUMIFS('08 Insurance'!$G$5:$G$304,'08 Insurance'!$B$5:$B$304,G20,'08 Insurance'!$N$5:$N$304,"Active") -> 0
D21: Fixed Income | E21: =SUMIFS('06 Assets'!$I$5:$I$302,'06 Assets'!$H$5:$H$302,D21,'06 Assets'!$T$5:$T$302,"Active") -> 0 | G21: Long-Term Care | H21: =SUMIFS('08 Insurance'!$G$5:$G$304,'08 Insurance'!$B$5:$B$304,G21,'08 Insurance'!$N$5:$N$304,"Active") -> 0
D22: Real Estate | E22: =SUMIFS('06 Assets'!$I$5:$I$302,'06 Assets'!$H$5:$H$302,D22,'06 Assets'!$T$5:$T$302,"Active") -> 1040500 | G22: Health | H22: =SUMIFS('08 Insurance'!$G$5:$G$304,'08 Insurance'!$B$5:$B$304,G22,'08 Insurance'!$N$5:$N$304,"Active") -> 0
D23: Alternatives | E23: =SUMIFS('06 Assets'!$I$5:$I$302,'06 Assets'!$H$5:$H$302,D23,'06 Assets'!$T$5:$T$302,"Active") -> 0 | G23: Auto | H23: =SUMIFS('08 Insurance'!$G$5:$G$304,'08 Insurance'!$B$5:$B$304,G23,'08 Insurance'!$N$5:$N$304,"Active") -> 0
D24: Business | E24: =SUMIFS('06 Assets'!$I$5:$I$302,'06 Assets'!$H$5:$H$302,D24,'06 Assets'!$T$5:$T$302,"Active") -> 0 | G24: Homeowners | H24: =SUMIFS('08 Insurance'!$G$5:$G$304,'08 Insurance'!$B$5:$B$304,G24,'08 Insurance'!$N$5:$N$304,"Active") -> 0
D25: Other | E25: =SUMIFS('06 Assets'!$I$5:$I$302,'06 Assets'!$H$5:$H$302,D25,'06 Assets'!$T$5:$T$302,"Active") -> 0 | G25: Umbrella | H25: =SUMIFS('08 Insurance'!$G$5:$G$304,'08 Insurance'!$B$5:$B$304,G25,'08 Insurance'!$N$5:$N$304,"Active") -> 0
G26: Business | H26: =SUMIFS('08 Insurance'!$G$5:$G$304,'08 Insurance'!$B$5:$B$304,G26,'08 Insurance'!$N$5:$N$304,"Active") -> 0
G27: Other | H27: =SUMIFS('08 Insurance'!$G$5:$G$304,'08 Insurance'!$B$5:$B$304,G27,'08 Insurance'!$N$5:$N$304,"Active") -> 0

Sheet 03 Client Profile
A1: Client Profile
A2: Household identity, residency, employment, health, advisors, and risk profile. Use last four digits only for sensitive IDs.
A4: Name | B4: Relationship | C4: Date of Birth | D4: Age | E4: Dependent? | F4: Tax Dependent? | G4: Citizen/Residency | H4: Employment / Occupation | I4: Health Notes | J4: Planning Notes
B5: Primary Client | D5: 36 | E5: No | F5: No | G5: US Citizen California | H5: Full Time Engineer | J5: Divorced, single income, risk-averse
D6: =IF(C6="","",DATEDIF(C6,TODAY(),"Y"))
D7: =IF(C7="","",DATEDIF(C7,TODAY(),"Y"))
D8: =IF(C8="","",DATEDIF(C8,TODAY(),"Y"))
D9: =IF(C9="","",DATEDIF(C9,TODAY(),"Y"))
D10: =IF(C10="","",DATEDIF(C10,TODAY(),"Y"))
D11: =IF(C11="","",DATEDIF(C11,TODAY(),"Y"))
D12: =IF(C12="","",DATEDIF(C12,TODAY(),"Y"))
D13: =IF(C13="","",DATEDIF(C13,TODAY(),"Y"))
D14: =IF(C14="","",DATEDIF(C14,TODAY(),"Y"))
D15: =IF(C15="","",DATEDIF(C15,TODAY(),"Y"))
D16: =IF(C16="","",DATEDIF(C16,TODAY(),"Y"))
D17: =IF(C17="","",DATEDIF(C17,TODAY(),"Y"))
... D304: =IF(C304="","",DATEDIF(C304,TODAY(),"Y"))
A306: Advisor Role | B306: Name / Firm | C306: Contact | D306: Email | E306: Phone | F306: Address | G306: Portal / Website | H306: Permission to Contact? | I306: Notes | J306: Status
A328: Risk / Preference Item | B328: Response | C328: Last Reviewed | D328: Notes
A329: Planning scope | D329: Retirement, tax, insurance, estate, education, cash flow, investment management, business planning
A330: Risk tolerance score | B330: Risk-averse | C330: 46204 | D330: Reference firm questionnaire or planning software output
A331: Risk capacity notes | D331: Time horizon, income stability, debt, dependents, business risk
A332: Loss tolerance | D332: Client reaction to portfolio decline
A333: Liquidity preference | D333: Cash reserves, lock-up comfort, real estate concentration
A334: Values / ESG / faith constraints | D334: Investment or planning constraints

Sheet 04 Goals
A1: Goals
A2: Capture goals, priority, target date, current funding, and monthly savings. Projection formula is a planning estimate, not advice.
A4: Goal ID | B4: Goal Name | C4: Owner | D4: Planning Area | E4: Priority | F4: Target Date | G4: Target Amount | H4: Current Funding | I4: Monthly Savings | J4: Expected Return | K4: Projected at Target | L4: Funding Gap | M4: On Track? | N4: Notes | O4: Status
K5: =IF(OR(O5<>"Active",F5="",G5=""),"",IFERROR(FV(J5/12,MAX(0,DATEDIF(TODAY(),F5,"m")),-I5,-H5),H5)) | L5: =IF(K5="","",MAX(0,G5-K5)) | M5: =IF(K5="","",IF(K5>=G5,"On track","Needs review"))
K6: =IF(OR(O6<>"Active",F6="",G6=""),"",IFERROR(FV(J6/12,MAX(0,DATEDIF(TODAY(),F6,"m")),-I6,-H6),H6)) | L6: =IF(K6="","",MAX(0,G6-K6)) | M6: =IF(K6="","",IF(K6>=G6,"On track","Needs review"))
K7: =IF(OR(O7<>"Active",F7="",G7=""),"",IFERROR(FV(J7/12,MAX(0,DATEDIF(TODAY(),F7,"m")),-I7,-H7),H7)) | L7: =IF(K7="","",MAX(0,G7-K7)) | M7: =IF(K7="","",IF(K7>=G7,"On track","Needs review"))
K8: =IF(OR(O8<>"Active",F8="",G8=""),"",IFERROR(FV(J8/12,MAX(0,DATEDIF(TODAY(),F8,"m")),-I8,-H8),H8)) | L8: =IF(K8="","",MAX(0,G8-K8)) | M8: =IF(K8="","",IF(K8>=G8,"On track","Needs review"))
K9: =IF(OR(O9<>"Active",F9="",G9=""),"",IFERROR(FV(J9/12,MAX(0,DATEDIF(TODAY(),F9,"m")),-I9,-H9),H9)) | L9: =IF(K9="","",MAX(0,G9-K9)) | M9: =IF(K9="","",IF(K9>=G9,"On track","Needs review"))
K10: =IF(OR(O10<>"Active",F10="",G10=""),"",IFERROR(FV(J10/12,MAX(0,DATEDIF(TODAY(),F10,"m")),-I10,-H10),H10)) | L10: =IF(K10="","",MAX(0,G10-K10)) | M10: =IF(K10="","",IF(K10>=G10,"On track","Needs review"))
K11: =IF(OR(O11<>"Active",F11="",G11=""),"",IFERROR(FV(J11/12,MAX(0,DATEDIF(TODAY(),F11,"m")),-I11,-H11),H11)) | L11: =IF(K11="","",MAX(0,G11-K11)) | M11: =IF(K11="","",IF(K11>=G11,"On track","Needs review"))
K12: =IF(OR(O12<>"Active",F12="",G12=""),"",IFERROR(FV(J12/12,MAX(0,DATEDIF(TODAY(),F12,"m")),-I12,-H12),H12)) | L12: =IF(K12="","",MAX(0,G12-K12)) | M12: =IF(K12="","",IF(K12>=G12,"On track","Needs review"))
K13: =IF(OR(O13<>"Active",F13="",G13=""),"",IFERROR(FV(J13/12,MAX(0,DATEDIF(TODAY(),F13,"m")),-I13,-H13),H13)) | L13: =IF(K13="","",MAX(0,G13-K13)) | M13: =IF(K13="","",IF(K13>=G13,"On track","Needs review"))
K14: =IF(OR(O14<>"Active",F14="",G14=""),"",IFERROR(FV(J14/12,MAX(0,DATEDIF(TODAY(),F14,"m")),-I14,-H14),H14)) | L14: =IF(K14="","",MAX(0,G14-K14)) | M14: =IF(K14="","",IF(K14>=G14,"On track","Needs review"))
K15: =IF(OR(O15<>"Active",F15="",G15=""),"",IFERROR(FV(J15/12,MAX(0,DATEDIF(TODAY(),F15,"m")),-I15,-H15),H15)) | L15: =IF(K15="","",MAX(0,G15-K15)) | M15: =IF(K15="","",IF(K15>=G15,"On track","Needs review"))
K16: =IF(OR(O16<>"Active",F16="",G16=""),"",IFERROR(FV(J16/12,MAX(0,DATEDIF(TODAY(),F16,"m")),-I16,-H16),H16)) | L16: =IF(K16="","",MAX(0,G16-K16)) | M16: =IF(K16="","",IF(K16>=G16,"On track","Needs review"))
... K304: =IF(OR(O304<>"Active",F304="",G304=""),"",IFERROR(FV(J304/12,MAX(0,DATEDIF(TODAY(),F304,"m")),-I304,-H304),H304)) | L304: =IF(K304="","",MAX(0,G304-K304)) | M304: =IF(K304="","",IF(K304>=G304,"On track","Needs review"))

Sheet 05 Cash Flow
A1: Cash Flow
A2: Enter recurring income and expenses. Use frequency and amount per frequency; formulas convert to monthly and annual figures.
A4: Type | B4: Category | C4: Owner | D4: Frequency | E4: Amount per Frequency | F4: Monthly Amount | G4: Annual Amount | H4: Essential? | I4: Tax Deductible? | J4: Notes | K4: Status
A5: Expense | B5: Mortgage | C5: Primary Client | D5: Monthly | E5: 2334.29 | F5: 2334.29 | G5: =F5*12 -> 28011.48 | H5: Yes | I5: Yes | K5: Active
A6: Expense | B6: Home | C6: Primary Client | D6: Monthly | E6: 5836 | F6: =IF(A6="","",E6*((D6="Weekly")*52/12+(D6="Biweekly")*26/12+(D6="Monthly")*1+(D6="Quarterly")/3+(D6="Annual")/12+(D6="One-Time")/12)) -> 5836 | G6: =IF(A6="","",F6*12) -> 70032 | H6: No | I6: No
A7: Expense | B7: Groceries | C7: Primary Client | D7: Monthly | E7: 1022 | F7: =IF(A7="","",E7*((D7="Weekly")*52/12+(D7="Biweekly")*26/12+(D7="Monthly")*1+(D7="Quarterly")/3+(D7="Annual")/12+(D7="One-Time")/12)) -> 1022 | G7: =IF(A7="","",F7*12) -> 12264 | H7: Yes | I7: No
A8: Expense | B8: Shopping/Entertainment | C8: Primary Client | D8: Monthly | E8: 2300 | F8: =IF(A8="","",E8*((D8="Weekly")*52/12+(D8="Biweekly")*26/12+(D8="Monthly")*1+(D8="Quarterly")/3+(D8="Annual")/12+(D8="One-Time")/12)) -> 2300 | G8: =IF(A8="","",F8*12) -> 27600 | H8: No | I8: No
A9: Expense | B9: Other | C9: Primary Client | D9: Monthly | E9: 846 | F9: =IF(A9="","",E9*((D9="Weekly")*52/12+(D9="Biweekly")*26/12+(D9="Monthly")*1+(D9="Quarterly")/3+(D9="Annual")/12+(D9="One-Time")/12)) -> 846 | G9: =IF(A9="","",F9*12) -> 10152 | H9: TBD | I9: No
A10: Expense | B10: Health | C10: Primary Client | D10: Monthly | E10: 1500 | F10: 1500 | G10: =IF(A10="","",F10*12) -> 18000 | H10: Yes | I10: No | K10: Active
F11: =IF(A11="","",E11*((D11="Weekly")*52/12+(D11="Biweekly")*26/12+(D11="Monthly")*1+(D11="Quarterly")/3+(D11="Annual")/12+(D11="One-Time")/12)) | G11: =IF(A11="","",F11*12)
F12: =IF(A12="","",E12*((D12="Weekly")*52/12+(D12="Biweekly")*26/12+(D12="Monthly")*1+(D12="Quarterly")/3+(D12="Annual")/12+(D12="One-Time")/12)) | G12: =IF(A12="","",F12*12)
F13: =IF(A13="","",E13*((D13="Weekly")*52/12+(D13="Biweekly")*26/12+(D13="Monthly")*1+(D13="Quarterly")/3+(D13="Annual")/12+(D13="One-Time")/12)) | G13: =IF(A13="","",F13*12)
F14: =IF(A14="","",E14*((D14="Weekly")*52/12+(D14="Biweekly")*26/12+(D14="Monthly")*1+(D14="Quarterly")/3+(D14="Annual")/12+(D14="One-Time")/12)) | G14: =IF(A14="","",F14*12)
F15: =IF(A15="","",E15*((D15="Weekly")*52/12+(D15="Biweekly")*26/12+(D15="Monthly")*1+(D15="Quarterly")/3+(D15="Annual")/12+(D15="One-Time")/12)) | G15: =IF(A15="","",F15*12)
F16: =IF(A16="","",E16*((D16="Weekly")*52/12+(D16="Biweekly")*26/12+(D16="Monthly")*1+(D16="Quarterly")/3+(D16="Annual")/12+(D16="One-Time")/12)) | G16: =IF(A16="","",F16*12)
F17: =IF(A17="","",E17*((D17="Weekly")*52/12+(D17="Biweekly")*26/12+(D17="Monthly")*1+(D17="Quarterly")/3+(D17="Annual")/12+(D17="One-Time")/12)) | G17: =IF(A17="","",F17*12)
F18: =IF(A18="","",E18*((D18="Weekly")*52/12+(D18="Biweekly")*26/12+(D18="Monthly")*1+(D18="Quarterly")/3+(D18="Annual")/12+(D18="One-Time")/12)) | G18: =IF(A18="","",F18*12)
F19: =IF(A19="","",E19*((D19="Weekly")*52/12+(D19="Biweekly")*26/12+(D19="Monthly")*1+(D19="Quarterly")/3+(D19="Annual")/12+(D19="One-Time")/12)) | G19: =IF(A19="","",F19*12)
F20: =IF(A20="","",E20*((D20="Weekly")*52/12+(D20="Biweekly")*26/12+(D20="Monthly")*1+(D20="Quarterly")/3+(D20="Annual")/12+(D20="One-Time")/12)) | G20: =IF(A20="","",F20*12)
F21: =IF(A21="","",E21*((D21="Weekly")*52/12+(D21="Biweekly")*26/12+(D21="Monthly")*1+(D21="Quarterly")/3+(D21="Annual")/12+(D21="One-Time")/12)) | G21: =IF(A21="","",F21*12)
F22: =IF(A22="","",E22*((D22="Weekly")*52/12+(D22="Biweekly")*26/12+(D22="Monthly")*1+(D22="Quarterly")/3+(D22="Annual")/12+(D22="One-Time")/12)) | G22: =IF(A22="","",F22*12)
... F302: =IF(A302="","",E302*((D302="Weekly")*52/12+(D302="Biweekly")*26/12+(D302="Monthly")*1+(D302="Quarterly")/3+(D302="Annual")/12+(D302="One-Time")/12)) | G302: =IF(A302="","",F302*12)

Sheet 06 Assets
A1: Assets
A2: Track each asset/account. Mark Status as Active to include current value in the dashboard.
A4: Record ID | B4: Account / Asset Name | C4: Asset Type | D4: Institution / Custodian | E4: Account Last 4 | F4: Tax Registration | G4: Liquidity | H4: Allocation Category | I4: Current Value | J4: Cost Basis | K4: Monthly Contribution | L4: Annual Return Assumption | M4: Income / Yield | N4: Beneficiary / Joint Owner | O4: Linked Goal | P4: Review Priority | Q4: Last Updated | R4: Projected 1-Yr Value | S4: Notes | T4: Status
A5: A-01 | B5: Primary Residence - 1945 Bradhoff Ave, San Leandro, CA 94577 | C5: Real Estate | H5: Real Estate | I5: 1040500 | J5: 1000000 | Q5: 46204 | R5: =I5*(1+L5) -> 1040500 | S5: Purchased 12/24/2025. Put $600k down. | T5: Active
A6: A-02 | B6: Google Stock | C6: Taxable Investment | D6: Morgan Stanley | F6: Individual | G6: Immediate | H6: Equities | I6: =IFERROR(__xludf.DUMMYFUNCTION("GOOGLEFINANCE(""GOOG"", ""price"") * 1668.55"),554892.988) -> 554892.99 | J6: 287503.14 | Q6: 46204 | R6: =I6*(1+L6) -> 554892.99 | S6: 1668.55 shares | T6: Active
A7: A-03 | B7: SpaceX Stock | C7: Taxable Investment | D7: Solium (Morgan Stanley) | F7: Individual | G7: Illiquid | H7: Equities | I7: =IFERROR(__xludf.DUMMYFUNCTION("GOOGLEFINANCE(""SPCX"", ""price"") * 20250"),2276505.0) -> 2276505 | J7: 66300 | Q7: 46204 | R7: =I7*(1+L7) -> 2276505 | S7: 20250 shares | T7: Active
A8: A-04 | B8: Keysight + Agilent Stock | C8: Taxable Investment | D8: Fidelity | F8: Individual | G8: Immediate | H8: Equities | I8: 81000 | J8: 60000 | Q8: 46220 | R8: =I8*(1+L8) -> 81000 | S8: Holds Agilent (49.727) & Keysight (237.767 shares) | T8: Active
A9: A-07 | B9: HSA | C9: HSA | D9: Health Equity | F9: HSA | G9: Immediate | H9: Cash | I9: 2000 | J9: 2000 | Q9: 46220 | R9: =IF(T9="Active",I9*(1+L9)+K9*12,"") -> 2000 | T9: Active
A10: A-08 | B10: RCU Checking | C10: Cash / Bank | D10: Redwood Credit Union | E10: -93-S10 | F10: Individual | G10: Immediate | H10: Cash | I10: 51060 | Q10: 46220 | R10: =IF(T10="Active",I10*(1+L10)+K10*12,"")
A11: A-09 | B11: RCU Savings | C11: Cash / Bank | D11: Redwood Credit Union | E11: -93-S01 | F11: Individual | G11: Immediate | H11: Cash | I11: 14538 | Q11: 46220 | R11: =IF(T11="Active",I11*(1+L11)+K11*12,"")
A12: A-10 | B12: Marcus HYSA | C12: Cash / Bank | D12: Marcus | E12: -1795 | F12: Individual | G12: Immediate | H12: Cash | I12: 15391 | Q12: 46220 | R12: =IF(T12="Active",I12*(1+L12)+K12*12,"")
A13: A-11 | B13: Wealthfront HYSA | C13: Cash / Bank | D13: Wealthfront | E13: -WDNF | F13: Individual | G13: Immediate | H13: Cash | I13: 15434 | Q13: 46220 | R13: =IF(T13="Active",I13*(1+L13)+K13*12,"")
A14: A-12 | B14: Google 401k | C14: Traditional Retirement | D14: Vanguard | F14: 401(k) / 403(b) | G14: Long-term | H14: Equities | I14: 126490 | Q14: 46220 | R14: =IF(T14="Active",I14*(1+L14)+K14*12,"")
A15: A-13 | B15: SpaceX 401k | C15: Traditional Retirement | D15: Fidelity | E15: -6233 | F15: 401(k) / 403(b) | G15: Long-term | H15: Equities | I15: 29763 | Q15: 46220 | R15: =IF(T15="Active",I15*(1+L15)+K15*12,"")
A16: A-14 | B16: Keysight 401k | C16: Traditional Retirement | D16: Fidelity | E16: -82 | F16: 401(k) / 403(b) | G16: Long-term | H16: Equities | I16: 64950 | Q16: 46220 | R16: =IF(T16="Active",I16*(1+L16)+K16*12,"")
R17: =IF(T17="Active",I17*(1+L17)+K17*12,"")
R18: =IF(T18="Active",I18*(1+L18)+K18*12,"")
R19: =IF(T19="Active",I19*(1+L19)+K19*12,"")
R20: =IF(T20="Active",I20*(1+L20)+K20*12,"")
R21: =IF(T21="Active",I21*(1+L21)+K21*12,"")
R22: =IF(T22="Active",I22*(1+L22)+K22*12,"")
R23: =IF(T23="Active",I23*(1+L23)+K23*12,"")
R24: =IF(T24="Active",I24*(1+L24)+K24*12,"")
R25: =IF(T25="Active",I25*(1+L25)+K25*12,"")
R26: =IF(T26="Active",I26*(1+L26)+K26*12,"")
R27: =IF(T27="Active",I27*(1+L27)+K27*12,"")
R28: =IF(T28="Active",I28*(1+L28)+K28*12,"")
... R302: =IF(T302="Active",I302*(1+L302)+K302*12,"")

Sheet 07 Liabilities
A1: Liabilities
A2: Track every debt with balance, rate, payment, maturity, tax deductibility, and payoff priority.
A4: Record ID | B4: Owner | C4: Creditor | D4: Liability Type | E4: Account Last 4 | F4: Secured By | G4: Current Balance | H4: Interest Rate | I4: Minimum Monthly Payment | J4: Planned Monthly Payment | K4: Original Balance | L4: Origination Date | M4: Maturity Date | N4: Tax Deductible? | O4: Variable Rate? | P4: Priority | Q4: Annual Payment | R4: Estimated Payoff Months | S4: Notes | T4: Status
A5: L-01 | B5: Primary Client | D5: Mortgage | F5: Primary Residence | G5: 397891.78 | H5: 0.0575 | I5: 2334.29 | J5: 2334.29 | N5: Yes | O5: No | Q5: =J5*12 -> 28011.48 | R5: =IFERROR(NPER(H5/12, J5, -G5), "") -> 355.0006 | S5: $1,906.56 / month in interest | T5: Active
Q6: =IF(T6="Active",J6*12,0) -> 0 | R6: =IF(OR(T6<>"Active",G6<=0,J6<=0),"",IFERROR(NPER(IF(H6="",0,H6)/12,-J6,G6),"Review"))
Q7: =IF(T7="Active",J7*12,0) -> 0 | R7: =IF(OR(T7<>"Active",G7<=0,J7<=0),"",IFERROR(NPER(IF(H7="",0,H7)/12,-J7,G7),"Review"))
Q8: =IF(T8="Active",J8*12,0) -> 0 | R8: =IF(OR(T8<>"Active",G8<=0,J8<=0),"",IFERROR(NPER(IF(H8="",0,H8)/12,-J8,G8),"Review"))
Q9: =IF(T9="Active",J9*12,0) -> 0 | R9: =IF(OR(T9<>"Active",G9<=0,J9<=0),"",IFERROR(NPER(IF(H9="",0,H9)/12,-J9,G9),"Review"))
Q10: =IF(T10="Active",J10*12,0) -> 0 | R10: =IF(OR(T10<>"Active",G10<=0,J10<=0),"",IFERROR(NPER(IF(H10="",0,H10)/12,-J10,G10),"Review"))
Q11: =IF(T11="Active",J11*12,0) -> 0 | R11: =IF(OR(T11<>"Active",G11<=0,J11<=0),"",IFERROR(NPER(IF(H11="",0,H11)/12,-J11,G11),"Review"))
Q12: =IF(T12="Active",J12*12,0) -> 0 | R12: =IF(OR(T12<>"Active",G12<=0,J12<=0),"",IFERROR(NPER(IF(H12="",0,H12)/12,-J12,G12),"Review"))
Q13: =IF(T13="Active",J13*12,0) -> 0 | R13: =IF(OR(T13<>"Active",G13<=0,J13<=0),"",IFERROR(NPER(IF(H13="",0,H13)/12,-J13,G13),"Review"))
Q14: =IF(T14="Active",J14*12,0) -> 0 | R14: =IF(OR(T14<>"Active",G14<=0,J14<=0),"",IFERROR(NPER(IF(H14="",0,H14)/12,-J14,G14),"Review"))
Q15: =IF(T15="Active",J15*12,0) -> 0 | R15: =IF(OR(T15<>"Active",G15<=0,J15<=0),"",IFERROR(NPER(IF(H15="",0,H15)/12,-J15,G15),"Review"))
Q16: =IF(T16="Active",J16*12,0) -> 0 | R16: =IF(OR(T16<>"Active",G16<=0,J16<=0),"",IFERROR(NPER(IF(H16="",0,H16)/12,-J16,G16),"Review"))
Q17: =IF(T17="Active",J17*12,0) -> 0 | R17: =IF(OR(T17<>"Active",G17<=0,J17<=0),"",IFERROR(NPER(IF(H17="",0,H17)/12,-J17,G17),"Review"))
... Q304: =IF(T304="Active",J304*12,0) -> 0 | R304: =IF(OR(T304<>"Active",G304<=0,J304<=0),"",IFERROR(NPER(IF(H304="",0,H304)/12,-J304,G304),"Review"))

Sheet 08 Insurance
A1: Insurance
A2: Track existing coverage, premiums, beneficiaries, cash values, renewal dates, and planning gaps.
A4: Policy ID | B4: Policy Type | C4: Owner | D4: Insured | E4: Carrier | F4: Policy Last 4 | G4: Coverage Amount | H4: Monthly Premium | I4: Cash Value | J4: Beneficiary | K4: Expiration / Renewal Date | L4: Need Analysis Status | M4: Notes | N4: Status

Sheet 09 Retirement Income
A1: Retirement Income
A2: Capture projected retirement income sources such as Social Security, pension, annuity, rental, business, and part-time income.
A4: Source ID | B4: Owner | C4: Source Type | D4: Provider / Agency | E4: Earliest Start Date | F4: Planned Start Date | G4: Annual Amount Today | H4: COLA | I4: Taxability | J4: Survivor Benefit | K4: Notes | L4: Status

Sheet 10 Employee Benefits
A1: Employee Benefits
A2: Capture employer benefits, elections, vesting, deadlines, and planning opportunities.
A4: Benefit ID | B4: Owner | C4: Employer | D4: Benefit Type | E4: Current Election / Details | F4: Employee Contribution | G4: Employer Contribution / Match | H4: Vesting | I4: Open Enrollment / Deadline | J4: Action Required | K4: Notes | L4: Status

Sheet 11 Taxes
A1: Taxes
A2: Track filing status, tax rates, income, withholding, estimated payments, carryforwards, and planning notes by year.
A4: Tax Year | B4: Filing Status | C4: Marginal Federal Rate | D4: State Tax Rate | E4: AGI | F4: Taxable Income | G4: Federal Tax Paid / Withholding | H4: State Tax Paid / Withholding | I4: Estimated Payments | J4: Carryforwards | K4: Roth Conversion Opportunity? | L4: Charitable Strategy | M4: Notes | N4: Status

Sheet 12 Estate
A1: Estate Planning
A2: Track documents, fiduciaries, locations, execution dates, and review needs.
A4: Item ID | B4: Document / Planning Item | C4: Applies To | D4: Status | E4: Date Signed / Updated | F4: Attorney / Firm | G4: Storage Location | H4: Review Needed? | I4: Notes
A5: EST-001 | B5: Will | C5: Household | D5: Not Started | H5: =IF(B5="","",IF(D5<>"Complete","Review",IF(E5="","Review",IF(TODAY()-E5>365*'02 Assumptions'!$B$12,"Review","OK")))) -> Review | I5: Include guardianship provisions where applicable
A6: EST-002 | B6: Revocable Living Trust | C6: Household | D6: Not Started | H6: =IF(B6="","",IF(D6<>"Complete","Review",IF(E6="","Review",IF(TODAY()-E6>365*'02 Assumptions'!$B$12,"Review","OK")))) -> Review | I6: Review account titling and trust funding
A7: EST-003 | B7: Durable Power of Attorney | C7: Primary Client | D7: Not Started | H7: =IF(B7="","",IF(D7<>"Complete","Review",IF(E7="","Review",IF(TODAY()-E7>365*'02 Assumptions'!$B$12,"Review","OK")))) -> Review
A8: EST-004 | B8: Durable Power of Attorney | C8: Co-Client / Spouse | D8: Not Started | H8: =IF(B8="","",IF(D8<>"Complete","Review",IF(E8="","Review",IF(TODAY()-E8>365*'02 Assumptions'!$B$12,"Review","OK")))) -> Review
A9: EST-005 | B9: Advance Health Care Directive | C9: Primary Client | D9: Not Started | H9: =IF(B9="","",IF(D9<>"Complete","Review",IF(E9="","Review",IF(TODAY()-E9>365*'02 Assumptions'!$B$12,"Review","OK")))) -> Review
A10: EST-006 | B10: Advance Health Care Directive | C10: Co-Client / Spouse | D10: Not Started | H10: =IF(B10="","",IF(D10<>"Complete","Review",IF(E10="","Review",IF(TODAY()-E10>365*'02 Assumptions'!$B$12,"Review","OK")))) -> Review
A11: EST-007 | B11: HIPAA Authorization | C11: Household | D11: Not Started | H11: =IF(B11="","",IF(D11<>"Complete","Review",IF(E11="","Review",IF(TODAY()-E11>365*'02 Assumptions'!$B$12,"Review","OK")))) -> Review
A12: EST-008 | B12: Beneficiary Designations Reviewed | C12: Household | D12: Not Started | H12: =IF(B12="","",IF(D12<>"Complete","Review",IF(E12="","Review",IF(TODAY()-E12>365*'02 Assumptions'!$B$12,"Review","OK")))) -> Review | I12: Cross-check against Beneficiaries tab
A13: EST-009 | B13: Guardianship Plan | C13: Other | D13: Not Started | H13: =IF(B13="","",IF(D13<>"Complete","Review",IF(E13="","Review",IF(TODAY()-E13>365*'02 Assumptions'!$B$12,"Review","OK")))) -> Review | I13: If applicable
A14: EST-010 | B14: Executor / Trustee Confirmed | C14: Household | D14: Not Started | H14: =IF(B14="","",IF(D14<>"Complete","Review",IF(E14="","Review",IF(TODAY()-E14>365*'02 Assumptions'!$B$12,"Review","OK")))) -> Review
H15: =IF(B15="","",IF(D15<>"Complete","Review",IF(E15="","Review",IF(TODAY()-E15>365*'02 Assumptions'!$B$12,"Review","OK"))))
H16: =IF(B16="","",IF(D16<>"Complete","Review",IF(E16="","Review",IF(TODAY()-E16>365*'02 Assumptions'!$B$12,"Review","OK"))))
H17: =IF(B17="","",IF(D17<>"Complete","Review",IF(E17="","Review",IF(TODAY()-E17>365*'02 Assumptions'!$B$12,"Review","OK"))))
H18: =IF(B18="","",IF(D18<>"Complete","Review",IF(E18="","Review",IF(TODAY()-E18>365*'02 Assumptions'!$B$12,"Review","OK"))))
H19: =IF(B19="","",IF(D19<>"Complete","Review",IF(E19="","Review",IF(TODAY()-E19>365*'02 Assumptions'!$B$12,"Review","OK"))))
H20: =IF(B20="","",IF(D20<>"Complete","Review",IF(E20="","Review",IF(TODAY()-E20>365*'02 Assumptions'!$B$12,"Review","OK"))))
H21: =IF(B21="","",IF(D21<>"Complete","Review",IF(E21="","Review",IF(TODAY()-E21>365*'02 Assumptions'!$B$12,"Review","OK"))))
H22: =IF(B22="","",IF(D22<>"Complete","Review",IF(E22="","Review",IF(TODAY()-E22>365*'02 Assumptions'!$B$12,"Review","OK"))))
H23: =IF(B23="","",IF(D23<>"Complete","Review",IF(E23="","Review",IF(TODAY()-E23>365*'02 Assumptions'!$B$12,"Review","OK"))))
H24: =IF(B24="","",IF(D24<>"Complete","Review",IF(E24="","Review",IF(TODAY()-E24>365*'02 Assumptions'!$B$12,"Review","OK"))))
H25: =IF(B25="","",IF(D25<>"Complete","Review",IF(E25="","Review",IF(TODAY()-E25>365*'02 Assumptions'!$B$12,"Review","OK"))))
H26: =IF(B26="","",IF(D26<>"Complete","Review",IF(E26="","Review",IF(TODAY()-E26>365*'02 Assumptions'!$B$12,"Review","OK"))))
... H304: =IF(B304="","",IF(D304<>"Complete","Review",IF(E304="","Review",IF(TODAY()-E304>365*'02 Assumptions'!$B$12,"Review","OK"))))

Sheet 13 Beneficiaries
A1: Beneficiaries
A2: Review beneficiary designations across accounts, policies, retirement plans, trusts, and TOD/POD registrations.
A4: Item ID | B4: Account / Policy | C4: Owner | D4: Primary Beneficiary | E4: Primary % | F4: Contingent Beneficiary | G4: Contingent % | H4: Per Stirpes? | I4: Last Reviewed | J4: Issue Flag | K4: Notes | L4: Status

Sheet 14 Documents
A1: Document Checklist
A2: CFP intake checklist for records needed to build, verify, and maintain the planning analysis.
A4: Document ID | B4: Document / Record | C4: Category | D4: Needed? | E4: Received? | F4: Date Received | G4: Storage / Link | H4: Notes | I4: Status
A5: DOC-001 | B5: Most recent federal and state tax returns | C5: Tax | D5: Yes | E5: No | H5: Include all schedules and K-1s | I5: Pending
A6: DOC-002 | B6: Current-year pay stubs | C6: Income | D6: Yes | E6: No | H6: At least one recent pay stub per earner | I6: Pending
A7: DOC-003 | B7: Bonus / commission / equity compensation details | C7: Income | D7: Yes | E7: No | H7: If applicable | I7: Pending
A8: DOC-004 | B8: Bank statements | C8: Investments | D8: Yes | E8: No | H8: Checking, savings, CDs, money market | I8: Pending
A9: DOC-005 | B9: Brokerage account statements | C9: Investments | D9: Yes | E9: No | H9: Taxable investments and managed accounts | I9: Pending
A10: DOC-006 | B10: Retirement account statements | C10: Retirement | D10: Yes | E10: No | H10: 401(k), 403(b), IRA, Roth IRA, SEP/SIMPLE | I10: Pending
A11: DOC-007 | B11: HSA and FSA statements | C11: Benefits | D11: Yes | E11: No | H11: If applicable | I11: Pending
A12: DOC-008 | B12: 529 / education account statements | C12: Investments | D12: Yes | E12: No | H12: If applicable | I12: Pending
A13: DOC-009 | B13: Mortgage statements | C13: Debt | D13: Yes | E13: No | H13: Include rate, payment, escrow, and maturity | I13: Pending
A14: DOC-010 | B14: Student, auto, personal, and credit card statements | C14: Debt | D14: Yes | E14: No | H14: All outstanding debts | I14: Pending
A15: DOC-011 | B15: Life insurance policies | C15: Insurance | D15: Yes | E15: No | H15: Include group and individual coverage | I15: Pending
A16: DOC-012 | B16: Disability insurance policies | C16: Insurance | D16: Yes | E16: No | H16: Employer and individual coverage | I16: Pending
... A29: DOC-025 | B29: Charitable giving records / DAF statements | C29: Tax | D29: No | E29: No | H29: If relevant to tax or legacy planning | I29: N/A

Sheet 15 Action Plan
A1: Action Plan
A2: Track recommendations, follow-ups, owner, priority, due date, and status after the data intake and planning review.
A4: Action ID | B4: Planning Area | C4: Action Item | D4: Owner | E4: Priority | F4: Due Date | G4: Status | H4: Next Step | I4: Notes

Sheet 16 Data Map
A1: CFP Data Map
A2: Use this as the master intake checklist showing the data a CFP generally needs and where it is captured in this workbook.
A4: Planning Area | B4: Data Needed | C4: Why It Matters | D4: Captured In | E4: Collection Status | F4: Notes
A5: Personal | B5: Legal names, nicknames, pronouns, contact information | C5: Accurate planning records and household communication | D5: 03 Client Profile
A6: Personal | B6: Dates of birth and ages | C6: Retirement, insurance, education, estate, and tax planning | D6: 03 Client Profile
A7: Personal | B7: Marital status, dependents, citizenship, residency | C7: Tax filing, estate, benefits, insurance, and college planning | D7: 03 Client Profile / 11 Taxes
A8: Personal | B8: Employment, occupation, job stability, compensation structure | C8: Cash flow, insurance, benefits, retirement contributions | D8: 03 Client Profile / 10 Employee Benefits
A9: Personal | B9: Health status and family longevity considerations | C9: Insurance, retirement timing, LTC, estate planning | D9: 03 Client Profile / 08 Insurance
A10: Goals | B10: Retirement age, desired lifestyle, relocation plans | C10: Retirement income and savings strategy | D10: 04 Goals / 09 Retirement Income
A11: Goals | B11: Education funding goals | C11: Savings vehicles, cash flow, tax planning | D11: 04 Goals / 06 Assets
A12: Goals | B12: Major purchases, home, business, travel, legacy goals | C12: Prioritization and funding schedule | D12: 04 Goals
A13: Goals | B13: Risk tolerance, risk capacity, values constraints | C13: Investment policy and behavioral planning | D13: 03 Client Profile / 06 Assets
A14: Cash Flow | B14: Salary, bonus, commission, equity comp, business income | C14: Savings capacity, tax withholding, insurance needs | D14: 05 Cash Flow / 10 Employee Benefits
A15: Cash Flow | B15: Fixed and variable expenses | C15: Budget, retirement spending baseline, emergency reserve | D15: 05 Cash Flow
A16: Cash Flow | B16: Savings contributions and debt payments | C16: Goal funding and debt strategy | D16: 05 Cash Flow / 06 Assets / 07 Liabilities
... A44: Implementation | B44: Recommendations, owner, priority, due date, status | C44: Keeps the plan actionable | D44: 15 Action Plan

Sheet Tax Lots
A1: Asset | B1: Symbol | C1: Acquisition Date | D1: Term | E1: Shares | F1: Total Cost Basis | G1: Cost Basis Per Share | H1: Value | I1: Gain
A2: Google | B2: GOOG | C2: 46167 | D2: Short Term | E2: 9.591 | F2: 3638.63 | G2: 379.38 | H2: =$L$2*E2 -> 3189.583 | I2: =E2*($L$2-G2) -> -449.05062 | K2: GOOG | L2: =IFERROR(__xludf.DUMMYFUNCTION("GOOGLEFINANCE(""NASDAQ:GOOG"",""price"")"),332.56) -> 332.56
A3: Google | B3: GOOG | C3: 46167 | D3: Short Term | E3: 4.197 | F3: 1592.26 | G3: 379.38 | H3: =$L$2*E3 -> 1395.7543 | I3: =E3*($L$2-G3) -> -196.50354 | K3: SPCX | L3: =IFERROR(__xludf.DUMMYFUNCTION("GOOGLEFINANCE(""NASDAQ:SPCX"",""price"")"),112.42) -> 112.42
A4: Google | B4: GOOG | C4: 46167 | D4: Short Term | E4: 4.182 | F4: 1586.57 | G4: 379.38 | H4: =$L$2*E4 -> 1390.7659 | I4: =E4*($L$2-G4) -> -195.80124 | K4: Agilent | L4: =IFERROR(__xludf.DUMMYFUNCTION("GOOGLEFINANCE(""NYSE:A"",""price"")"),138.64) -> 138.64
A5: Google | B5: GOOG | C5: 46167 | D5: Short Term | E5: 2.381 | F5: 903.3 | G5: 379.38 | H5: =$L$2*E5 -> 791.82536 | I5: =E5*($L$2-G5) -> -111.47842 | K5: Keysight | L5: =IFERROR(__xludf.DUMMYFUNCTION("GOOGLEFINANCE(""NYSE:KEYS"",""price"")"),312.36) -> 312.36
A6: Google | B6: GOOG | C6: 46198 | D6: Short Term | E6: 2.383 | F6: 822.23 | G6: 345.04 | H6: =$L$2*E6 -> 792.49048 | I6: =E6*($L$2-G6) -> -29.73984
A7: Google | B7: GOOG | C7: 46137 | D7: Short Term | E7: 2.381 | F7: 815.06 | G7: 342.32 | H7: =$L$2*E7 -> 791.82536 | I7: =E7*($L$2-G7) -> -23.23856
A8: Google | B8: GOOG | C8: 46198 | D8: Short Term | E8: 4.2 | F8: 1449.17 | G8: 345.04 | H8: =$L$2*E8 -> 1396.752 | I8: =E8*($L$2-G8) -> -52.416
A9: Google | B9: GOOG | C9: 46198 | D9: Short Term | E9: 4.784 | F9: 1650.67 | G9: 345.04 | H9: =$L$2*E9 -> 1590.967 | I9: =E9*($L$2-G9) -> -59.70432
A10: Google | B10: GOOG | C10: 46137 | D10: Short Term | E10: 4.182 | F10: 1431.58 | G10: 342.32 | H10: =$L$2*E10 -> 1390.7659 | I10: =E10*($L$2-G10) -> -40.81632
A11: Google | B11: GOOG | C11: 46137 | D11: Short Term | E11: 4.797 | F11: 1642.11 | G11: 342.32 | H11: =$L$2*E11 -> 1595.2903 | I11: =E11*($L$2-G11) -> -46.81872
A12: Google | B12: GOOG | C12: 46198 | D12: Short Term | E12: 8.998 | F12: 3104.67 | G12: 345.04 | H12: =$L$2*E12 -> 2992.3749 | I12: =E12*($L$2-G12) -> -112.29504
A13: Google | B13: GOOG | C13: 46137 | D13: Short Term | E13: 8.993 | F13: 3078.48 | G13: 342.32 | H13: =$L$2*E13 -> 2990.7121 | I13: =E13*($L$2-G13) -> -87.77168
A14: Google | B14: GOOG | C14: 46106 | D14: Short Term | E14: 1.786 | F14: 516.51 | G14: 289.2 | H14: =$L$2*E14 -> 593.95216 | I14: =E14*($L$2-G14) -> 77.44096
A15: Google | B15: GOOG | C15: 46047 | D15: Short Term | E15: 4.778 | F15: 1569.24 | G15: 328.43 | H15: =$L$2*E15 -> 1588.9717 | I15: =E15*($L$2-G15) -> 19.73314
A16: Google | B16: GOOG | C16: 46047 | D16: Short Term | E16: 4.793 | F16: 1574.16 | G16: 328.43 | H16: =$L$2*E16 -> 1593.9601 | I16: =E16*($L$2-G16) -> 19.79509
A17: Google | B17: GOOG | C17: 45986 | D17: Short Term | E17: 4.173 | F17: 1328.98 | G17: 318.47 | H17: =$L$2*E17 -> 1387.7729 | I17: =E17*($L$2-G17) -> 58.79757
... A120: Google | B120: GOOG | C120: 45010 | D120: Long Term | E120: 106.596 | F120: 11305.57 | G120: 106.06 | H120: =$L$2*E120 -> 35449.566 | I120: =E120*($L$2-G120) -> 24143.994
A122: SpaceX | B122: SPCX | C122: 43600 | D122: Long Term | E122: 1650 | F122: 6732 | G122: =F122/E122 -> 4.08 | H122: =$L$2*E122 -> 548724 | I122: =E122*($L$3-G122) -> 178761
A123: SpaceX | B123: SPCX | C123: 43419 | D123: Long Term | E123: 1700 | F123: 5746 | G123: =F123/E123 -> 3.38 | H123: =$L$3*E123 -> 191114 | I123: =E123*($L$3-G123) -> 185368
A124: SpaceX | B124: SPCX | C124: 43910 | D124: Long Term | E124: 1900 | F124: 6422 | G124: =F124/E124 -> 3.38 | H124: =$L$3*E124 -> 213598 | I124: =E124*($L$3-G124) -> 207176
A125: SpaceX | B125: SPCX | C125: 43600 | D125: Long Term | E125: 5000 | F125: 20400 | G125: =F125/E125 -> 4.08 | H125: =$L$3*E125 -> 562100 | I125: =E125*($L$3-G125) -> 541700
A126: SpaceX | B126: SPCX | C126: 43054 | D126: Long Term | E126: 10000 | F126: 27000 | G126: =F126/E126 -> 2.7 | H126: =$L$3*E126 -> 1124200 | I126: =E126*($L$3-G126) -> 1097200

Sheet Hedge
A2: Current Holdings & Prices | B2: Holdings | C2: Hedge | E2: Scenario Matrix: Total P&L | G2: Profit Matrix
A3: Asset | E3: ARKX Price at Expiration
A4: Ticker | B4: SPCX | C4: ARKX | D4: SPCX Price | E4: =$C$6*0.7 -> 21.063 | F4: =$C$6*0.8 -> 24.072 | G4: =$C$6*0.9 -> 27.081 | H4: =$C$6*1 -> 30.09 | I4: =$C$6*1.1 -> 33.099 | J4: =$C$6*1.2 -> 36.108 | K4: =$C$6*1.3 -> 39.117 | L4: =$C$6*1.4 -> 42.126 | M4: =$C$6*1.5 -> 45.135 | N4: =$C$6*1.6 -> 48.144
A5: Shares | B5: 20000 | C5: 0 | D5: =$B$6*0.5 -> 56.21 | E5: =($B$5 * ($D5 - $B$6)) + ($B$10 * 100 * (MAX(0, $B$11 - E$4) - MAX(0, $B$13 - E$4))) - $B$15 -> -1108700 | F5: =($B$5 * ($D5 - $B$6)) + ($B$10 * 100 * (MAX(0, $B$11 - F$4) - MAX(0, $B$13 - F$4))) - $B$15 -> -1108700 | G5: =($B$5 * ($D5 - $B$6)) + ($B$10 * 100 * (MAX(0, $B$11 - G$4) - MAX(0, $B$13 - G$4))) - $B$15 -> -1109105 | H5: =($B$5 * ($D5 - $B$6)) + ($B$10 * 100 * (MAX(0, $B$11 - H$4) - MAX(0, $B$13 - H$4))) - $B$15 -> -1124150 | I5: =($B$5 * ($D5 - $B$6)) + ($B$10 * 100 * (MAX(0, $B$11 - I$4) - MAX(0, $B$13 - I$4))) - $B$15 -> -1128700 | J5: =($B$5 * ($D5 - $B$6)) + ($B$10 * 100 * (MAX(0, $B$11 - J$4) - MAX(0, $B$13 - J$4))) - $B$15 -> -1128700 | K5: =($B$5 * ($D5 - $B$6)) + ($B$10 * 100 * (MAX(0, $B$11 - K$4) - MAX(0, $B$13 - K$4))) - $B$15 -> -1128700 | L5: =($B$5 * ($D5 - $B$6)) + ($B$10 * 100 * (MAX(0, $B$11 - L$4) - MAX(0, $B$13 - L$4))) - $B$15 -> -1128700 | ... N5: =($B$5 * ($D5 - $B$6)) + ($B$10 * 100 * (MAX(0, $B$11 - N$4) - MAX(0, $B$13 - N$4))) - $B$15 -> -1128700
A6: Current Price | B6: =IFERROR(__xludf.DUMMYFUNCTION("GOOGLEFINANCE(B4, ""price"")"),112.42) -> 112.42 | C6: =IFERROR(__xludf.DUMMYFUNCTION("GOOGLEFINANCE(""BATS:ARKX"")"),30.09) -> 30.09 | D6: =$B$6*0.6 -> 67.452 | E6: =($B$5 * ($D6 - $B$6)) + ($B$10 * 100 * (MAX(0, $B$11 - E$4) - MAX(0, $B$13 - E$4))) - $B$15 -> -883860 | F6: =($B$5 * ($D6 - $B$6)) + ($B$10 * 100 * (MAX(0, $B$11 - F$4) - MAX(0, $B$13 - F$4))) - $B$15 -> -883860 | G6: =($B$5 * ($D6 - $B$6)) + ($B$10 * 100 * (MAX(0, $B$11 - G$4) - MAX(0, $B$13 - G$4))) - $B$15 -> -884265 | H6: =($B$5 * ($D6 - $B$6)) + ($B$10 * 100 * (MAX(0, $B$11 - H$4) - MAX(0, $B$13 - H$4))) - $B$15 -> -899310 | I6: =($B$5 * ($D6 - $B$6)) + ($B$10 * 100 * (MAX(0, $B$11 - I$4) - MAX(0, $B$13 - I$4))) - $B$15 -> -903860 | J6: =($B$5 * ($D6 - $B$6)) + ($B$10 * 100 * (MAX(0, $B$11 - J$4) - MAX(0, $B$13 - J$4))) - $B$15 -> -903860 | K6: =($B$5 * ($D6 - $B$6)) + ($B$10 * 100 * (MAX(0, $B$11 - K$4) - MAX(0, $B$13 - K$4))) - $B$15 -> -903860 | L6: =($B$5 * ($D6 - $B$6)) + ($B$10 * 100 * (MAX(0, $B$11 - L$4) - MAX(0, $B$13 - L$4))) - $B$15 -> -903860 | ... N6: =($B$5 * ($D6 - $B$6)) + ($B$10 * 100 * (MAX(0, $B$11 - N$4) - MAX(0, $B$13 - N$4))) - $B$15 -> -903860
A7: Total Value | B7: =B5*B6 -> 2248400 | D7: =$B$6*0.7 -> 78.694 | E7: =($B$5 * ($D7 - $B$6)) + ($B$10 * 100 * (MAX(0, $B$11 - E$4) - MAX(0, $B$13 - E$4))) - $B$15 -> -659020 | F7: =($B$5 * ($D7 - $B$6)) + ($B$10 * 100 * (MAX(0, $B$11 - F$4) - MAX(0, $B$13 - F$4))) - $B$15 -> -659020 | G7: =($B$5 * ($D7 - $B$6)) + ($B$10 * 100 * (MAX(0, $B$11 - G$4) - MAX(0, $B$13 - G$4))) - $B$15 -> -659425 | H7: =($B$5 * ($D7 - $B$6)) + ($B$10 * 100 * (MAX(0, $B$11 - H$4) - MAX(0, $B$13 - H$4))) - $B$15 -> -674470 | I7: =($B$5 * ($D7 - $B$6)) + ($B$10 * 100 * (MAX(0, $B$11 - I$4) - MAX(0, $B$13 - I$4))) - $B$15 -> -679020 | J7: =($B$5 * ($D7 - $B$6)) + ($B$10 * 100 * (MAX(0, $B$11 - J$4) - MAX(0, $B$13 - J$4))) - $B$15 -> -679020 | K7: =($B$5 * ($D7 - $B$6)) + ($B$10 * 100 * (MAX(0, $B$11 - K$4) - MAX(0, $B$13 - K$4))) - $B$15 -> -679020 | L7: =($B$5 * ($D7 - $B$6)) + ($B$10 * 100 * (MAX(0, $B$11 - L$4) - MAX(0, $B$13 - L$4))) - $B$15 -> -679020 | ... N7: =($B$5 * ($D7 - $B$6)) + ($B$10 * 100 * (MAX(0, $B$11 - N$4) - MAX(0, $B$13 - N$4))) - $B$15 -> -679020
D8: =$B$6*0.8 -> 89.936 | E8: =($B$5 * ($D8 - $B$6)) + ($B$10 * 100 * (MAX(0, $B$11 - E$4) - MAX(0, $B$13 - E$4))) - $B$15 -> -434180 | F8: =($B$5 * ($D8 - $B$6)) + ($B$10 * 100 * (MAX(0, $B$11 - F$4) - MAX(0, $B$13 - F$4))) - $B$15 -> -434180 | G8: =($B$5 * ($D8 - $B$6)) + ($B$10 * 100 * (MAX(0, $B$11 - G$4) - MAX(0, $B$13 - G$4))) - $B$15 -> -434585 | H8: =($B$5 * ($D8 - $B$6)) + ($B$10 * 100 * (MAX(0, $B$11 - H$4) - MAX(0, $B$13 - H$4))) - $B$15 -> -449630 | I8: =($B$5 * ($D8 - $B$6)) + ($B$10 * 100 * (MAX(0, $B$11 - I$4) - MAX(0, $B$13 - I$4))) - $B$15 -> -454180 | J8: =($B$5 * ($D8 - $B$6)) + ($B$10 * 100 * (MAX(0, $B$11 - J$4) - MAX(0, $B$13 - J$4))) - $B$15 -> -454180 | K8: =($B$5 * ($D8 - $B$6)) + ($B$10 * 100 * (MAX(0, $B$11 - K$4) - MAX(0, $B$13 - K$4))) - $B$15 -> -454180 | L8: =($B$5 * ($D8 - $B$6)) + ($B$10 * 100 * (MAX(0, $B$11 - L$4) - MAX(0, $B$13 - L$4))) - $B$15 -> -454180 | ... N8: =($B$5 * ($D8 - $B$6)) + ($B$10 * 100 * (MAX(0, $B$11 - N$4) - MAX(0, $B$13 - N$4))) - $B$15 -> -454180
A9: Bear Put Spread (ARKX) | B9: Values | D9: =$B$6*0.9 -> 101.178 | E9: =($B$5 * ($D9 - $B$6)) + ($B$10 * 100 * (MAX(0, $B$11 - E$4) - MAX(0, $B$13 - E$4))) - $B$15 -> -209340 | F9: =($B$5 * ($D9 - $B$6)) + ($B$10 * 100 * (MAX(0, $B$11 - F$4) - MAX(0, $B$13 - F$4))) - $B$15 -> -209340 | G9: =($B$5 * ($D9 - $B$6)) + ($B$10 * 100 * (MAX(0, $B$11 - G$4) - MAX(0, $B$13 - G$4))) - $B$15 -> -209745 | H9: =($B$5 * ($D9 - $B$6)) + ($B$10 * 100 * (MAX(0, $B$11 - H$4) - MAX(0, $B$13 - H$4))) - $B$15 -> -224790 | I9: =($B$5 * ($D9 - $B$6)) + ($B$10 * 100 * (MAX(0, $B$11 - I$4) - MAX(0, $B$13 - I$4))) - $B$15 -> -229340 | J9: =($B$5 * ($D9 - $B$6)) + ($B$10 * 100 * (MAX(0, $B$11 - J$4) - MAX(0, $B$13 - J$4))) - $B$15 -> -229340 | K9: =($B$5 * ($D9 - $B$6)) + ($B$10 * 100 * (MAX(0, $B$11 - K$4) - MAX(0, $B$13 - K$4))) - $B$15 -> -229340 | L9: =($B$5 * ($D9 - $B$6)) + ($B$10 * 100 * (MAX(0, $B$11 - L$4) - MAX(0, $B$13 - L$4))) - $B$15 -> -229340 | ... N9: =($B$5 * ($D9 - $B$6)) + ($B$10 * 100 * (MAX(0, $B$11 - N$4) - MAX(0, $B$13 - N$4))) - $B$15 -> -229340
A10: Contracts | B10: 50 | D10: =$B$6*1.1 -> 123.662 | E10: =($B$5 * ($D10 - $B$6)) + ($B$10 * 100 * (MAX(0, $B$11 - E$4) - MAX(0, $B$13 - E$4))) - $B$15 -> 240340 | F10: =($B$5 * ($D10 - $B$6)) + ($B$10 * 100 * (MAX(0, $B$11 - F$4) - MAX(0, $B$13 - F$4))) - $B$15 -> 240340 | G10: =($B$5 * ($D10 - $B$6)) + ($B$10 * 100 * (MAX(0, $B$11 - G$4) - MAX(0, $B$13 - G$4))) - $B$15 -> 239935 | H10: =($B$5 * ($D10 - $B$6)) + ($B$10 * 100 * (MAX(0, $B$11 - H$4) - MAX(0, $B$13 - H$4))) - $B$15 -> 224890 | I10: =($B$5 * ($D10 - $B$6)) + ($B$10 * 100 * (MAX(0, $B$11 - I$4) - MAX(0, $B$13 - I$4))) - $B$15 -> 220340 | J10: =($B$5 * ($D10 - $B$6)) + ($B$10 * 100 * (MAX(0, $B$11 - J$4) - MAX(0, $B$13 - J$4))) - $B$15 -> 220340 | K10: =($B$5 * ($D10 - $B$6)) + ($B$10 * 100 * (MAX(0, $B$11 - K$4) - MAX(0, $B$13 - K$4))) - $B$15 -> 220340 | L10: =($B$5 * ($D10 - $B$6)) + ($B$10 * 100 * (MAX(0, $B$11 - L$4) - MAX(0, $B$13 - L$4))) - $B$15 -> 220340 | ... N10: =($B$5 * ($D10 - $B$6)) + ($B$10 * 100 * (MAX(0, $B$11 - N$4) - MAX(0, $B$13 - N$4))) - $B$15 -> 220340
A11: Long Put Strike | B11: 31 | D11: =$B$6*1.2 -> 134.904 | E11: =($B$5 * ($D11 - $B$6)) + ($B$10 * 100 * (MAX(0, $B$11 - E$4) - MAX(0, $B$13 - E$4))) - $B$15 -> 465180 | F11: =($B$5 * ($D11 - $B$6)) + ($B$10 * 100 * (MAX(0, $B$11 - F$4) - MAX(0, $B$13 - F$4))) - $B$15 -> 465180 | G11: =($B$5 * ($D11 - $B$6)) + ($B$10 * 100 * (MAX(0, $B$11 - G$4) - MAX(0, $B$13 - G$4))) - $B$15 -> 464775 | H11: =($B$5 * ($D11 - $B$6)) + ($B$10 * 100 * (MAX(0, $B$11 - H$4) - MAX(0, $B$13 - H$4))) - $B$15 -> 449730 | I11: =($B$5 * ($D11 - $B$6)) + ($B$10 * 100 * (MAX(0, $B$11 - I$4) - MAX(0, $B$13 - I$4))) - $B$15 -> 445180 | J11: =($B$5 * ($D11 - $B$6)) + ($B$10 * 100 * (MAX(0, $B$11 - J$4) - MAX(0, $B$13 - J$4))) - $B$15 -> 445180 | K11: =($B$5 * ($D11 - $B$6)) + ($B$10 * 100 * (MAX(0, $B$11 - K$4) - MAX(0, $B$13 - K$4))) - $B$15 -> 445180 | L11: =($B$5 * ($D11 - $B$6)) + ($B$10 * 100 * (MAX(0, $B$11 - L$4) - MAX(0, $B$13 - L$4))) - $B$15 -> 445180 | ... N11: =($B$5 * ($D11 - $B$6)) + ($B$10 * 100 * (MAX(0, $B$11 - N$4) - MAX(0, $B$13 - N$4))) - $B$15 -> 445180
A12: Long Put Premium | B12: 1.15 | D12: =$B$6*1.3 -> 146.146 | E12: =($B$5 * ($D12 - $B$6)) + ($B$10 * 100 * (MAX(0, $B$11 - E$4) - MAX(0, $B$13 - E$4))) - $B$15 -> 690020 | F12: =($B$5 * ($D12 - $B$6)) + ($B$10 * 100 * (MAX(0, $B$11 - F$4) - MAX(0, $B$13 - F$4))) - $B$15 -> 690020 | G12: =($B$5 * ($D12 - $B$6)) + ($B$10 * 100 * (MAX(0, $B$11 - G$4) - MAX(0, $B$13 - G$4))) - $B$15 -> 689615 | H12: =($B$5 * ($D12 - $B$6)) + ($B$10 * 100 * (MAX(0, $B$11 - H$4) - MAX(0, $B$13 - H$4))) - $B$15 -> 674570 | I12: =($B$5 * ($D12 - $B$6)) + ($B$10 * 100 * (MAX(0, $B$11 - I$4) - MAX(0, $B$13 - I$4))) - $B$15 -> 670020 | J12: =($B$5 * ($D12 - $B$6)) + ($B$10 * 100 * (MAX(0, $B$11 - J$4) - MAX(0, $B$13 - J$4))) - $B$15 -> 670020 | K12: =($B$5 * ($D12 - $B$6)) + ($B$10 * 100 * (MAX(0, $B$11 - K$4) - MAX(0, $B$13 - K$4))) - $B$15 -> 670020 | L12: =($B$5 * ($D12 - $B$6)) + ($B$10 * 100 * (MAX(0, $B$11 - L$4) - MAX(0, $B$13 - L$4))) - $B$15 -> 670020 | ... N12: =($B$5 * ($D12 - $B$6)) + ($B$10 * 100 * (MAX(0, $B$11 - N$4) - MAX(0, $B$13 - N$4))) - $B$15 -> 670020
A13: Short Put Strike | B13: 27 | D13: =$B$6*1.4 -> 157.388 | E13: =($B$5 * ($D13 - $B$6)) + ($B$10 * 100 * (MAX(0, $B$11 - E$4) - MAX(0, $B$13 - E$4))) - $B$15 -> 914860 | F13: =($B$5 * ($D13 - $B$6)) + ($B$10 * 100 * (MAX(0, $B$11 - F$4) - MAX(0, $B$13 - F$4))) - $B$15 -> 914860 | G13: =($B$5 * ($D13 - $B$6)) + ($B$10 * 100 * (MAX(0, $B$11 - G$4) - MAX(0, $B$13 - G$4))) - $B$15 -> 914455 | H13: =($B$5 * ($D13 - $B$6)) + ($B$10 * 100 * (MAX(0, $B$11 - H$4) - MAX(0, $B$13 - H$4))) - $B$15 -> 899410 | I13: =($B$5 * ($D13 - $B$6)) + ($B$10 * 100 * (MAX(0, $B$11 - I$4) - MAX(0, $B$13 - I$4))) - $B$15 -> 894860 | J13: =($B$5 * ($D13 - $B$6)) + ($B$10 * 100 * (MAX(0, $B$11 - J$4) - MAX(0, $B$13 - J$4))) - $B$15 -> 894860 | K13: =($B$5 * ($D13 - $B$6)) + ($B$10 * 100 * (MAX(0, $B$11 - K$4) - MAX(0, $B$13 - K$4))) - $B$15 -> 894860 | L13: =($B$5 * ($D13 - $B$6)) + ($B$10 * 100 * (MAX(0, $B$11 - L$4) - MAX(0, $B$13 - L$4))) - $B$15 -> 894860 | ... N13: =($B$5 * ($D13 - $B$6)) + ($B$10 * 100 * (MAX(0, $B$11 - N$4) - MAX(0, $B$13 - N$4))) - $B$15 -> 894860
A14: Short Put Premium | B14: 0.25 | D14: =$B$6*1.5 -> 168.63 | E14: =($B$5 * ($D14 - $B$6)) + ($B$10 * 100 * (MAX(0, $B$11 - E$4) - MAX(0, $B$13 - E$4))) - $B$15 -> 1139700 | F14: =($B$5 * ($D14 - $B$6)) + ($B$10 * 100 * (MAX(0, $B$11 - F$4) - MAX(0, $B$13 - F$4))) - $B$15 -> 1139700 | G14: =($B$5 * ($D14 - $B$6)) + ($B$10 * 100 * (MAX(0, $B$11 - G$4) - MAX(0, $B$13 - G$4))) - $B$15 -> 1139295 | H14: =($B$5 * ($D14 - $B$6)) + ($B$10 * 100 * (MAX(0, $B$11 - H$4) - MAX(0, $B$13 - H$4))) - $B$15 -> 1124250 | I14: =($B$5 * ($D14 - $B$6)) + ($B$10 * 100 * (MAX(0, $B$11 - I$4) - MAX(0, $B$13 - I$4))) - $B$15 -> 1119700 | J14: =($B$5 * ($D14 - $B$6)) + ($B$10 * 100 * (MAX(0, $B$11 - J$4) - MAX(0, $B$13 - J$4))) - $B$15 -> 1119700 | K14: =($B$5 * ($D14 - $B$6)) + ($B$10 * 100 * (MAX(0, $B$11 - K$4) - MAX(0, $B$13 - K$4))) - $B$15 -> 1119700 | L14: =($B$5 * ($D14 - $B$6)) + ($B$10 * 100 * (MAX(0, $B$11 - L$4) - MAX(0, $B$13 - L$4))) - $B$15 -> 1119700 | ... N14: =($B$5 * ($D14 - $B$6)) + ($B$10 * 100 * (MAX(0, $B$11 - N$4) - MAX(0, $B$13 - N$4))) - $B$15 -> 1119700
A15: Net Premium Paid | B15: =(B12-B14)*B10*100 -> 4500 | D15: =$B$6*1.6 -> 179.872 | E15: =($B$5 * ($D15 - $B$6)) + ($B$10 * 100 * (MAX(0, $B$11 - E$4) - MAX(0, $B$13 - E$4))) - $B$15 -> 1364540 | F15: =($B$5 * ($D15 - $B$6)) + ($B$10 * 100 * (MAX(0, $B$11 - F$4) - MAX(0, $B$13 - F$4))) - $B$15 -> 1364540 | G15: =($B$5 * ($D15 - $B$6)) + ($B$10 * 100 * (MAX(0, $B$11 - G$4) - MAX(0, $B$13 - G$4))) - $B$15 -> 1364135 | H15: =($B$5 * ($D15 - $B$6)) + ($B$10 * 100 * (MAX(0, $B$11 - H$4) - MAX(0, $B$13 - H$4))) - $B$15 -> 1349090 | I15: =($B$5 * ($D15 - $B$6)) + ($B$10 * 100 * (MAX(0, $B$11 - I$4) - MAX(0, $B$13 - I$4))) - $B$15 -> 1344540 | J15: =($B$5 * ($D15 - $B$6)) + ($B$10 * 100 * (MAX(0, $B$11 - J$4) - MAX(0, $B$13 - J$4))) - $B$15 -> 1344540 | K15: =($B$5 * ($D15 - $B$6)) + ($B$10 * 100 * (MAX(0, $B$11 - K$4) - MAX(0, $B$13 - K$4))) - $B$15 -> 1344540 | L15: =($B$5 * ($D15 - $B$6)) + ($B$10 * 100 * (MAX(0, $B$11 - L$4) - MAX(0, $B$13 - L$4))) - $B$15 -> 1344540 | ... N15: =($B$5 * ($D15 - $B$6)) + ($B$10 * 100 * (MAX(0, $B$11 - N$4) - MAX(0, $B$13 - N$4))) - $B$15 -> 1344540
A16: Max Profit | B16: =((B11-B13)*B10*100)-B15 -> 15500 | D16: =$B$6*1.7 -> 191.114 | E16: =($B$5 * ($D16 - $B$6)) + ($B$10 * 100 * (MAX(0, $B$11 - E$4) - MAX(0, $B$13 - E$4))) - $B$15 -> 1589380 | F16: =($B$5 * ($D16 - $B$6)) + ($B$10 * 100 * (MAX(0, $B$11 - F$4) - MAX(0, $B$13 - F$4))) - $B$15 -> 1589380 | G16: =($B$5 * ($D16 - $B$6)) + ($B$10 * 100 * (MAX(0, $B$11 - G$4) - MAX(0, $B$13 - G$4))) - $B$15 -> 1588975 | H16: =($B$5 * ($D16 - $B$6)) + ($B$10 * 100 * (MAX(0, $B$11 - H$4) - MAX(0, $B$13 - H$4))) - $B$15 -> 1573930 | I16: =($B$5 * ($D16 - $B$6)) + ($B$10 * 100 * (MAX(0, $B$11 - I$4) - MAX(0, $B$13 - I$4))) - $B$15 -> 1569380 | J16: =($B$5 * ($D16 - $B$6)) + ($B$10 * 100 * (MAX(0, $B$11 - J$4) - MAX(0, $B$13 - J$4))) - $B$15 -> 1569380 | K16: =($B$5 * ($D16 - $B$6)) + ($B$10 * 100 * (MAX(0, $B$11 - K$4) - MAX(0, $B$13 - K$4))) - $B$15 -> 1569380 | L16: =($B$5 * ($D16 - $B$6)) + ($B$10 * 100 * (MAX(0, $B$11 - L$4) - MAX(0, $B$13 - L$4))) - $B$15 -> 1569380 | ... N16: =($B$5 * ($D16 - $B$6)) + ($B$10 * 100 * (MAX(0, $B$11 - N$4) - MAX(0, $B$13 - N$4))) - $B$15 -> 1569380
A17: Max Loss | B17: =B15 -> 4500 | D17: =$B$6*1.8 -> 202.356 | E17: =($B$5 * ($D17 - $B$6)) + ($B$10 * 100 * (MAX(0, $B$11 - E$4) - MAX(0, $B$13 - E$4))) - $B$15 -> 1814220 | F17: =($B$5 * ($D17 - $B$6)) + ($B$10 * 100 * (MAX(0, $B$11 - F$4) - MAX(0, $B$13 - F$4))) - $B$15 -> 1814220 | G17: =($B$5 * ($D17 - $B$6)) + ($B$10 * 100 * (MAX(0, $B$11 - G$4) - MAX(0, $B$13 - G$4))) - $B$15 -> 1813815 | H17: =($B$5 * ($D17 - $B$6)) + ($B$10 * 100 * (MAX(0, $B$11 - H$4) - MAX(0, $B$13 - H$4))) - $B$15 -> 1798770 | I17: =($B$5 * ($D17 - $B$6)) + ($B$10 * 100 * (MAX(0, $B$11 - I$4) - MAX(0, $B$13 - I$4))) - $B$15 -> 1794220 | J17: =($B$5 * ($D17 - $B$6)) + ($B$10 * 100 * (MAX(0, $B$11 - J$4) - MAX(0, $B$13 - J$4))) - $B$15 -> 1794220 | K17: =($B$5 * ($D17 - $B$6)) + ($B$10 * 100 * (MAX(0, $B$11 - K$4) - MAX(0, $B$13 - K$4))) - $B$15 -> 1794220 | L17: =($B$5 * ($D17 - $B$6)) + ($B$10 * 100 * (MAX(0, $B$11 - L$4) - MAX(0, $B$13 - L$4))) - $B$15 -> 1794220 | ... N17: =($B$5 * ($D17 - $B$6)) + ($B$10 * 100 * (MAX(0, $B$11 - N$4) - MAX(0, $B$13 - N$4))) - $B$15 -> 1794220
A18: Breakeven (ARKX) | B18: =B11-(B15/(B10*100)) -> 30.1 | D18: =$B$6*1.9 -> 213.598 | E18: =($B$5 * ($D18 - $B$6)) + ($B$10 * 100 * (MAX(0, $B$11 - E$4) - MAX(0, $B$13 - E$4))) - $B$15 -> 2039060 | F18: =($B$5 * ($D18 - $B$6)) + ($B$10 * 100 * (MAX(0, $B$11 - F$4) - MAX(0, $B$13 - F$4))) - $B$15 -> 2039060 | G18: =($B$5 * ($D18 - $B$6)) + ($B$10 * 100 * (MAX(0, $B$11 - G$4) - MAX(0, $B$13 - G$4))) - $B$15 -> 2038655 | H18: =($B$5 * ($D18 - $B$6)) + ($B$10 * 100 * (MAX(0, $B$11 - H$4) - MAX(0, $B$13 - H$4))) - $B$15 -> 2023610 | I18: =($B$5 * ($D18 - $B$6)) + ($B$10 * 100 * (MAX(0, $B$11 - I$4) - MAX(0, $B$13 - I$4))) - $B$15 -> 2019060 | J18: =($B$5 * ($D18 - $B$6)) + ($B$10 * 100 * (MAX(0, $B$11 - J$4) - MAX(0, $B$13 - J$4))) - $B$15 -> 2019060 | K18: =($B$5 * ($D18 - $B$6)) + ($B$10 * 100 * (MAX(0, $B$11 - K$4) - MAX(0, $B$13 - K$4))) - $B$15 -> 2019060 | L18: =($B$5 * ($D18 - $B$6)) + ($B$10 * 100 * (MAX(0, $B$11 - L$4) - MAX(0, $B$13 - L$4))) - $B$15 -> 2019060 | ... N18: =($B$5 * ($D18 - $B$6)) + ($B$10 * 100 * (MAX(0, $B$11 - N$4) - MAX(0, $B$13 - N$4))) - $B$15 -> 2019060
A21: ARKX Bear Put Spread Profit | E21: {=(IF($B$11 - E4:N4 > 0, $B$11 - E4:N4, 0) - IF($B$13 - E4:N4 > 0, $B$13 - E4:N4, 0)) * $B$10 * 100 - $B$15} -> 15500 | F21: 15500 | G21: 15095 | H21: 50 | I21: -4500 | J21: -4500 | K21: -4500 | L21: -4500 | M21: -4500 | N21: -4500
E23: Balance Matrix
D24: SPCX Price | E24: {=E4:N4} -> 21.063 | F24: 24.072 | G24: 27.081 | H24: 30.09 | I24: 33.099 | J24: 36.108 | K24: 39.117 | L24: 42.126 | M24: 45.135 | N24: 48.144
D25: {=D5:D18} -> 56.21 | E25: {=$B$7 + E5:N18} -> 1139700 | F25: 1139700 | G25: 1139295 | H25: 1124250 | I25: 1119700 | J25: 1119700 | K25: 1119700 | L25: 1119700 | M25: 1119700 | N25: 1119700
D26: 67.452 | E26: 1364540 | F26: 1364540 | G26: 1364135 | H26: 1349090 | I26: 1344540 | J26: 1344540 | K26: 1344540 | L26: 1344540 | M26: 1344540 | N26: 1344540
D27: 78.694 | E27: 1589380 | F27: 1589380 | G27: 1588975 | H27: 1573930 | I27: 1569380 | J27: 1569380 | K27: 1569380 | L27: 1569380 | M27: 1569380 | N27: 1569380
D28: 89.936 | E28: 1814220 | F28: 1814220 | G28: 1813815 | H28: 1798770 | I28: 1794220 | J28: 1794220 | K28: 1794220 | L28: 1794220 | M28: 1794220 | N28: 1794220
D29: 101.178 | E29: 2039060 | F29: 2039060 | G29: 2038655 | H29: 2023610 | I29: 2019060 | J29: 2019060 | K29: 2019060 | L29: 2019060 | M29: 2019060 | N29: 2019060
D30: 123.662 | E30: 2488740 | F30: 2488740 | G30: 2488335 | H30: 2473290 | I30: 2468740 | J30: 2468740 | K30: 2468740 | L30: 2468740 | M30: 2468740 | N30: 2468740
D31: 134.904 | E31: 2713580 | F31: 2713580 | G31: 2713175 | H31: 2698130 | I31: 2693580 | J31: 2693580 | K31: 2693580 | L31: 2693580 | M31: 2693580 | N31: 2693580
D32: 146.146 | E32: 2938420 | F32: 2938420 | G32: 2938015 | H32: 2922970 | I32: 2918420 | J32: 2918420 | K32: 2918420 | L32: 2918420 | M32: 2918420 | N32: 2918420
D33: 157.388 | E33: 3163260 | F33: 3163260 | G33: 3162855 | H33: 3147810 | I33: 3143260 | J33: 3143260 | K33: 3143260 | L33: 3143260 | M33: 3143260 | N33: 3143260
D34: 168.63 | E34: 3388100 | F34: 3388100 | G34: 3387695 | H34: 3372650 | I34: 3368100 | J34: 3368100 | K34: 3368100 | L34: 3368100 | M34: 3368100 | N34: 3368100
D35: 179.872 | E35: 3612940 | F35: 3612940 | G35: 3612535 | H35: 3597490 | I35: 3592940 | J35: 3592940 | K35: 3592940 | L35: 3592940 | M35: 3592940 | N35: 3592940
D36: 191.114 | E36: 3837780 | F36: 3837780 | G36: 3837375 | H36: 3822330 | I36: 3817780 | J36: 3817780 | K36: 3817780 | L36: 3817780 | M36: 3817780 | N36: 3817780
D37: 202.356 | E37: 4062620 | F37: 4062620 | G37: 4062215 | H37: 4047170 | I37: 4042620 | J37: 4042620 | K37: 4042620 | L37: 4042620 | M37: 4042620 | N37: 4042620
D38: 213.598 | E38: 4287460 | F38: 4287460 | G38: 4287055 | H38: 4272010 | I38: 4267460 | J38: 4267460 | K38: 4267460 | L38: 4267460 | M38: 4267460 | N38: 4267460
A43: SpaceX | I43: ARKX
A44: Date | B44: Open | C44: High | D44: Low | E44: SPCX Close | F44: Adj Close | G44: Volume | I44: Date | J44: Open | K44: High | L44: Low | M44: ARKX Close | N44: Adj Close | O44: Volume
A45: 46185 | B45: 150 | C45: 176.52 | D45: 149.34 | E45: 160.95 | F45: 160.95 | G45: 519234800 | I45: 46185 | J45: 34.71 | K45: 34.74 | L45: 33.44 | M45: 33.78 | N45: 33.78 | O45: 2549500
A46: 46188 | B46: 171.74 | C46: 193 | D46: 168.35 | E46: 192.5 | F46: 192.5 | G46: 256226600 | I46: 46188 | J46: 34.9 | K46: 35.31 | L46: 34.84 | M46: 35.18 | N46: 35.18 | O46: 3063700
A47: 46189 | B47: 200.51 | C47: 225.64 | D47: 199.98 | E47: 211.39 | F47: 211.39 | G47: 195401600 | I47: 46189 | J47: 35.26 | K47: 35.42 | L47: 34.7 | M47: 34.75 | N47: 34.75 | O47: 2791700
A48: 46190 | B48: 209.84 | C48: 213.8 | D48: 187.01 | E48: 191.82 | F48: 191.82 | G48: 201719500 | I48: 46190 | J48: 34.93 | K48: 35.34 | L48: 34.45 | M48: 34.51 | N48: 34.51 | O48: 4033400
A49: 46191 | B49: 188.39 | C49: 190 | D49: 172.11 | E49: 185 | F49: 185 | G49: 272126800 | I49: 46191 | J49: 34.94 | K49: 34.94 | L49: 33.9 | M49: 34.56 | N49: 34.56 | O49: 2650100
A50: 46195 | B50: 176.04 | C50: 176.75 | D50: 154 | E50: 154.6 | F50: 154.6 | G50: 169183800 | I50: 46195 | J50: 34.17 | K50: 34.17 | L50: 33.24 | M50: 33.36 | N50: 33.36 | O50: 1909700
A51: 46196 | B51: 151.06 | C51: 165.5 | D51: 147.11 | E51: 156.11 | F51: 156.11 | G51: 155848100 | I51: 46196 | J51: 32.52 | K51: 33.31 | L51: 32.51 | M51: 32.8 | N51: 32.8 | O51: 1659400
A52: 46197 | B52: 154.2 | C52: 159.86 | D52: 150.72 | E52: 154.54 | F52: 154.54 | G52: 76101500 | I52: 46197 | J52: 32.67 | K52: 32.85 | L52: 32.14 | M52: 32.18 | N52: 32.18 | O52: 1978900
A53: 46198 | B53: 156.63 | C53: 160.65 | D53: 150 | E53: 153 | F53: 153 | G53: 62212400 | I53: 46198 | J53: 32.36 | K53: 32.45 | L53: 31.58 | M53: 31.92 | N53: 31.92 | O53: 1191400
A54: 46199 | B54: 150.62 | C54: 158.4 | D54: 148.51 | E54: 153.23 | F54: 153.23 | G54: 126932900 | I54: 46199 | J54: 31.6 | K54: 32.43 | L54: 31.6 | M54: 31.93 | N54: 31.93 | O54: 932500
A55: 46202 | B55: 157.36 | C55: 166.17 | D55: 151.74 | E55: 164.19 | F55: 164.19 | G55: 81443100 | I55: 46202 | J55: 32.66 | K55: 33.18 | L55: 32.26 | M55: 33.13 | N55: 33.13 | O55: 914600
A56: 46203 | B56: 163.38 | C56: 172.4 | D56: 161.64 | E56: 170.86 | F56: 170.86 | G56: 82047500 | I56: 46203 | J56: 33.59 | K56: 34.17 | L56: 33.5 | M56: 34.12 | N56: 34.12 | O56: 1436200
... A73: 46230 | B73: 113.43 | C73: 114.83 | D73: 108.66 | E73: 113.5 | F73: 113.5 | G73: 63388545 | I73: 46230 | J73: 30.66 | K73: 30.9 | L73: 30.1 | M73: 30.72 | N73: 30.72 | O73: 580595

Sheet 18 Social Security
B2: Inputs | E2: Claiming Scenarios
B3: Birth Year | C3: 1975 | E3: Metric | F3: Age 62 | G3: Age 67 (FRA) | H3: Age 70
B4: Full Retirement Age (FRA) | C4: 67 | E4: Monthly Benefit | F4: =C5*0.7 -> 2100 | G4: =C5 -> 3000 | H4: =C5*1.24 -> 3720
B5: Estimated Monthly Benefit (PIA) | C5: 3000 | E5: Annual Benefit | F5: =F4*12 -> 25200 | G5: =G4*12 -> 36000 | H5: =H4*12 -> 44640
B8: Break-Even Analysis
B9: Age | C9: Claim at 62 | D9: Claim at 67 | E9: Claim at 70 | F9: Optimal Strategy
B10: 62 | C10: =IF($B10>=62, $F$5 * ($B10 - 61), 0) -> 25200 | D10: =IF($B10>=67, $G$5 * ($B10 - 66), 0) -> 0 | E10: =IF($B10>=70, $H$5 * ($B10 - 69), 0) -> 0 | F10: =IF(MAX(C10:E10)=0, "", INDEX($C$9:$E$9, 1, MATCH(MAX(C10:E10), C10:E10, 0))) -> Claim at 62
B11: 63 | C11: =IF($B11>=62, $F$5 * ($B11 - 61), 0) -> 50400 | D11: =IF($B11>=67, $G$5 * ($B11 - 66), 0) -> 0 | E11: =IF($B11>=70, $H$5 * ($B11 - 69), 0) -> 0 | F11: =IF(MAX(C11:E11)=0, "", INDEX($C$9:$E$9, 1, MATCH(MAX(C11:E11), C11:E11, 0))) -> Claim at 62
B12: 64 | C12: =IF($B12>=62, $F$5 * ($B12 - 61), 0) -> 75600 | D12: =IF($B12>=67, $G$5 * ($B12 - 66), 0) -> 0 | E12: =IF($B12>=70, $H$5 * ($B12 - 69), 0) -> 0 | F12: =IF(MAX(C12:E12)=0, "", INDEX($C$9:$E$9, 1, MATCH(MAX(C12:E12), C12:E12, 0))) -> Claim at 62
B13: 65 | C13: =IF($B13>=62, $F$5 * ($B13 - 61), 0) -> 100800 | D13: =IF($B13>=67, $G$5 * ($B13 - 66), 0) -> 0 | E13: =IF($B13>=70, $H$5 * ($B13 - 69), 0) -> 0 | F13: =IF(MAX(C13:E13)=0, "", INDEX($C$9:$E$9, 1, MATCH(MAX(C13:E13), C13:E13, 0))) -> Claim at 62
B14: 66 | C14: =IF($B14>=62, $F$5 * ($B14 - 61), 0) -> 126000 | D14: =IF($B14>=67, $G$5 * ($B14 - 66), 0) -> 0 | E14: =IF($B14>=70, $H$5 * ($B14 - 69), 0) -> 0 | F14: =IF(MAX(C14:E14)=0, "", INDEX($C$9:$E$9, 1, MATCH(MAX(C14:E14), C14:E14, 0))) -> Claim at 62
B15: 67 | C15: =IF($B15>=62, $F$5 * ($B15 - 61), 0) -> 151200 | D15: =IF($B15>=67, $G$5 * ($B15 - 66), 0) -> 36000 | E15: =IF($B15>=70, $H$5 * ($B15 - 69), 0) -> 0 | F15: =IF(MAX(C15:E15)=0, "", INDEX($C$9:$E$9, 1, MATCH(MAX(C15:E15), C15:E15, 0))) -> Claim at 62
B16: 68 | C16: =IF($B16>=62, $F$5 * ($B16 - 61), 0) -> 176400 | D16: =IF($B16>=67, $G$5 * ($B16 - 66), 0) -> 72000 | E16: =IF($B16>=70, $H$5 * ($B16 - 69), 0) -> 0 | F16: =IF(MAX(C16:E16)=0, "", INDEX($C$9:$E$9, 1, MATCH(MAX(C16:E16), C16:E16, 0))) -> Claim at 62
B17: 69 | C17: =IF($B17>=62, $F$5 * ($B17 - 61), 0) -> 201600 | D17: =IF($B17>=67, $G$5 * ($B17 - 66), 0) -> 108000 | E17: =IF($B17>=70, $H$5 * ($B17 - 69), 0) -> 0 | F17: =IF(MAX(C17:E17)=0, "", INDEX($C$9:$E$9, 1, MATCH(MAX(C17:E17), C17:E17, 0))) -> Claim at 62
B18: 70 | C18: =IF($B18>=62, $F$5 * ($B18 - 61), 0) -> 226800 | D18: =IF($B18>=67, $G$5 * ($B18 - 66), 0) -> 144000 | E18: =IF($B18>=70, $H$5 * ($B18 - 69), 0) -> 44640 | F18: =IF(MAX(C18:E18)=0, "", INDEX($C$9:$E$9, 1, MATCH(MAX(C18:E18), C18:E18, 0))) -> Claim at 62
B19: 71 | C19: =IF($B19>=62, $F$5 * ($B19 - 61), 0) -> 252000 | D19: =IF($B19>=67, $G$5 * ($B19 - 66), 0) -> 180000 | E19: =IF($B19>=70, $H$5 * ($B19 - 69), 0) -> 89280 | F19: =IF(MAX(C19:E19)=0, "", INDEX($C$9:$E$9, 1, MATCH(MAX(C19:E19), C19:E19, 0))) -> Claim at 62
B20: 72 | C20: =IF($B20>=62, $F$5 * ($B20 - 61), 0) -> 277200 | D20: =IF($B20>=67, $G$5 * ($B20 - 66), 0) -> 216000 | E20: =IF($B20>=70, $H$5 * ($B20 - 69), 0) -> 133920 | F20: =IF(MAX(C20:E20)=0, "", INDEX($C$9:$E$9, 1, MATCH(MAX(C20:E20), C20:E20, 0))) -> Claim at 62
B21: 73 | C21: =IF($B21>=62, $F$5 * ($B21 - 61), 0) -> 302400 | D21: =IF($B21>=67, $G$5 * ($B21 - 66), 0) -> 252000 | E21: =IF($B21>=70, $H$5 * ($B21 - 69), 0) -> 178560 | F21: =IF(MAX(C21:E21)=0, "", INDEX($C$9:$E$9, 1, MATCH(MAX(C21:E21), C21:E21, 0))) -> Claim at 62
... B43: 95 | C43: =IF($B43>=62, $F$5 * ($B43 - 61), 0) -> 856800 | D43: =IF($B43>=67, $G$5 * ($B43 - 66), 0) -> 1044000 | E43: =IF($B43>=70, $H$5 * ($B43 - 69), 0) -> 1160640 | F43: =IF(MAX(C43:E43)=0, "", INDEX($C$9:$E$9, 1, MATCH(MAX(C43:E43), C43:E43, 0))) -> Claim at 70

Sheet Calc_Data
A1: Starting Balance | B1: ='Retirement Projection'!L2 -> 2874574.7
A2: Projected Final Balance | B2: {=INDEX('Retirement Projection'!L2:L1000, COUNTA('Retirement Projection'!A2:A1000))} -> -33872379
A3: Average Annual Expenses | B3: =AVERAGE('Retirement Projection'!F2:F1000) -> 318191.18
